Workbook

Sheet GUÍA
A1: CONSOLA DEL REPRESENTANTE ENCARGADO DE CUMPLIMIENTO · Actividades Vulnerables
A2: Herramienta de trabajo diario para quien cumple la LFPIORPI. Actualizada con la Ley (DOF 16-jul-2025), el Reglamento (DOF 27-mar-2026) y las Reglas de Carácter General con el Acuerdo 115/2026 (DOF 7-ago-2026). GMC360 · 360educa.
A4: 1. PRIMERA VEZ (15 minutos)
A5: 1) CONFIG: revisa la tabla de UMA por año y captura el nombre del sujeto obligado, el RFC y el nombre de la persona Representante Encargada de Cumplimiento.
A6: 2) CLIENTES: borra el renglón EJEMPLO-01 y da de alta a tus clientes con sus factores de riesgo, su perfil transaccional y las fechas del expediente.
A7: 3) OPERACIONES: borra el renglón de ejemplo y empieza a registrar operaciones en orden de fecha.
A9: 2. LA RUTINA DEL REC
A10: CADA DÍA
A11: • Registra cada operación en OPERACIONES (fecha, cliente, actividad, monto, efectivo). El motor te dice si identificas, si acumula, si ya hay Aviso y su fecha límite, y si el efectivo está prohibido.
A12: • Lee la columna ALERTAS: exceso de perfil, tercero que paga, cliente de riesgo alto (debida diligencia reforzada), PEP, efectivo prohibido.
A13: • Si algo te huele mal, regístralo en AVISOS_24H en ese momento: el reloj de 24 horas empieza a correr.
A14: • ¿Duda rápida antes de cerrar una venta? Hoja CONSULTA.
... A58: Fuentes: LFPIORPI (DOF 16-jul-2025) · Reglamento (DOF 27-mar-2026) · RCG, Acuerdo 115/2026 (DOF 7-ago-2026) · UMA INEGI (DOF 9-ene-2026). Material de apoyo; no constituye asesoría legal específica.

Sheet TABLERO
A1: TABLERO DEL REPRESENTANTE DE CUMPLIMIENTO
A2: ="Corte: "&DAY(CONFIG!$B$6)&"/"&MONTH(CONFIG!$B$6)&"/"&YEAR(CONFIG!$B$6)&" · "&IF(CONFIG!$B$7="","(captura tus datos en CONFIG)",CONFIG!$B$7&" · REC: "&CONFIG!$B$9) -> Corte: 21/9/2026 · (captura tus datos en CONFIG)
A4: AVISOS Y OPERACIONES | D4: CLIENTES | G4: AVISOS DE 24 HORAS Y RCG
A5: Operaciones del mes en curso | B5: =COUNTIFS(OPERACIONES!$B$6:$B$505,">="&DATE(YEAR(CONFIG!$B$6),MONTH(CONFIG!$B$6),1),OPERACIONES!$B$6:$B$505,"<"&EDATE(DATE(YEAR(CONFIG!$B$6),MONTH(CONFIG!$B$6),1),1)) -> 0 | D5: Clientes registrados | E5: =COUNTA(CLIENTES!$A$6:$A$305) -> 1 | G5: Registros de 24 h pendientes | H5: =COUNTIF(AVISOS_24H!$J$6:$J$105,"Pendiente") -> 0
A6: Monto operado en el mes | B6: =SUMIFS(OPERACIONES!$E$6:$E$505,OPERACIONES!$B$6:$B$505,">="&DATE(YEAR(CONFIG!$B$6),MONTH(CONFIG!$B$6),1),OPERACIONES!$B$6:$B$505,"<"&EDATE(DATE(YEAR(CONFIG!$B$6),MONTH(CONFIG!$B$6),1),1)) -> 0 | D6: Grado ALTO | E6: =COUNTIF(CLIENTES!$Z$6:$Z$305,"Alto") -> 0 | G6: Registros de 24 h VENCIDOS | H6: =COUNTIF(AVISOS_24H!$L$6:$L$105,"VENCIDO") -> 0
A7: Avisos pendientes de presentar | B7: =COUNTIFS(OPERACIONES!$P$6:$P$505,"AVISO*",OPERACIONES!$T$6:$T$505,"<>Presentado") -> 0 | D7: Grado MEDIO | E7: =COUNTIF(CLIENTES!$Z$6:$Z$305,"Medio") -> 1 | G7: Avance obligaciones RCG | H7: =OBLIGACIONES!$B$3 -> 0
A8: Avisos VENCIDOS | B8: =COUNTIF(OPERACIONES!$V$6:$V$505,"VENCIDO") -> 0 | D8: Grado BAJO | E8: =COUNTIF(CLIENTES!$Z$6:$Z$305,"Bajo") -> 0 | G8: Días al 1-mar-2027 (evaluación de riesgo) | H8: =MAX(0,DATE(2027,3,1)-CONFIG!$B$6) -> 161
A9: Próximo vencimiento de Aviso | B9: =IF(MIN(OPERACIONES!$AT$6:$AT$505)=0,"—",MIN(OPERACIONES!$AT$6:$AT$505)) -> — | D9: PEP (nacionales y extranjeras) | E9: =COUNTIF(CLIENTES!$H$6:$H$305,"Nacional")+COUNTIF(CLIENTES!$H$6:$H$305,"Extranjera") -> 0 | G9: Días al 1-jun-2027 (mecanismos automatizados) | H9: =MAX(0,DATE(2027,6,1)-CONFIG!$B$6) -> 253
A10: Operaciones con efectivo prohibido (Art. 32) | B10: =COUNTIF(OPERACIONES!$R$6:$R$505,"PROHIBIDO") -> 0 | D10: Clientes con pendientes | E10: =COUNTIF(CLIENTES!$AE$6:$AE$305,"Revisar") -> 1
A11: Operaciones que exceden el perfil | B11: =SUM(OPERACIONES!$AQ$6:$AQ$505) -> 0 | D11: Evaluaciones de riesgo vencidas | E11: =COUNTIF(CLIENTES!$AB$6:$AB$305,"<"&CONFIG!$B$6) -> 1
A12: Operaciones pagadas por un tercero | B12: =COUNTIF(OPERACIONES!$H$6:$H$505,"Sí") -> 0 | D12: Expedientes incompletos | E12: =COUNTIF(CLIENTES!$P$6:$P$305,"No") -> 0
A13: Meses con Avisos o informe VENCIDO | B13: =COUNTIF(CALENDARIO!$K$6:$K$17,"VENCIDO") -> 8 | D13: Beneficiario Controlador pendiente | E13: =COUNTIF(CLIENTES!$Q$6:$Q$305,"Pendiente") -> 0
A15: Cómo leerlo: todo lo que aparece en rojo es un pendiente. Ve a la hoja indicada y filtra por la columna de semáforo o alertas.
G16: Grado | H16: Clientes
G17: Bajo | H17: =E8 -> 0
G18: Medio | H18: =E7 -> 1
G19: Alto | H19: =E6 -> 0

Sheet OPERACIONES
A1: OPERACIONES — Bitácora y motor de identificación, acumulación y Aviso
A2: Un renglón por operación, de TODOS los clientes, en orden de fecha. El motor acumula por cliente y por actividad (Art. 7 del Reglamento y RCG 19): sólo suma las operaciones que por sí solas alcanzan el umbral de identificación, en periodos de hasta 6 meses desde la primera. Captura lo amarillo; el renglón 6 es un EJEMPLO, bórralo.
A5: Folio | B5: Fecha | C5: ID cliente | D5: Actividad (Fr. - Actividad) | E5: Monto SIN IVA ni accesorios | F5: Pagado en efectivo (CON IVA y accesorios) | G5: Instrumento de pago | H5: ¿Paga un tercero? | I5: Cliente | J5: Grado del cliente | K5: ¿Identificar? | L5: Acumulación | M5: ¿Cuenta para acumular? | N5: Inicio del periodo | O5: Acumulado del periodo | P5: AVISO | Q5: Fecha límite del Aviso | R5: Efectivo (Art. 32) | S5: Alertas | T5: Estatus del Aviso | U5: Fecha en que se presentó | V5: Semáforo del Aviso | W5: Cifra a reportar en el Aviso (total CON IVA) | X5: Observaciones | AA5: aux categoría | AB5: aux id UMA | AC5: aux id $ | AD5: aux aviso UMA | AE5: aux aviso $ | AF5: aux art32 UMA | AG5: aux art32 $ | AH5: aux llave | AI5: aux fila previa | AJ5: aux inicio | AK5: aux acumulado | AL5: aux periodo nuevo | AM5: aux índice cat | AN5: aux periodo abierto | AO5: aux monto mes cliente | AP5: aux perfil | AQ5: aux excede | AR5: aux orden | AS5: aux PEP | AT5: aux vence | AU5: aux Aviso inciso a) | AV5: aux UMA de la fecha | AW5: aux suma 24 h juegos | AX5: aux estatus
A6: =IF(E6="","",ROW()-5) -> 1 | B6: 46086 | C6: EJEMPLO-01 | D6: VI - Piedras y metales preciosos, joyas | E6: 120000 | F6: 0 | G6: Transferencia | H6: No | I6: =IF(C6="","",IFERROR(INDEX(CLIENTES!$B$6:$B$305,MATCH(C6,CLIENTES!$A$6:$A$305,0)),"⚠ ID no registrado")) -> Comercializadora Ejemplo, S.A. de C.V. | J6: =IF(C6="","",IFERROR(INDEX(CLIENTES!$Z$6:$Z$305,MATCH(C6,CLIENTES!$A$6:$A$305,0)),"")) -> Medio | K6: =IF(E6="","",IF(AB6="Siempre","Sí",IF(ISNUMBER(AC6),IF(E6>=AC6,"Sí",IF(AW6>=AC6,"Sí (serie 24 h)","No")),""))) -> Sí | L6: =IF(E6="","",AA6) -> ACUMULA | M6: =IF(E6="","",IF(AA6<>"ACUMULA","No aplica",IF(LEFT(K6,2)="Sí","Sí","No"))) -> Sí | N6: =IF(M6="Sí",AJ6,"") -> 46086 | O6: =IF(M6="Sí",AK6,"") -> 120000 | P6: =IF(AND(LEFT(D6,6)="XIV - ",LEFT(AX6,5)="AVISO"),"Pedimento (R 16): no va al SPPLD",AX6) -> Acumulando | Q6: =IF(LEFT(P6,5)="AVISO",IF(ISNUMBER(B6),DATE(YEAR(B6),MONTH(B6)+1,17),"Falta fecha"),"") | R6: =IF(OR(F6="",F6=0),"",IF(ISNUMBER(AG6),IF(F6>=AG6,"PROHIBIDO","Dentro del límite"),"No aplica")) | S6: =IF(E6="","",MID(IF(AQ6=1," · Excede el perfil declarado","")&IF(H6="Sí"," · Paga un tercero","")&IF(J6="Alto"," · Cliente de riesgo alto: DDR (RCG 23 Ter 3 y 4)","")&IF(AND(AS6<>"",AS6<>"No",AS6<>0)," · PEP","")&IF(R6="PROHIBIDO"," · Efectivo prohibido: no lo recibas (Art. 32)","")&IF(AR6=1," · ⚠ Fecha fuera de orden","")&IF(LEFT(I6,1)="⚠"," · ⚠ Cliente no registrado","")&IF(D6=""," · ⚠ Falta la actividad","")&IF(AND(LEFT(P6,5)="AVISO",W6="")," · Captura la cifra total con IVA para el Aviso","")&IF(AND(ISNUMBER(W6),W6<E6)," · ⚠ La cifra con IVA es menor que el monto sin IVA",""),4,400)) | V6: =IF(LEFT(P6,5)<>"AVISO","",IF(T6="Presentado",IF(AND(ISNUMBER(U6),ISNUMBER(Q6),U6>Q6),"Presentado tarde","Presentado"),IF(NOT(ISNUMBER(Q6)),"Falta fecha",IF(Q6<CONFIG!$B$6,"VENCIDO","Vence en "&(Q6-CONFIG!$B$6)&" días")))) | AA6: =IF(AM6="","",INDEX(CATÁLOGO!$D$5:$D$39,AM6)) -> ACUMULA | AB6: =IF(AM6="","",INDEX(CATÁLOGO!$E$5:$E$39,AM6)) -> 805 | AC6: =IF(AB6="","",IF(ISNUMBER(AB6),AB6*AV6,AB6)) -> 94434.55 | AD6: =IF(AM6="","",INDEX(CATÁLOGO!$F$5:$F$39,AM6)) -> 1605 | AE6: =IF(AD6="","",IF(ISNUMBER(AD6),AD6*AV6,AD6)) -> 188282.55 | AF6: =IF(AM6="","",INDEX(CATÁLOGO!$G$5:$G$39,AM6)) -> 3210 | AG6: =IF(AF6="","",IF(ISNUMBER(AF6),AF6*AV6,AF6)) -> 376565.1 | AH6: =IF(E6="","",C6&"|"&D6) -> EJEMPLO-01|VI - Piedras y metales preciosos, joyas | AI6: =IF(M6<>"Sí",0,SUMPRODUCT(MAX(($AH$5:AH5=AH6)*($M$5:M5="Sí")*ROW($AH$5:AH5)))) -> 0 | AJ6: =IF(M6<>"Sí","",IF(AL6=1,B6,INDEX($AJ:$AJ,AI6))) -> 46086 | AK6: =IF(M6<>"Sí","",IF(AL6=1,E6,INDEX($AK:$AK,AI6)+E6)) -> 120000 | AL6: =IF(M6<>"Sí","",IF(AI6=0,1,IF(INDEX($AN:$AN,AI6)=0,1,IF(B6>=EDATE(INDEX($AJ:$AJ,AI6),6),1,0)))) -> 1 | AM6: =IF(D6="","",IFERROR(MATCH(D6,CATÁLOGO!$C$5:$C$39,0),"")) -> 8 | AN6: =IF(M6<>"Sí","",IF(AND(ISNUMBER(AE6),AK6>=AE6),0,1)) -> 1 | AO6: =IF(OR(E6="",C6="",NOT(ISNUMBER(B6))),"",SUMIFS($E$6:$E$505,$C$6:$C$505,C6,$B$6:$B$505,">="&DATE(YEAR(B6),MONTH(B6),1),$B$6:$B$505,"<"&DATE(YEAR(B6),MONTH(B6)+1,1))) -> 120000 | AP6: =IF(C6="","",IFERROR(INDEX(CLIENTES!$M$6:$M$305,MATCH(C6,CLIENTES!$A$6:$A$305,0)),"")) -> 250000 | AQ6: =IF(AND(ISNUMBER(AO6),ISNUMBER(AP6)),IF(AND(AP6>0,AO6>AP6),1,0),0) -> 0 | AR6: =IF(NOT(ISNUMBER(B6)),0,IF(B6<MAX($B$5:B5),1,0)) -> 0 | AS6: =IF(C6="","",IFERROR(INDEX(CLIENTES!$H$6:$H$305,MATCH(C6,CLIENTES!$A$6:$A$305,0)),"")) -> No | AT6: =IF(AND(LEFT(P6,5)="AVISO",T6<>"Presentado",ISNUMBER(Q6)),Q6,"") | AU6: =IF(AND(D6="XVI - Activos virtuales (PSAV): operación de intercambio/transferencia",M6="Sí",ISNUMBER(AE6)),IF(AK6>=AE6,1,0),0) -> 0 | AV6: =IF(NOT(ISNUMBER(B6)),CONFIG!$B$4,IFERROR(INDEX(CONFIG!$I$5:$I$14,MATCH(IF(MONTH(B6)=1,YEAR(B6)-1,YEAR(B6)),CONFIG!$H$5:$H$14,0)),CONFIG!$B$4)) -> 117.31 | AW6: =IF(AND(LEFT(D6,4)="I - ",ISNUMBER(B6),C6<>""),SUMIFS($E$6:$E$505,$C$6:$C$505,C6,$D$6:$D$505,D6,$B$6:$B$505,">"&(B6-1),$B$6:$B$505,"<="&B6),0) -> 0 | AX6: =IF(E6="","",IF(AD6="Siempre","AVISO (siempre)",IF(AD6="No aplica","Sin Aviso (sólo preparas: Ley 17 XI)",IF(NOT(ISNUMBER(AE6)),"",IF(AA6<>"ACUMULA",IF(E6>=AE6,IF(AND(D6="XVI - Activos virtuales (PSAV): cobro de contraprestación (comisión) por el servicio",COUNTIFS($C$6:$C$505,C6,$B$6:$B$505,">="&INT(B6),$B$6:$B$505,"<"&(INT(B6)+1),$AU$6:$AU$505,1)>0),"En el Aviso del inciso a) (R 31 Bis)","AVISO"),"—"),IF(M6<>"Sí","—",IF(AK6>=AE6,IF(AK6=E6,"AVISO","AVISO (acumulado)"),"Acumulando"))))))) -> Acumulando
A7: =IF(E7="","",ROW()-5) | I7: =IF(C7="","",IFERROR(INDEX(CLIENTES!$B$6:$B$305,MATCH(C7,CLIENTES!$A$6:$A$305,0)),"⚠ ID no registrado")) | J7: =IF(C7="","",IFERROR(INDEX(CLIENTES!$Z$6:$Z$305,MATCH(C7,CLIENTES!$A$6:$A$305,0)),"")) | K7: =IF(E7="","",IF(AB7="Siempre","Sí",IF(ISNUMBER(AC7),IF(E7>=AC7,"Sí",IF(AW7>=AC7,"Sí (serie 24 h)","No")),""))) | L7: =IF(E7="","",AA7) | M7: =IF(E7="","",IF(AA7<>"ACUMULA","No aplica",IF(LEFT(K7,2)="Sí","Sí","No"))) | N7: =IF(M7="Sí",AJ7,"") | O7: =IF(M7="Sí",AK7,"") | P7: =IF(AND(LEFT(D7,6)="XIV - ",LEFT(AX7,5)="AVISO"),"Pedimento (R 16): no va al SPPLD",AX7) | Q7: =IF(LEFT(P7,5)="AVISO",IF(ISNUMBER(B7),DATE(YEAR(B7),MONTH(B7)+1,17),"Falta fecha"),"") | R7: =IF(OR(F7="",F7=0),"",IF(ISNUMBER(AG7),IF(F7>=AG7,"PROHIBIDO","Dentro del límite"),"No aplica")) | S7: =IF(E7="","",MID(IF(AQ7=1," · Excede el perfil declarado","")&IF(H7="Sí"," · Paga un tercero","")&IF(J7="Alto"," · Cliente de riesgo alto: DDR (RCG 23 Ter 3 y 4)","")&IF(AND(AS7<>"",AS7<>"No",AS7<>0)," · PEP","")&IF(R7="PROHIBIDO"," · Efectivo prohibido: no lo recibas (Art. 32)","")&IF(AR7=1," · ⚠ Fecha fuera de orden","")&IF(LEFT(I7,1)="⚠"," · ⚠ Cliente no registrado","")&IF(D7=""," · ⚠ Falta la actividad","")&IF(AND(LEFT(P7,5)="AVISO",W7="")," · Captura la cifra total con IVA para el Aviso","")&IF(AND(ISNUMBER(W7),W7<E7)," · ⚠ La cifra con IVA es menor que el monto sin IVA",""),4,400)) | V7: =IF(LEFT(P7,5)<>"AVISO","",IF(T7="Presentado",IF(AND(ISNUMBER(U7),ISNUMBER(Q7),U7>Q7),"Presentado tarde","Presentado"),IF(NOT(ISNUMBER(Q7)),"Falta fecha",IF(Q7<CONFIG!$B$6,"VENCIDO","Vence en "&(Q7-CONFIG!$B$6)&" días")))) | AA7: =IF(AM7="","",INDEX(CATÁLOGO!$D$5:$D$39,AM7)) | AB7: =IF(AM7="","",INDEX(CATÁLOGO!$E$5:$E$39,AM7)) | AC7: =IF(AB7="","",IF(ISNUMBER(AB7),AB7*AV7,AB7)) | AD7: =IF(AM7="","",INDEX(CATÁLOGO!$F$5:$F$39,AM7)) | AE7: =IF(AD7="","",IF(ISNUMBER(AD7),AD7*AV7,AD7)) | AF7: =IF(AM7="","",INDEX(CATÁLOGO!$G$5:$G$39,AM7)) | AG7: =IF(AF7="","",IF(ISNUMBER(AF7),AF7*AV7,AF7)) | AH7: =IF(E7="","",C7&"|"&D7) | AI7: =IF(M7<>"Sí",0,SUMPRODUCT(MAX(($AH$5:AH6=AH7)*($M$5:M6="Sí")*ROW($AH$5:AH6)))) -> 0 | AJ7: =IF(M7<>"Sí","",IF(AL7=1,B7,INDEX($AJ:$AJ,AI7))) | AK7: =IF(M7<>"Sí","",IF(AL7=1,E7,INDEX($AK:$AK,AI7)+E7)) | AL7: =IF(M7<>"Sí","",IF(AI7=0,1,IF(INDEX($AN:$AN,AI7)=0,1,IF(B7>=EDATE(INDEX($AJ:$AJ,AI7),6),1,0)))) | AM7: =IF(D7="","",IFERROR(MATCH(D7,CATÁLOGO!$C$5:$C$39,0),"")) | AN7: =IF(M7<>"Sí","",IF(AND(ISNUMBER(AE7),AK7>=AE7),0,1)) | AO7: =IF(OR(E7="",C7="",NOT(ISNUMBER(B7))),"",SUMIFS($E$6:$E$505,$C$6:$C$505,C7,$B$6:$B$505,">="&DATE(YEAR(B7),MONTH(B7),1),$B$6:$B$505,"<"&DATE(YEAR(B7),MONTH(B7)+1,1))) | AP7: =IF(C7="","",IFERROR(INDEX(CLIENTES!$M$6:$M$305,MATCH(C7,CLIENTES!$A$6:$A$305,0)),"")) | AQ7: =IF(AND(ISNUMBER(AO7),ISNUMBER(AP7)),IF(AND(AP7>0,AO7>AP7),1,0),0) -> 0 | AR7: =IF(NOT(ISNUMBER(B7)),0,IF(B7<MAX($B$5:B6),1,0)) -> 0 | AS7: =IF(C7="","",IFERROR(INDEX(CLIENTES!$H$6:$H$305,MATCH(C7,CLIENTES!$A$6:$A$305,0)),"")) | AT7: =IF(AND(LEFT(P7,5)="AVISO",T7<>"Presentado",ISNUMBER(Q7)),Q7,"") | AU7: =IF(AND(D7="XVI - Activos virtuales (PSAV): operación de intercambio/transferencia",M7="Sí",ISNUMBER(AE7)),IF(AK7>=AE7,1,0),0) -> 0 | AV7: =IF(NOT(ISNUMBER(B7)),CONFIG!$B$4,IFERROR(INDEX(CONFIG!$I$5:$I$14,MATCH(IF(MONTH(B7)=1,YEAR(B7)-1,YEAR(B7)),CONFIG!$H$5:$H$14,0)),CONFIG!$B$4)) -> 117.31 | AW7: =IF(AND(LEFT(D7,4)="I - ",ISNUMBER(B7),C7<>""),SUMIFS($E$6:$E$505,$C$6:$C$505,C7,$D$6:$D$505,D7,$B$6:$B$505,">"&(B7-1),$B$6:$B$505,"<="&B7),0) -> 0 | AX7: =IF(E7="","",IF(AD7="Siempre","AVISO (siempre)",IF(AD7="No aplica","Sin Aviso (sólo preparas: Ley 17 XI)",IF(NOT(ISNUMBER(AE7)),"",IF(AA7<>"ACUMULA",IF(E7>=AE7,IF(AND(D7="XVI - Activos virtuales (PSAV): cobro de contraprestación (comisión) por el servicio",COUNTIFS($C$6:$C$505,C7,$B$6:$B$505,">="&INT(B7),$B$6:$B$505,"<"&(INT(B7)+1),$AU$6:$AU$505,1)>0),"En el Aviso del inciso a) (R 31 Bis)","AVISO"),"—"),IF(M7<>"Sí","—",IF(AK7>=AE7,IF(AK7=E7,"AVISO","AVISO (acumulado)"),"Acumulando")))))))
A8: =IF(E8="","",ROW()-5) | I8: =IF(C8="","",IFERROR(INDEX(CLIENTES!$B$6:$B$305,MATCH(C8,CLIENTES!$A$6:$A$305,0)),"⚠ ID no registrado")) | J8: =IF(C8="","",IFERROR(INDEX(CLIENTES!$Z$6:$Z$305,MATCH(C8,CLIENTES!$A$6:$A$305,0)),"")) | K8: =IF(E8="","",IF(AB8="Siempre","Sí",IF(ISNUMBER(AC8),IF(E8>=AC8,"Sí",IF(AW8>=AC8,"Sí (serie 24 h)","No")),""))) | L8: =IF(E8="","",AA8) | M8: =IF(E8="","",IF(AA8<>"ACUMULA","No aplica",IF(LEFT(K8,2)="Sí","Sí","No"))) | N8: =IF(M8="Sí",AJ8,"") | O8: =IF(M8="Sí",AK8,"") | P8: =IF(AND(LEFT(D8,6)="XIV - ",LEFT(AX8,5)="AVISO"),"Pedimento (R 16): no va al SPPLD",AX8) | Q8: =IF(LEFT(P8,5)="AVISO",IF(ISNUMBER(B8),DATE(YEAR(B8),MONTH(B8)+1,17),"Falta fecha"),"") | R8: =IF(OR(F8="",F8=0),"",IF(ISNUMBER(AG8),IF(F8>=AG8,"PROHIBIDO","Dentro del límite"),"No aplica")) | S8: =IF(E8="","",MID(IF(AQ8=1," · Excede el perfil declarado","")&IF(H8="Sí"," · Paga un tercero","")&IF(J8="Alto"," · Cliente de riesgo alto: DDR (RCG 23 Ter 3 y 4)","")&IF(AND(AS8<>"",AS8<>"No",AS8<>0)," · PEP","")&IF(R8="PROHIBIDO"," · Efectivo prohibido: no lo recibas (Art. 32)","")&IF(AR8=1," · ⚠ Fecha fuera de orden","")&IF(LEFT(I8,1)="⚠"," · ⚠ Cliente no registrado","")&IF(D8=""," · ⚠ Falta la actividad","")&IF(AND(LEFT(P8,5)="AVISO",W8="")," · Captura la cifra total con IVA para el Aviso","")&IF(AND(ISNUMBER(W8),W8<E8)," · ⚠ La cifra con IVA es menor que el monto sin IVA",""),4,400)) | V8: =IF(LEFT(P8,5)<>"AVISO","",IF(T8="Presentado",IF(AND(ISNUMBER(U8),ISNUMBER(Q8),U8>Q8),"Presentado tarde","Presentado"),IF(NOT(ISNUMBER(Q8)),"Falta fecha",IF(Q8<CONFIG!$B$6,"VENCIDO","Vence en "&(Q8-CONFIG!$B$6)&" días")))) | AA8: =IF(AM8="","",INDEX(CATÁLOGO!$D$5:$D$39,AM8)) | AB8: =IF(AM8="","",INDEX(CATÁLOGO!$E$5:$E$39,AM8)) | AC8: =IF(AB8="","",IF(ISNUMBER(AB8),AB8*AV8,AB8)) | AD8: =IF(AM8="","",INDEX(CATÁLOGO!$F$5:$F$39,AM8)) | AE8: =IF(AD8="","",IF(ISNUMBER(AD8),AD8*AV8,AD8)) | AF8: =IF(AM8="","",INDEX(CATÁLOGO!$G$5:$G$39,AM8)) | AG8: =IF(AF8="","",IF(ISNUMBER(AF8),AF8*AV8,AF8)) | AH8: =IF(E8="","",C8&"|"&D8) | AI8: =IF(M8<>"Sí",0,SUMPRODUCT(MAX(($AH$5:AH7=AH8)*($M$5:M7="Sí")*ROW($AH$5:AH7)))) -> 0 | AJ8: =IF(M8<>"Sí","",IF(AL8=1,B8,INDEX($AJ:$AJ,AI8))) | AK8: =IF(M8<>"Sí","",IF(AL8=1,E8,INDEX($AK:$AK,AI8)+E8)) | AL8: =IF(M8<>"Sí","",IF(AI8=0,1,IF(INDEX($AN:$AN,AI8)=0,1,IF(B8>=EDATE(INDEX($AJ:$AJ,AI8),6),1,0)))) | AM8: =IF(D8="","",IFERROR(MATCH(D8,CATÁLOGO!$C$5:$C$39,0),"")) | AN8: =IF(M8<>"Sí","",IF(AND(ISNUMBER(AE8),AK8>=AE8),0,1)) | AO8: =IF(OR(E8="",C8="",NOT(ISNUMBER(B8))),"",SUMIFS($E$6:$E$505,$C$6:$C$505,C8,$B$6:$B$505,">="&DATE(YEAR(B8),MONTH(B8),1),$B$6:$B$505,"<"&DATE(YEAR(B8),MONTH(B8)+1,1))) | AP8: =IF(C8="","",IFERROR(INDEX(CLIENTES!$M$6:$M$305,MATCH(C8,CLIENTES!$A$6:$A$305,0)),"")) | AQ8: =IF(AND(ISNUMBER(AO8),ISNUMBER(AP8)),IF(AND(AP8>0,AO8>AP8),1,0),0) -> 0 | AR8: =IF(NOT(ISNUMBER(B8)),0,IF(B8<MAX($B$5:B7),1,0)) -> 0 | AS8: =IF(C8="","",IFERROR(INDEX(CLIENTES!$H$6:$H$305,MATCH(C8,CLIENTES!$A$6:$A$305,0)),"")) | AT8: =IF(AND(LEFT(P8,5)="AVISO",T8<>"Presentado",ISNUMBER(Q8)),Q8,"") | AU8: =IF(AND(D8="XVI - Activos virtuales (PSAV): operación de intercambio/transferencia",M8="Sí",ISNUMBER(AE8)),IF(AK8>=AE8,1,0),0) -> 0 | AV8: =IF(NOT(ISNUMBER(B8)),CONFIG!$B$4,IFERROR(INDEX(CONFIG!$I$5:$I$14,MATCH(IF(MONTH(B8)=1,YEAR(B8)-1,YEAR(B8)),CONFIG!$H$5:$H$14,0)),CONFIG!$B$4)) -> 117.31 | AW8: =IF(AND(LEFT(D8,4)="I - ",ISNUMBER(B8),C8<>""),SUMIFS($E$6:$E$505,$C$6:$C$505,C8,$D$6:$D$505,D8,$B$6:$B$505,">"&(B8-1),$B$6:$B$505,"<="&B8),0) -> 0 | AX8: =IF(E8="","",IF(AD8="Siempre","AVISO (siempre)",IF(AD8="No aplica","Sin Aviso (sólo preparas: Ley 17 XI)",IF(NOT(ISNUMBER(AE8)),"",IF(AA8<>"ACUMULA",IF(E8>=AE8,IF(AND(D8="XVI - Activos virtuales (PSAV): cobro de contraprestación (comisión) por el servicio",COUNTIFS($C$6:$C$505,C8,$B$6:$B$505,">="&INT(B8),$B$6:$B$505,"<"&(INT(B8)+1),$AU$6:$AU$505,1)>0),"En el Aviso del inciso a) (R 31 Bis)","AVISO"),"—"),IF(M8<>"Sí","—",IF(AK8>=AE8,IF(AK8=E8,"AVISO","AVISO (acumulado)"),"Acumulando")))))))
A9: =IF(E9="","",ROW()-5) | I9: =IF(C9="","",IFERROR(INDEX(CLIENTES!$B$6:$B$305,MATCH(C9,CLIENTES!$A$6:$A$305,0)),"⚠ ID no registrado")) | J9: =IF(C9="","",IFERROR(INDEX(CLIENTES!$Z$6:$Z$305,MATCH(C9,CLIENTES!$A$6:$A$305,0)),"")) | K9: =IF(E9="","",IF(AB9="Siempre","Sí",IF(ISNUMBER(AC9),IF(E9>=AC9,"Sí",IF(AW9>=AC9,"Sí (serie 24 h)","No")),""))) | L9: =IF(E9="","",AA9) | M9: =IF(E9="","",IF(AA9<>"ACUMULA","No aplica",IF(LEFT(K9,2)="Sí","Sí","No"))) | N9: =IF(M9="Sí",AJ9,"") | O9: =IF(M9="Sí",AK9,"") | P9: =IF(AND(LEFT(D9,6)="XIV - ",LEFT(AX9,5)="AVISO"),"Pedimento (R 16): no va al SPPLD",AX9) | Q9: =IF(LEFT(P9,5)="AVISO",IF(ISNUMBER(B9),DATE(YEAR(B9),MONTH(B9)+1,17),"Falta fecha"),"") | R9: =IF(OR(F9="",F9=0),"",IF(ISNUMBER(AG9),IF(F9>=AG9,"PROHIBIDO","Dentro del límite"),"No aplica")) | S9: =IF(E9="","",MID(IF(AQ9=1," · Excede el perfil declarado","")&IF(H9="Sí"," · Paga un tercero","")&IF(J9="Alto"," · Cliente de riesgo alto: DDR (RCG 23 Ter 3 y 4)","")&IF(AND(AS9<>"",AS9<>"No",AS9<>0)," · PEP","")&IF(R9="PROHIBIDO"," · Efectivo prohibido: no lo recibas (Art. 32)","")&IF(AR9=1," · ⚠ Fecha fuera de orden","")&IF(LEFT(I9,1)="⚠"," · ⚠ Cliente no registrado","")&IF(D9=""," · ⚠ Falta la actividad","")&IF(AND(LEFT(P9,5)="AVISO",W9="")," · Captura la cifra total con IVA para el Aviso","")&IF(AND(ISNUMBER(W9),W9<E9)," · ⚠ La cifra con IVA es menor que el monto sin IVA",""),4,400)) | V9: =IF(LEFT(P9,5)<>"AVISO","",IF(T9="Presentado",IF(AND(ISNUMBER(U9),ISNUMBER(Q9),U9>Q9),"Presentado tarde","Presentado"),IF(NOT(ISNUMBER(Q9)),"Falta fecha",IF(Q9<CONFIG!$B$6,"VENCIDO","Vence en "&(Q9-CONFIG!$B$6)&" días")))) | AA9: =IF(AM9="","",INDEX(CATÁLOGO!$D$5:$D$39,AM9)) | AB9: =IF(AM9="","",INDEX(CATÁLOGO!$E$5:$E$39,AM9)) | AC9: =IF(AB9="","",IF(ISNUMBER(AB9),AB9*AV9,AB9)) | AD9: =IF(AM9="","",INDEX(CATÁLOGO!$F$5:$F$39,AM9)) | AE9: =IF(AD9="","",IF(ISNUMBER(AD9),AD9*AV9,AD9)) | AF9: =IF(AM9="","",INDEX(CATÁLOGO!$G$5:$G$39,AM9)) | AG9: =IF(AF9="","",IF(ISNUMBER(AF9),AF9*AV9,AF9)) | AH9: =IF(E9="","",C9&"|"&D9) | AI9: =IF(M9<>"Sí",0,SUMPRODUCT(MAX(($AH$5:AH8=AH9)*($M$5:M8="Sí")*ROW($AH$5:AH8)))) -> 0 | AJ9: =IF(M9<>"Sí","",IF(AL9=1,B9,INDEX($AJ:$AJ,AI9))) | AK9: =IF(M9<>"Sí","",IF(AL9=1,E9,INDEX($AK:$AK,AI9)+E9)) | AL9: =IF(M9<>"Sí","",IF(AI9=0,1,IF(INDEX($AN:$AN,AI9)=0,1,IF(B9>=EDATE(INDEX($AJ:$AJ,AI9),6),1,0)))) | AM9: =IF(D9="","",IFERROR(MATCH(D9,CATÁLOGO!$C$5:$C$39,0),"")) | AN9: =IF(M9<>"Sí","",IF(AND(ISNUMBER(AE9),AK9>=AE9),0,1)) | AO9: =IF(OR(E9="",C9="",NOT(ISNUMBER(B9))),"",SUMIFS($E$6:$E$505,$C$6:$C$505,C9,$B$6:$B$505,">="&DATE(YEAR(B9),MONTH(B9),1),$B$6:$B$505,"<"&DATE(YEAR(B9),MONTH(B9)+1,1))) | AP9: =IF(C9="","",IFERROR(INDEX(CLIENTES!$M$6:$M$305,MATCH(C9,CLIENTES!$A$6:$A$305,0)),"")) | AQ9: =IF(AND(ISNUMBER(AO9),ISNUMBER(AP9)),IF(AND(AP9>0,AO9>AP9),1,0),0) -> 0 | AR9: =IF(NOT(ISNUMBER(B9)),0,IF(B9<MAX($B$5:B8),1,0)) -> 0 | AS9: =IF(C9="","",IFERROR(INDEX(CLIENTES!$H$6:$H$305,MATCH(C9,CLIENTES!$A$6:$A$305,0)),"")) | AT9: =IF(AND(LEFT(P9,5)="AVISO",T9<>"Presentado",ISNUMBER(Q9)),Q9,"") | AU9: =IF(AND(D9="XVI - Activos virtuales (PSAV): operación de intercambio/transferencia",M9="Sí",ISNUMBER(AE9)),IF(AK9>=AE9,1,0),0) -> 0 | AV9: =IF(NOT(ISNUMBER(B9)),CONFIG!$B$4,IFERROR(INDEX(CONFIG!$I$5:$I$14,MATCH(IF(MONTH(B9)=1,YEAR(B9)-1,YEAR(B9)),CONFIG!$H$5:$H$14,0)),CONFIG!$B$4)) -> 117.31 | AW9: =IF(AND(LEFT(D9,4)="I - ",ISNUMBER(B9),C9<>""),SUMIFS($E$6:$E$505,$C$6:$C$505,C9,$D$6:$D$505,D9,$B$6:$B$505,">"&(B9-1),$B$6:$B$505,"<="&B9),0) -> 0 | AX9: =IF(E9="","",IF(AD9="Siempre","AVISO (siempre)",IF(AD9="No aplica","Sin Aviso (sólo preparas: Ley 17 XI)",IF(NOT(ISNUMBER(AE9)),"",IF(AA9<>"ACUMULA",IF(E9>=AE9,IF(AND(D9="XVI - Activos virtuales (PSAV): cobro de contraprestación (comisión) por el servicio",COUNTIFS($C$6:$C$505,C9,$B$6:$B$505,">="&INT(B9),$B$6:$B$505,"<"&(INT(B9)+1),$AU$6:$AU$505,1)>0),"En el Aviso del inciso a) (R 31 Bis)","AVISO"),"—"),IF(M9<>"Sí","—",IF(AK9>=AE9,IF(AK9=E9,"AVISO","AVISO (acumulado)"),"Acumulando")))))))
A10: =IF(E10="","",ROW()-5) | I10: =IF(C10="","",IFERROR(INDEX(CLIENTES!$B$6:$B$305,MATCH(C10,CLIENTES!$A$6:$A$305,0)),"⚠ ID no registrado")) | J10: =IF(C10="","",IFERROR(INDEX(CLIENTES!$Z$6:$Z$305,MATCH(C10,CLIENTES!$A$6:$A$305,0)),"")) | K10: =IF(E10="","",IF(AB10="Siempre","Sí",IF(ISNUMBER(AC10),IF(E10>=AC10,"Sí",IF(AW10>=AC10,"Sí (serie 24 h)","No")),""))) | L10: =IF(E10="","",AA10) | M10: =IF(E10="","",IF(AA10<>"ACUMULA","No aplica",IF(LEFT(K10,2)="Sí","Sí","No"))) | N10: =IF(M10="Sí",AJ10,"") | O10: =IF(M10="Sí",AK10,"") | P10: =IF(AND(LEFT(D10,6)="XIV - ",LEFT(AX10,5)="AVISO"),"Pedimento (R 16): no va al SPPLD",AX10) | Q10: =IF(LEFT(P10,5)="AVISO",IF(ISNUMBER(B10),DATE(YEAR(B10),MONTH(B10)+1,17),"Falta fecha"),"") | R10: =IF(OR(F10="",F10=0),"",IF(ISNUMBER(AG10),IF(F10>=AG10,"PROHIBIDO","Dentro del límite"),"No aplica")) | S10: =IF(E10="","",MID(IF(AQ10=1," · Excede el perfil declarado","")&IF(H10="Sí"," · Paga un tercero","")&IF(J10="Alto"," · Cliente de riesgo alto: DDR (RCG 23 Ter 3 y 4)","")&IF(AND(AS10<>"",AS10<>"No",AS10<>0)," · PEP","")&IF(R10="PROHIBIDO"," · Efectivo prohibido: no lo recibas (Art. 32)","")&IF(AR10=1," · ⚠ Fecha fuera de orden","")&IF(LEFT(I10,1)="⚠"," · ⚠ Cliente no registrado","")&IF(D10=""," · ⚠ Falta la actividad","")&IF(AND(LEFT(P10,5)="AVISO",W10="")," · Captura la cifra total con IVA para el Aviso","")&IF(AND(ISNUMBER(W10),W10<E10)," · ⚠ La cifra con IVA es menor que el monto sin IVA",""),4,400)) | V10: =IF(LEFT(P10,5)<>"AVISO","",IF(T10="Presentado",IF(AND(ISNUMBER(U10),ISNUMBER(Q10),U10>Q10),"Presentado tarde","Presentado"),IF(NOT(ISNUMBER(Q10)),"Falta fecha",IF(Q10<CONFIG!$B$6,"VENCIDO","Vence en "&(Q10-CONFIG!$B$6)&" días")))) | AA10: =IF(AM10="","",INDEX(CATÁLOGO!$D$5:$D$39,AM10)) | AB10: =IF(AM10="","",INDEX(CATÁLOGO!$E$5:$E$39,AM10)) | AC10: =IF(AB10="","",IF(ISNUMBER(AB10),AB10*AV10,AB10)) | AD10: =IF(AM10="","",INDEX(CATÁLOGO!$F$5:$F$39,AM10)) | AE10: =IF(AD10="","",IF(ISNUMBER(AD10),AD10*AV10,AD10)) | AF10: =IF(AM10="","",INDEX(CATÁLOGO!$G$5:$G$39,AM10)) | AG10: =IF(AF10="","",IF(ISNUMBER(AF10),AF10*AV10,AF10)) | AH10: =IF(E10="","",C10&"|"&D10) | AI10: =IF(M10<>"Sí",0,SUMPRODUCT(MAX(($AH$5:AH9=AH10)*($M$5:M9="Sí")*ROW($AH$5:AH9)))) -> 0 | AJ10: =IF(M10<>"Sí","",IF(AL10=1,B10,INDEX($AJ:$AJ,AI10))) | AK10: =IF(M10<>"Sí","",IF(AL10=1,E10,INDEX($AK:$AK,AI10)+E10)) | AL10: =IF(M10<>"Sí","",IF(AI10=0,1,IF(INDEX($AN:$AN,AI10)=0,1,IF(B10>=EDATE(INDEX($AJ:$AJ,AI10),6),1,0)))) | AM10: =IF(D10="","",IFERROR(MATCH(D10,CATÁLOGO!$C$5:$C$39,0),"")) | AN10: =IF(M10<>"Sí","",IF(AND(ISNUMBER(AE10),AK10>=AE10),0,1)) | AO10: =IF(OR(E10="",C10="",NOT(ISNUMBER(B10))),"",SUMIFS($E$6:$E$505,$C$6:$C$505,C10,$B$6:$B$505,">="&DATE(YEAR(B10),MONTH(B10),1),$B$6:$B$505,"<"&DATE(YEAR(B10),MONTH(B10)+1,1))) | AP10: =IF(C10="","",IFERROR(INDEX(CLIENTES!$M$6:$M$305,MATCH(C10,CLIENTES!$A$6:$A$305,0)),"")) | AQ10: =IF(AND(ISNUMBER(AO10),ISNUMBER(AP10)),IF(AND(AP10>0,AO10>AP10),1,0),0) -> 0 | AR10: =IF(NOT(ISNUMBER(B10)),0,IF(B10<MAX($B$5:B9),1,0)) -> 0 | AS10: =IF(C10="","",IFERROR(INDEX(CLIENTES!$H$6:$H$305,MATCH(C10,CLIENTES!$A$6:$A$305,0)),"")) | AT10: =IF(AND(LEFT(P10,5)="AVISO",T10<>"Presentado",ISNUMBER(Q10)),Q10,"") | AU10: =IF(AND(D10="XVI - Activos virtuales (PSAV): operación de intercambio/transferencia",M10="Sí",ISNUMBER(AE10)),IF(AK10>=AE10,1,0),0) -> 0 | AV10: =IF(NOT(ISNUMBER(B10)),CONFIG!$B$4,IFERROR(INDEX(CONFIG!$I$5:$I$14,MATCH(IF(MONTH(B10)=1,YEAR(B10)-1,YEAR(B10)),CONFIG!$H$5:$H$14,0)),CONFIG!$B$4)) -> 117.31 | AW10: =IF(AND(LEFT(D10,4)="I - ",ISNUMBER(B10),C10<>""),SUMIFS($E$6:$E$505,$C$6:$C$505,C10,$D$6:$D$505,D10,$B$6:$B$505,">"&(B10-1),$B$6:$B$505,"<="&B10),0) -> 0 | AX10: =IF(E10="","",IF(AD10="Siempre","AVISO (siempre)",IF(AD10="No aplica","Sin Aviso (sólo preparas: Ley 17 XI)",IF(NOT(ISNUMBER(AE10)),"",IF(AA10<>"ACUMULA",IF(E10>=AE10,IF(AND(D10="XVI - Activos virtuales (PSAV): cobro de contraprestación (comisión) por el servicio",COUNTIFS($C$6:$C$505,C10,$B$6:$B$505,">="&INT(B10),$B$6:$B$505,"<"&(INT(B10)+1),$AU$6:$AU$505,1)>0),"En el Aviso del inciso a) (R 31 Bis)","AVISO"),"—"),IF(M10<>"Sí","—",IF(AK10>=AE10,IF(AK10=E10,"AVISO","AVISO (acumulado)"),"Acumulando")))))))
A11: =IF(E11="","",ROW()-5) | I11: =IF(C11="","",IFERROR(INDEX(CLIENTES!$B$6:$B$305,MATCH(C11,CLIENTES!$A$6:$A$305,0)),"⚠ ID no registrado")) | J11: =IF(C11="","",IFERROR(INDEX(CLIENTES!$Z$6:$Z$305,MATCH(C11,CLIENTES!$A$6:$A$305,0)),"")) | K11: =IF(E11="","",IF(AB11="Siempre","Sí",IF(ISNUMBER(AC11),IF(E11>=AC11,"Sí",IF(AW11>=AC11,"Sí (serie 24 h)","No")),""))) | L11: =IF(E11="","",AA11) | M11: =IF(E11="","",IF(AA11<>"ACUMULA","No aplica",IF(LEFT(K11,2)="Sí","Sí","No"))) | N11: =IF(M11="Sí",AJ11,"") | O11: =IF(M11="Sí",AK11,"") | P11: =IF(AND(LEFT(D11,6)="XIV - ",LEFT(AX11,5)="AVISO"),"Pedimento (R 16): no va al SPPLD",AX11) | Q11: =IF(LEFT(P11,5)="AVISO",IF(ISNUMBER(B11),DATE(YEAR(B11),MONTH(B11)+1,17),"Falta fecha"),"") | R11: =IF(OR(F11="",F11=0),"",IF(ISNUMBER(AG11),IF(F11>=AG11,"PROHIBIDO","Dentro del límite"),"No aplica")) | S11: =IF(E11="","",MID(IF(AQ11=1," · Excede el perfil declarado","")&IF(H11="Sí"," · Paga un tercero","")&IF(J11="Alto"," · Cliente de riesgo alto: DDR (RCG 23 Ter 3 y 4)","")&IF(AND(AS11<>"",AS11<>"No",AS11<>0)," · PEP","")&IF(R11="PROHIBIDO"," · Efectivo prohibido: no lo recibas (Art. 32)","")&IF(AR11=1," · ⚠ Fecha fuera de orden","")&IF(LEFT(I11,1)="⚠"," · ⚠ Cliente no registrado","")&IF(D11=""," · ⚠ Falta la actividad","")&IF(AND(LEFT(P11,5)="AVISO",W11="")," · Captura la cifra total con IVA para el Aviso","")&IF(AND(ISNUMBER(W11),W11<E11)," · ⚠ La cifra con IVA es menor que el monto sin IVA",""),4,400)) | V11: =IF(LEFT(P11,5)<>"AVISO","",IF(T11="Presentado",IF(AND(ISNUMBER(U11),ISNUMBER(Q11),U11>Q11),"Presentado tarde","Presentado"),IF(NOT(ISNUMBER(Q11)),"Falta fecha",IF(Q11<CONFIG!$B$6,"VENCIDO","Vence en "&(Q11-CONFIG!$B$6)&" días")))) | AA11: =IF(AM11="","",INDEX(CATÁLOGO!$D$5:$D$39,AM11)) | AB11: =IF(AM11="","",INDEX(CATÁLOGO!$E$5:$E$39,AM11)) | AC11: =IF(AB11="","",IF(ISNUMBER(AB11),AB11*AV11,AB11)) | AD11: =IF(AM11="","",INDEX(CATÁLOGO!$F$5:$F$39,AM11)) | AE11: =IF(AD11="","",IF(ISNUMBER(AD11),AD11*AV11,AD11)) | AF11: =IF(AM11="","",INDEX(CATÁLOGO!$G$5:$G$39,AM11)) | AG11: =IF(AF11="","",IF(ISNUMBER(AF11),AF11*AV11,AF11)) | AH11: =IF(E11="","",C11&"|"&D11) | AI11: =IF(M11<>"Sí",0,SUMPRODUCT(MAX(($AH$5:AH10=AH11)*($M$5:M10="Sí")*ROW($AH$5:AH10)))) -> 0 | AJ11: =IF(M11<>"Sí","",IF(AL11=1,B11,INDEX($AJ:$AJ,AI11))) | AK11: =IF(M11<>"Sí","",IF(AL11=1,E11,INDEX($AK:$AK,AI11)+E11)) | AL11: =IF(M11<>"Sí","",IF(AI11=0,1,IF(INDEX($AN:$AN,AI11)=0,1,IF(B11>=EDATE(INDEX($AJ:$AJ,AI11),6),1,0)))) | AM11: =IF(D11="","",IFERROR(MATCH(D11,CATÁLOGO!$C$5:$C$39,0),"")) | AN11: =IF(M11<>"Sí","",IF(AND(ISNUMBER(AE11),AK11>=AE11),0,1)) | AO11: =IF(OR(E11="",C11="",NOT(ISNUMBER(B11))),"",SUMIFS($E$6:$E$505,$C$6:$C$505,C11,$B$6:$B$505,">="&DATE(YEAR(B11),MONTH(B11),1),$B$6:$B$505,"<"&DATE(YEAR(B11),MONTH(B11)+1,1))) | AP11: =IF(C11="","",IFERROR(INDEX(CLIENTES!$M$6:$M$305,MATCH(C11,CLIENTES!$A$6:$A$305,0)),"")) | AQ11: =IF(AND(ISNUMBER(AO11),ISNUMBER(AP11)),IF(AND(AP11>0,AO11>AP11),1,0),0) -> 0 | AR11: =IF(NOT(ISNUMBER(B11)),0,IF(B11<MAX($B$5:B10),1,0)) -> 0 | AS11: =IF(C11="","",IFERROR(INDEX(CLIENTES!$H$6:$H$305,MATCH(C11,CLIENTES!$A$6:$A$305,0)),"")) | AT11: =IF(AND(LEFT(P11,5)="AVISO",T11<>"Presentado",ISNUMBER(Q11)),Q11,"") | AU11: =IF(AND(D11="XVI - Activos virtuales (PSAV): operación de intercambio/transferencia",M11="Sí",ISNUMBER(AE11)),IF(AK11>=AE11,1,0),0) -> 0 | AV11: =IF(NOT(ISNUMBER(B11)),CONFIG!$B$4,IFERROR(INDEX(CONFIG!$I$5:$I$14,MATCH(IF(MONTH(B11)=1,YEAR(B11)-1,YEAR(B11)),CONFIG!$H$5:$H$14,0)),CONFIG!$B$4)) -> 117.31 | AW11: =IF(AND(LEFT(D11,4)="I - ",ISNUMBER(B11),C11<>""),SUMIFS($E$6:$E$505,$C$6:$C$505,C11,$D$6:$D$505,D11,$B$6:$B$505,">"&(B11-1),$B$6:$B$505,"<="&B11),0) -> 0 | AX11: =IF(E11="","",IF(AD11="Siempre","AVISO (siempre)",IF(AD11="No aplica","Sin Aviso (sólo preparas: Ley 17 XI)",IF(NOT(ISNUMBER(AE11)),"",IF(AA11<>"ACUMULA",IF(E11>=AE11,IF(AND(D11="XVI - Activos virtuales (PSAV): cobro de contraprestación (comisión) por el servicio",COUNTIFS($C$6:$C$505,C11,$B$6:$B$505,">="&INT(B11),$B$6:$B$505,"<"&(INT(B11)+1),$AU$6:$AU$505,1)>0),"En el Aviso del inciso a) (R 31 Bis)","AVISO"),"—"),IF(M11<>"Sí","—",IF(AK11>=AE11,IF(AK11=E11,"AVISO","AVISO (acumulado)"),"Acumulando")))))))
A12: =IF(E12="","",ROW()-5) | I12: =IF(C12="","",IFERROR(INDEX(CLIENTES!$B$6:$B$305,MATCH(C12,CLIENTES!$A$6:$A$305,0)),"⚠ ID no registrado")) | J12: =IF(C12="","",IFERROR(INDEX(CLIENTES!$Z$6:$Z$305,MATCH(C12,CLIENTES!$A$6:$A$305,0)),"")) | K12: =IF(E12="","",IF(AB12="Siempre","Sí",IF(ISNUMBER(AC12),IF(E12>=AC12,"Sí",IF(AW12>=AC12,"Sí (serie 24 h)","No")),""))) | L12: =IF(E12="","",AA12) | M12: =IF(E12="","",IF(AA12<>"ACUMULA","No aplica",IF(LEFT(K12,2)="Sí","Sí","No"))) | N12: =IF(M12="Sí",AJ12,"") | O12: =IF(M12="Sí",AK12,"") | P12: =IF(AND(LEFT(D12,6)="XIV - ",LEFT(AX12,5)="AVISO"),"Pedimento (R 16): no va al SPPLD",AX12) | Q12: =IF(LEFT(P12,5)="AVISO",IF(ISNUMBER(B12),DATE(YEAR(B12),MONTH(B12)+1,17),"Falta fecha"),"") | R12: =IF(OR(F12="",F12=0),"",IF(ISNUMBER(AG12),IF(F12>=AG12,"PROHIBIDO","Dentro del límite"),"No aplica")) | S12: =IF(E12="","",MID(IF(AQ12=1," · Excede el perfil declarado","")&IF(H12="Sí"," · Paga un tercero","")&IF(J12="Alto"," · Cliente de riesgo alto: DDR (RCG 23 Ter 3 y 4)","")&IF(AND(AS12<>"",AS12<>"No",AS12<>0)," · PEP","")&IF(R12="PROHIBIDO"," · Efectivo prohibido: no lo recibas (Art. 32)","")&IF(AR12=1," · ⚠ Fecha fuera de orden","")&IF(LEFT(I12,1)="⚠"," · ⚠ Cliente no registrado","")&IF(D12=""," · ⚠ Falta la actividad","")&IF(AND(LEFT(P12,5)="AVISO",W12="")," · Captura la cifra total con IVA para el Aviso","")&IF(AND(ISNUMBER(W12),W12<E12)," · ⚠ La cifra con IVA es menor que el monto sin IVA",""),4,400)) | V12: =IF(LEFT(P12,5)<>"AVISO","",IF(T12="Presentado",IF(AND(ISNUMBER(U12),ISNUMBER(Q12),U12>Q12),"Presentado tarde","Presentado"),IF(NOT(ISNUMBER(Q12)),"Falta fecha",IF(Q12<CONFIG!$B$6,"VENCIDO","Vence en "&(Q12-CONFIG!$B$6)&" días")))) | AA12: =IF(AM12="","",INDEX(CATÁLOGO!$D$5:$D$39,AM12)) | AB12: =IF(AM12="","",INDEX(CATÁLOGO!$E$5:$E$39,AM12)) | AC12: =IF(AB12="","",IF(ISNUMBER(AB12),AB12*AV12,AB12)) | AD12: =IF(AM12="","",INDEX(CATÁLOGO!$F$5:$F$39,AM12)) | AE12: =IF(AD12="","",IF(ISNUMBER(AD12),AD12*AV12,AD12)) | AF12: =IF(AM12="","",INDEX(CATÁLOGO!$G$5:$G$39,AM12)) | AG12: =IF(AF12="","",IF(ISNUMBER(AF12),AF12*AV12,AF12)) | AH12: =IF(E12="","",C12&"|"&D12) | AI12: =IF(M12<>"Sí",0,SUMPRODUCT(MAX(($AH$5:AH11=AH12)*($M$5:M11="Sí")*ROW($AH$5:AH11)))) -> 0 | AJ12: =IF(M12<>"Sí","",IF(AL12=1,B12,INDEX($AJ:$AJ,AI12))) | AK12: =IF(M12<>"Sí","",IF(AL12=1,E12,INDEX($AK:$AK,AI12)+E12)) | AL12: =IF(M12<>"Sí","",IF(AI12=0,1,IF(INDEX($AN:$AN,AI12)=0,1,IF(B12>=EDATE(INDEX($AJ:$AJ,AI12),6),1,0)))) | AM12: =IF(D12="","",IFERROR(MATCH(D12,CATÁLOGO!$C$5:$C$39,0),"")) | AN12: =IF(M12<>"Sí","",IF(AND(ISNUMBER(AE12),AK12>=AE12),0,1)) | AO12: =IF(OR(E12="",C12="",NOT(ISNUMBER(B12))),"",SUMIFS($E$6:$E$505,$C$6:$C$505,C12,$B$6:$B$505,">="&DATE(YEAR(B12),MONTH(B12),1),$B$6:$B$505,"<"&DATE(YEAR(B12),MONTH(B12)+1,1))) | AP12: =IF(C12="","",IFERROR(INDEX(CLIENTES!$M$6:$M$305,MATCH(C12,CLIENTES!$A$6:$A$305,0)),"")) | AQ12: =IF(AND(ISNUMBER(AO12),ISNUMBER(AP12)),IF(AND(AP12>0,AO12>AP12),1,0),0) -> 0 | AR12: =IF(NOT(ISNUMBER(B12)),0,IF(B12<MAX($B$5:B11),1,0)) -> 0 | AS12: =IF(C12="","",IFERROR(INDEX(CLIENTES!$H$6:$H$305,MATCH(C12,CLIENTES!$A$6:$A$305,0)),"")) | AT12: =IF(AND(LEFT(P12,5)="AVISO",T12<>"Presentado",ISNUMBER(Q12)),Q12,"") | AU12: =IF(AND(D12="XVI - Activos virtuales (PSAV): operación de intercambio/transferencia",M12="Sí",ISNUMBER(AE12)),IF(AK12>=AE12,1,0),0) -> 0 | AV12: =IF(NOT(ISNUMBER(B12)),CONFIG!$B$4,IFERROR(INDEX(CONFIG!$I$5:$I$14,MATCH(IF(MONTH(B12)=1,YEAR(B12)-1,YEAR(B12)),CONFIG!$H$5:$H$14,0)),CONFIG!$B$4)) -> 117.31 | AW12: =IF(AND(LEFT(D12,4)="I - ",ISNUMBER(B12),C12<>""),SUMIFS($E$6:$E$505,$C$6:$C$505,C12,$D$6:$D$505,D12,$B$6:$B$505,">"&(B12-1),$B$6:$B$505,"<="&B12),0) -> 0 | AX12: =IF(E12="","",IF(AD12="Siempre","AVISO (siempre)",IF(AD12="No aplica","Sin Aviso (sólo preparas: Ley 17 XI)",IF(NOT(ISNUMBER(AE12)),"",IF(AA12<>"ACUMULA",IF(E12>=AE12,IF(AND(D12="XVI - Activos virtuales (PSAV): cobro de contraprestación (comisión) por el servicio",COUNTIFS($C$6:$C$505,C12,$B$6:$B$505,">="&INT(B12),$B$6:$B$505,"<"&(INT(B12)+1),$AU$6:$AU$505,1)>0),"En el Aviso del inciso a) (R 31 Bis)","AVISO"),"—"),IF(M12<>"Sí","—",IF(AK12>=AE12,IF(AK12=E12,"AVISO","AVISO (acumulado)"),"Acumulando")))))))
A13: =IF(E13="","",ROW()-5) | I13: =IF(C13="","",IFERROR(INDEX(CLIENTES!$B$6:$B$305,MATCH(C13,CLIENTES!$A$6:$A$305,0)),"⚠ ID no registrado")) | J13: =IF(C13="","",IFERROR(INDEX(CLIENTES!$Z$6:$Z$305,MATCH(C13,CLIENTES!$A$6:$A$305,0)),"")) | K13: =IF(E13="","",IF(AB13="Siempre","Sí",IF(ISNUMBER(AC13),IF(E13>=AC13,"Sí",IF(AW13>=AC13,"Sí (serie 24 h)","No")),""))) | L13: =IF(E13="","",AA13) | M13: =IF(E13="","",IF(AA13<>"ACUMULA","No aplica",IF(LEFT(K13,2)="Sí","Sí","No"))) | N13: =IF(M13="Sí",AJ13,"") | O13: =IF(M13="Sí",AK13,"") | P13: =IF(AND(LEFT(D13,6)="XIV - ",LEFT(AX13,5)="AVISO"),"Pedimento (R 16): no va al SPPLD",AX13) | Q13: =IF(LEFT(P13,5)="AVISO",IF(ISNUMBER(B13),DATE(YEAR(B13),MONTH(B13)+1,17),"Falta fecha"),"") | R13: =IF(OR(F13="",F13=0),"",IF(ISNUMBER(AG13),IF(F13>=AG13,"PROHIBIDO","Dentro del límite"),"No aplica")) | S13: =IF(E13="","",MID(IF(AQ13=1," · Excede el perfil declarado","")&IF(H13="Sí"," · Paga un tercero","")&IF(J13="Alto"," · Cliente de riesgo alto: DDR (RCG 23 Ter 3 y 4)","")&IF(AND(AS13<>"",AS13<>"No",AS13<>0)," · PEP","")&IF(R13="PROHIBIDO"," · Efectivo prohibido: no lo recibas (Art. 32)","")&IF(AR13=1," · ⚠ Fecha fuera de orden","")&IF(LEFT(I13,1)="⚠"," · ⚠ Cliente no registrado","")&IF(D13=""," · ⚠ Falta la actividad","")&IF(AND(LEFT(P13,5)="AVISO",W13="")," · Captura la cifra total con IVA para el Aviso","")&IF(AND(ISNUMBER(W13),W13<E13)," · ⚠ La cifra con IVA es menor que el monto sin IVA",""),4,400)) | V13: =IF(LEFT(P13,5)<>"AVISO","",IF(T13="Presentado",IF(AND(ISNUMBER(U13),ISNUMBER(Q13),U13>Q13),"Presentado tarde","Presentado"),IF(NOT(ISNUMBER(Q13)),"Falta fecha",IF(Q13<CONFIG!$B$6,"VENCIDO","Vence en "&(Q13-CONFIG!$B$6)&" días")))) | AA13: =IF(AM13="","",INDEX(CATÁLOGO!$D$5:$D$39,AM13)) | AB13: =IF(AM13="","",INDEX(CATÁLOGO!$E$5:$E$39,AM13)) | AC13: =IF(AB13="","",IF(ISNUMBER(AB13),AB13*AV13,AB13)) | AD13: =IF(AM13="","",INDEX(CATÁLOGO!$F$5:$F$39,AM13)) | AE13: =IF(AD13="","",IF(ISNUMBER(AD13),AD13*AV13,AD13)) | AF13: =IF(AM13="","",INDEX(CATÁLOGO!$G$5:$G$39,AM13)) | AG13: =IF(AF13="","",IF(ISNUMBER(AF13),AF13*AV13,AF13)) | AH13: =IF(E13="","",C13&"|"&D13) | AI13: =IF(M13<>"Sí",0,SUMPRODUCT(MAX(($AH$5:AH12=AH13)*($M$5:M12="Sí")*ROW($AH$5:AH12)))) -> 0 | AJ13: =IF(M13<>"Sí","",IF(AL13=1,B13,INDEX($AJ:$AJ,AI13))) | AK13: =IF(M13<>"Sí","",IF(AL13=1,E13,INDEX($AK:$AK,AI13)+E13)) | AL13: =IF(M13<>"Sí","",IF(AI13=0,1,IF(INDEX($AN:$AN,AI13)=0,1,IF(B13>=EDATE(INDEX($AJ:$AJ,AI13),6),1,0)))) | AM13: =IF(D13="","",IFERROR(MATCH(D13,CATÁLOGO!$C$5:$C$39,0),"")) | AN13: =IF(M13<>"Sí","",IF(AND(ISNUMBER(AE13),AK13>=AE13),0,1)) | AO13: =IF(OR(E13="",C13="",NOT(ISNUMBER(B13))),"",SUMIFS($E$6:$E$505,$C$6:$C$505,C13,$B$6:$B$505,">="&DATE(YEAR(B13),MONTH(B13),1),$B$6:$B$505,"<"&DATE(YEAR(B13),MONTH(B13)+1,1))) | AP13: =IF(C13="","",IFERROR(INDEX(CLIENTES!$M$6:$M$305,MATCH(C13,CLIENTES!$A$6:$A$305,0)),"")) | AQ13: =IF(AND(ISNUMBER(AO13),ISNUMBER(AP13)),IF(AND(AP13>0,AO13>AP13),1,0),0) -> 0 | AR13: =IF(NOT(ISNUMBER(B13)),0,IF(B13<MAX($B$5:B12),1,0)) -> 0 | AS13: =IF(C13="","",IFERROR(INDEX(CLIENTES!$H$6:$H$305,MATCH(C13,CLIENTES!$A$6:$A$305,0)),"")) | AT13: =IF(AND(LEFT(P13,5)="AVISO",T13<>"Presentado",ISNUMBER(Q13)),Q13,"") | AU13: =IF(AND(D13="XVI - Activos virtuales (PSAV): operación de intercambio/transferencia",M13="Sí",ISNUMBER(AE13)),IF(AK13>=AE13,1,0),0) -> 0 | AV13: =IF(NOT(ISNUMBER(B13)),CONFIG!$B$4,IFERROR(INDEX(CONFIG!$I$5:$I$14,MATCH(IF(MONTH(B13)=1,YEAR(B13)-1,YEAR(B13)),CONFIG!$H$5:$H$14,0)),CONFIG!$B$4)) -> 117.31 | AW13: =IF(AND(LEFT(D13,4)="I - ",ISNUMBER(B13),C13<>""),SUMIFS($E$6:$E$505,$C$6:$C$505,C13,$D$6:$D$505,D13,$B$6:$B$505,">"&(B13-1),$B$6:$B$505,"<="&B13),0) -> 0 | AX13: =IF(E13="","",IF(AD13="Siempre","AVISO (siempre)",IF(AD13="No aplica","Sin Aviso (sólo preparas: Ley 17 XI)",IF(NOT(ISNUMBER(AE13)),"",IF(AA13<>"ACUMULA",IF(E13>=AE13,IF(AND(D13="XVI - Activos virtuales (PSAV): cobro de contraprestación (comisión) por el servicio",COUNTIFS($C$6:$C$505,C13,$B$6:$B$505,">="&INT(B13),$B$6:$B$505,"<"&(INT(B13)+1),$AU$6:$AU$505,1)>0),"En el Aviso del inciso a) (R 31 Bis)","AVISO"),"—"),IF(M13<>"Sí","—",IF(AK13>=AE13,IF(AK13=E13,"AVISO","AVISO (acumulado)"),"Acumulando")))))))
A14: =IF(E14="","",ROW()-5) | I14: =IF(C14="","",IFERROR(INDEX(CLIENTES!$B$6:$B$305,MATCH(C14,CLIENTES!$A$6:$A$305,0)),"⚠ ID no registrado")) | J14: =IF(C14="","",IFERROR(INDEX(CLIENTES!$Z$6:$Z$305,MATCH(C14,CLIENTES!$A$6:$A$305,0)),"")) | K14: =IF(E14="","",IF(AB14="Siempre","Sí",IF(ISNUMBER(AC14),IF(E14>=AC14,"Sí",IF(AW14>=AC14,"Sí (serie 24 h)","No")),""))) | L14: =IF(E14="","",AA14) | M14: =IF(E14="","",IF(AA14<>"ACUMULA","No aplica",IF(LEFT(K14,2)="Sí","Sí","No"))) | N14: =IF(M14="Sí",AJ14,"") | O14: =IF(M14="Sí",AK14,"") | P14: =IF(AND(LEFT(D14,6)="XIV - ",LEFT(AX14,5)="AVISO"),"Pedimento (R 16): no va al SPPLD",AX14) | Q14: =IF(LEFT(P14,5)="AVISO",IF(ISNUMBER(B14),DATE(YEAR(B14),MONTH(B14)+1,17),"Falta fecha"),"") | R14: =IF(OR(F14="",F14=0),"",IF(ISNUMBER(AG14),IF(F14>=AG14,"PROHIBIDO","Dentro del límite"),"No aplica")) | S14: =IF(E14="","",MID(IF(AQ14=1," · Excede el perfil declarado","")&IF(H14="Sí"," · Paga un tercero","")&IF(J14="Alto"," · Cliente de riesgo alto: DDR (RCG 23 Ter 3 y 4)","")&IF(AND(AS14<>"",AS14<>"No",AS14<>0)," · PEP","")&IF(R14="PROHIBIDO"," · Efectivo prohibido: no lo recibas (Art. 32)","")&IF(AR14=1," · ⚠ Fecha fuera de orden","")&IF(LEFT(I14,1)="⚠"," · ⚠ Cliente no registrado","")&IF(D14=""," · ⚠ Falta la actividad","")&IF(AND(LEFT(P14,5)="AVISO",W14="")," · Captura la cifra total con IVA para el Aviso","")&IF(AND(ISNUMBER(W14),W14<E14)," · ⚠ La cifra con IVA es menor que el monto sin IVA",""),4,400)) | V14: =IF(LEFT(P14,5)<>"AVISO","",IF(T14="Presentado",IF(AND(ISNUMBER(U14),ISNUMBER(Q14),U14>Q14),"Presentado tarde","Presentado"),IF(NOT(ISNUMBER(Q14)),"Falta fecha",IF(Q14<CONFIG!$B$6,"VENCIDO","Vence en "&(Q14-CONFIG!$B$6)&" días")))) | AA14: =IF(AM14="","",INDEX(CATÁLOGO!$D$5:$D$39,AM14)) | AB14: =IF(AM14="","",INDEX(CATÁLOGO!$E$5:$E$39,AM14)) | AC14: =IF(AB14="","",IF(ISNUMBER(AB14),AB14*AV14,AB14)) | AD14: =IF(AM14="","",INDEX(CATÁLOGO!$F$5:$F$39,AM14)) | AE14: =IF(AD14="","",IF(ISNUMBER(AD14),AD14*AV14,AD14)) | AF14: =IF(AM14="","",INDEX(CATÁLOGO!$G$5:$G$39,AM14)) | AG14: =IF(AF14="","",IF(ISNUMBER(AF14),AF14*AV14,AF14)) | AH14: =IF(E14="","",C14&"|"&D14) | AI14: =IF(M14<>"Sí",0,SUMPRODUCT(MAX(($AH$5:AH13=AH14)*($M$5:M13="Sí")*ROW($AH$5:AH13)))) -> 0 | AJ14: =IF(M14<>"Sí","",IF(AL14=1,B14,INDEX($AJ:$AJ,AI14))) | AK14: =IF(M14<>"Sí","",IF(AL14=1,E14,INDEX($AK:$AK,AI14)+E14)) | AL14: =IF(M14<>"Sí","",IF(AI14=0,1,IF(INDEX($AN:$AN,AI14)=0,1,IF(B14>=EDATE(INDEX($AJ:$AJ,AI14),6),1,0)))) | AM14: =IF(D14="","",IFERROR(MATCH(D14,CATÁLOGO!$C$5:$C$39,0),"")) | AN14: =IF(M14<>"Sí","",IF(AND(ISNUMBER(AE14),AK14>=AE14),0,1)) | AO14: =IF(OR(E14="",C14="",NOT(ISNUMBER(B14))),"",SUMIFS($E$6:$E$505,$C$6:$C$505,C14,$B$6:$B$505,">="&DATE(YEAR(B14),MONTH(B14),1),$B$6:$B$505,"<"&DATE(YEAR(B14),MONTH(B14)+1,1))) | AP14: =IF(C14="","",IFERROR(INDEX(CLIENTES!$M$6:$M$305,MATCH(C14,CLIENTES!$A$6:$A$305,0)),"")) | AQ14: =IF(AND(ISNUMBER(AO14),ISNUMBER(AP14)),IF(AND(AP14>0,AO14>AP14),1,0),0) -> 0 | AR14: =IF(NOT(ISNUMBER(B14)),0,IF(B14<MAX($B$5:B13),1,0)) -> 0 | AS14: =IF(C14="","",IFERROR(INDEX(CLIENTES!$H$6:$H$305,MATCH(C14,CLIENTES!$A$6:$A$305,0)),"")) | AT14: =IF(AND(LEFT(P14,5)="AVISO",T14<>"Presentado",ISNUMBER(Q14)),Q14,"") | AU14: =IF(AND(D14="XVI - Activos virtuales (PSAV): operación de intercambio/transferencia",M14="Sí",ISNUMBER(AE14)),IF(AK14>=AE14,1,0),0) -> 0 | AV14: =IF(NOT(ISNUMBER(B14)),CONFIG!$B$4,IFERROR(INDEX(CONFIG!$I$5:$I$14,MATCH(IF(MONTH(B14)=1,YEAR(B14)-1,YEAR(B14)),CONFIG!$H$5:$H$14,0)),CONFIG!$B$4)) -> 117.31 | AW14: =IF(AND(LEFT(D14,4)="I - ",ISNUMBER(B14),C14<>""),SUMIFS($E$6:$E$505,$C$6:$C$505,C14,$D$6:$D$505,D14,$B$6:$B$505,">"&(B14-1),$B$6:$B$505,"<="&B14),0) -> 0 | AX14: =IF(E14="","",IF(AD14="Siempre","AVISO (siempre)",IF(AD14="No aplica","Sin Aviso (sólo preparas: Ley 17 XI)",IF(NOT(ISNUMBER(AE14)),"",IF(AA14<>"ACUMULA",IF(E14>=AE14,IF(AND(D14="XVI - Activos virtuales (PSAV): cobro de contraprestación (comisión) por el servicio",COUNTIFS($C$6:$C$505,C14,$B$6:$B$505,">="&INT(B14),$B$6:$B$505,"<"&(INT(B14)+1),$AU$6:$AU$505,1)>0),"En el Aviso del inciso a) (R 31 Bis)","AVISO"),"—"),IF(M14<>"Sí","—",IF(AK14>=AE14,IF(AK14=E14,"AVISO","AVISO (acumulado)"),"Acumulando")))))))
A15: =IF(E15="","",ROW()-5) | I15: =IF(C15="","",IFERROR(INDEX(CLIENTES!$B$6:$B$305,MATCH(C15,CLIENTES!$A$6:$A$305,0)),"⚠ ID no registrado")) | J15: =IF(C15="","",IFERROR(INDEX(CLIENTES!$Z$6:$Z$305,MATCH(C15,CLIENTES!$A$6:$A$305,0)),"")) | K15: =IF(E15="","",IF(AB15="Siempre","Sí",IF(ISNUMBER(AC15),IF(E15>=AC15,"Sí",IF(AW15>=AC15,"Sí (serie 24 h)","No")),""))) | L15: =IF(E15="","",AA15) | M15: =IF(E15="","",IF(AA15<>"ACUMULA","No aplica",IF(LEFT(K15,2)="Sí","Sí","No"))) | N15: =IF(M15="Sí",AJ15,"") | O15: =IF(M15="Sí",AK15,"") | P15: =IF(AND(LEFT(D15,6)="XIV - ",LEFT(AX15,5)="AVISO"),"Pedimento (R 16): no va al SPPLD",AX15) | Q15: =IF(LEFT(P15,5)="AVISO",IF(ISNUMBER(B15),DATE(YEAR(B15),MONTH(B15)+1,17),"Falta fecha"),"") | R15: =IF(OR(F15="",F15=0),"",IF(ISNUMBER(AG15),IF(F15>=AG15,"PROHIBIDO","Dentro del límite"),"No aplica")) | S15: =IF(E15="","",MID(IF(AQ15=1," · Excede el perfil declarado","")&IF(H15="Sí"," · Paga un tercero","")&IF(J15="Alto"," · Cliente de riesgo alto: DDR (RCG 23 Ter 3 y 4)","")&IF(AND(AS15<>"",AS15<>"No",AS15<>0)," · PEP","")&IF(R15="PROHIBIDO"," · Efectivo prohibido: no lo recibas (Art. 32)","")&IF(AR15=1," · ⚠ Fecha fuera de orden","")&IF(LEFT(I15,1)="⚠"," · ⚠ Cliente no registrado","")&IF(D15=""," · ⚠ Falta la actividad","")&IF(AND(LEFT(P15,5)="AVISO",W15="")," · Captura la cifra total con IVA para el Aviso","")&IF(AND(ISNUMBER(W15),W15<E15)," · ⚠ La cifra con IVA es menor que el monto sin IVA",""),4,400)) | V15: =IF(LEFT(P15,5)<>"AVISO","",IF(T15="Presentado",IF(AND(ISNUMBER(U15),ISNUMBER(Q15),U15>Q15),"Presentado tarde","Presentado"),IF(NOT(ISNUMBER(Q15)),"Falta fecha",IF(Q15<CONFIG!$B$6,"VENCIDO","Vence en "&(Q15-CONFIG!$B$6)&" días")))) | AA15: =IF(AM15="","",INDEX(CATÁLOGO!$D$5:$D$39,AM15)) | AB15: =IF(AM15="","",INDEX(CATÁLOGO!$E$5:$E$39,AM15)) | AC15: =IF(AB15="","",IF(ISNUMBER(AB15),AB15*AV15,AB15)) | AD15: =IF(AM15="","",INDEX(CATÁLOGO!$F$5:$F$39,AM15)) | AE15: =IF(AD15="","",IF(ISNUMBER(AD15),AD15*AV15,AD15)) | AF15: =IF(AM15="","",INDEX(CATÁLOGO!$G$5:$G$39,AM15)) | AG15: =IF(AF15="","",IF(ISNUMBER(AF15),AF15*AV15,AF15)) | AH15: =IF(E15="","",C15&"|"&D15) | AI15: =IF(M15<>"Sí",0,SUMPRODUCT(MAX(($AH$5:AH14=AH15)*($M$5:M14="Sí")*ROW($AH$5:AH14)))) -> 0 | AJ15: =IF(M15<>"Sí","",IF(AL15=1,B15,INDEX($AJ:$AJ,AI15))) | AK15: =IF(M15<>"Sí","",IF(AL15=1,E15,INDEX($AK:$AK,AI15)+E15)) | AL15: =IF(M15<>"Sí","",IF(AI15=0,1,IF(INDEX($AN:$AN,AI15)=0,1,IF(B15>=EDATE(INDEX($AJ:$AJ,AI15),6),1,0)))) | AM15: =IF(D15="","",IFERROR(MATCH(D15,CATÁLOGO!$C$5:$C$39,0),"")) | AN15: =IF(M15<>"Sí","",IF(AND(ISNUMBER(AE15),AK15>=AE15),0,1)) | AO15: =IF(OR(E15="",C15="",NOT(ISNUMBER(B15))),"",SUMIFS($E$6:$E$505,$C$6:$C$505,C15,$B$6:$B$505,">="&DATE(YEAR(B15),MONTH(B15),1),$B$6:$B$505,"<"&DATE(YEAR(B15),MONTH(B15)+1,1))) | AP15: =IF(C15="","",IFERROR(INDEX(CLIENTES!$M$6:$M$305,MATCH(C15,CLIENTES!$A$6:$A$305,0)),"")) | AQ15: =IF(AND(ISNUMBER(AO15),ISNUMBER(AP15)),IF(AND(AP15>0,AO15>AP15),1,0),0) -> 0 | AR15: =IF(NOT(ISNUMBER(B15)),0,IF(B15<MAX($B$5:B14),1,0)) -> 0 | AS15: =IF(C15="","",IFERROR(INDEX(CLIENTES!$H$6:$H$305,MATCH(C15,CLIENTES!$A$6:$A$305,0)),"")) | AT15: =IF(AND(LEFT(P15,5)="AVISO",T15<>"Presentado",ISNUMBER(Q15)),Q15,"") | AU15: =IF(AND(D15="XVI - Activos virtuales (PSAV): operación de intercambio/transferencia",M15="Sí",ISNUMBER(AE15)),IF(AK15>=AE15,1,0),0) -> 0 | AV15: =IF(NOT(ISNUMBER(B15)),CONFIG!$B$4,IFERROR(INDEX(CONFIG!$I$5:$I$14,MATCH(IF(MONTH(B15)=1,YEAR(B15)-1,YEAR(B15)),CONFIG!$H$5:$H$14,0)),CONFIG!$B$4)) -> 117.31 | AW15: =IF(AND(LEFT(D15,4)="I - ",ISNUMBER(B15),C15<>""),SUMIFS($E$6:$E$505,$C$6:$C$505,C15,$D$6:$D$505,D15,$B$6:$B$505,">"&(B15-1),$B$6:$B$505,"<="&B15),0) -> 0 | AX15: =IF(E15="","",IF(AD15="Siempre","AVISO (siempre)",IF(AD15="No aplica","Sin Aviso (sólo preparas: Ley 17 XI)",IF(NOT(ISNUMBER(AE15)),"",IF(AA15<>"ACUMULA",IF(E15>=AE15,IF(AND(D15="XVI - Activos virtuales (PSAV): cobro de contraprestación (comisión) por el servicio",COUNTIFS($C$6:$C$505,C15,$B$6:$B$505,">="&INT(B15),$B$6:$B$505,"<"&(INT(B15)+1),$AU$6:$AU$505,1)>0),"En el Aviso del inciso a) (R 31 Bis)","AVISO"),"—"),IF(M15<>"Sí","—",IF(AK15>=AE15,IF(AK15=E15,"AVISO","AVISO (acumulado)"),"Acumulando")))))))
A16: =IF(E16="","",ROW()-5) | I16: =IF(C16="","",IFERROR(INDEX(CLIENTES!$B$6:$B$305,MATCH(C16,CLIENTES!$A$6:$A$305,0)),"⚠ ID no registrado")) | J16: =IF(C16="","",IFERROR(INDEX(CLIENTES!$Z$6:$Z$305,MATCH(C16,CLIENTES!$A$6:$A$305,0)),"")) | K16: =IF(E16="","",IF(AB16="Siempre","Sí",IF(ISNUMBER(AC16),IF(E16>=AC16,"Sí",IF(AW16>=AC16,"Sí (serie 24 h)","No")),""))) | L16: =IF(E16="","",AA16) | M16: =IF(E16="","",IF(AA16<>"ACUMULA","No aplica",IF(LEFT(K16,2)="Sí","Sí","No"))) | N16: =IF(M16="Sí",AJ16,"") | O16: =IF(M16="Sí",AK16,"") | P16: =IF(AND(LEFT(D16,6)="XIV - ",LEFT(AX16,5)="AVISO"),"Pedimento (R 16): no va al SPPLD",AX16) | Q16: =IF(LEFT(P16,5)="AVISO",IF(ISNUMBER(B16),DATE(YEAR(B16),MONTH(B16)+1,17),"Falta fecha"),"") | R16: =IF(OR(F16="",F16=0),"",IF(ISNUMBER(AG16),IF(F16>=AG16,"PROHIBIDO","Dentro del límite"),"No aplica")) | S16: =IF(E16="","",MID(IF(AQ16=1," · Excede el perfil declarado","")&IF(H16="Sí"," · Paga un tercero","")&IF(J16="Alto"," · Cliente de riesgo alto: DDR (RCG 23 Ter 3 y 4)","")&IF(AND(AS16<>"",AS16<>"No",AS16<>0)," · PEP","")&IF(R16="PROHIBIDO"," · Efectivo prohibido: no lo recibas (Art. 32)","")&IF(AR16=1," · ⚠ Fecha fuera de orden","")&IF(LEFT(I16,1)="⚠"," · ⚠ Cliente no registrado","")&IF(D16=""," · ⚠ Falta la actividad","")&IF(AND(LEFT(P16,5)="AVISO",W16="")," · Captura la cifra total con IVA para el Aviso","")&IF(AND(ISNUMBER(W16),W16<E16)," · ⚠ La cifra con IVA es menor que el monto sin IVA",""),4,400)) | V16: =IF(LEFT(P16,5)<>"AVISO","",IF(T16="Presentado",IF(AND(ISNUMBER(U16),ISNUMBER(Q16),U16>Q16),"Presentado tarde","Presentado"),IF(NOT(ISNUMBER(Q16)),"Falta fecha",IF(Q16<CONFIG!$B$6,"VENCIDO","Vence en "&(Q16-CONFIG!$B$6)&" días")))) | AA16: =IF(AM16="","",INDEX(CATÁLOGO!$D$5:$D$39,AM16)) | AB16: =IF(AM16="","",INDEX(CATÁLOGO!$E$5:$E$39,AM16)) | AC16: =IF(AB16="","",IF(ISNUMBER(AB16),AB16*AV16,AB16)) | AD16: =IF(AM16="","",INDEX(CATÁLOGO!$F$5:$F$39,AM16)) | AE16: =IF(AD16="","",IF(ISNUMBER(AD16),AD16*AV16,AD16)) | AF16: =IF(AM16="","",INDEX(CATÁLOGO!$G$5:$G$39,AM16)) | AG16: =IF(AF16="","",IF(ISNUMBER(AF16),AF16*AV16,AF16)) | AH16: =IF(E16="","",C16&"|"&D16) | AI16: =IF(M16<>"Sí",0,SUMPRODUCT(MAX(($AH$5:AH15=AH16)*($M$5:M15="Sí")*ROW($AH$5:AH15)))) -> 0 | AJ16: =IF(M16<>"Sí","",IF(AL16=1,B16,INDEX($AJ:$AJ,AI16))) | AK16: =IF(M16<>"Sí","",IF(AL16=1,E16,INDEX($AK:$AK,AI16)+E16)) | AL16: =IF(M16<>"Sí","",IF(AI16=0,1,IF(INDEX($AN:$AN,AI16)=0,1,IF(B16>=EDATE(INDEX($AJ:$AJ,AI16),6),1,0)))) | AM16: =IF(D16="","",IFERROR(MATCH(D16,CATÁLOGO!$C$5:$C$39,0),"")) | AN16: =IF(M16<>"Sí","",IF(AND(ISNUMBER(AE16),AK16>=AE16),0,1)) | AO16: =IF(OR(E16="",C16="",NOT(ISNUMBER(B16))),"",SUMIFS($E$6:$E$505,$C$6:$C$505,C16,$B$6:$B$505,">="&DATE(YEAR(B16),MONTH(B16),1),$B$6:$B$505,"<"&DATE(YEAR(B16),MONTH(B16)+1,1))) | AP16: =IF(C16="","",IFERROR(INDEX(CLIENTES!$M$6:$M$305,MATCH(C16,CLIENTES!$A$6:$A$305,0)),"")) | AQ16: =IF(AND(ISNUMBER(AO16),ISNUMBER(AP16)),IF(AND(AP16>0,AO16>AP16),1,0),0) -> 0 | AR16: =IF(NOT(ISNUMBER(B16)),0,IF(B16<MAX($B$5:B15),1,0)) -> 0 | AS16: =IF(C16="","",IFERROR(INDEX(CLIENTES!$H$6:$H$305,MATCH(C16,CLIENTES!$A$6:$A$305,0)),"")) | AT16: =IF(AND(LEFT(P16,5)="AVISO",T16<>"Presentado",ISNUMBER(Q16)),Q16,"") | AU16: =IF(AND(D16="XVI - Activos virtuales (PSAV): operación de intercambio/transferencia",M16="Sí",ISNUMBER(AE16)),IF(AK16>=AE16,1,0),0) -> 0 | AV16: =IF(NOT(ISNUMBER(B16)),CONFIG!$B$4,IFERROR(INDEX(CONFIG!$I$5:$I$14,MATCH(IF(MONTH(B16)=1,YEAR(B16)-1,YEAR(B16)),CONFIG!$H$5:$H$14,0)),CONFIG!$B$4)) -> 117.31 | AW16: =IF(AND(LEFT(D16,4)="I - ",ISNUMBER(B16),C16<>""),SUMIFS($E$6:$E$505,$C$6:$C$505,C16,$D$6:$D$505,D16,$B$6:$B$505,">"&(B16-1),$B$6:$B$505,"<="&B16),0) -> 0 | AX16: =IF(E16="","",IF(AD16="Siempre","AVISO (siempre)",IF(AD16="No aplica","Sin Aviso (sólo preparas: Ley 17 XI)",IF(NOT(ISNUMBER(AE16)),"",IF(AA16<>"ACUMULA",IF(E16>=AE16,IF(AND(D16="XVI - Activos virtuales (PSAV): cobro de contraprestación (comisión) por el servicio",COUNTIFS($C$6:$C$505,C16,$B$6:$B$505,">="&INT(B16),$B$6:$B$505,"<"&(INT(B16)+1),$AU$6:$AU$505,1)>0),"En el Aviso del inciso a) (R 31 Bis)","AVISO"),"—"),IF(M16<>"Sí","—",IF(AK16>=AE16,IF(AK16=E16,"AVISO","AVISO (acumulado)"),"Acumulando")))))))
A17: =IF(E17="","",ROW()-5) | I17: =IF(C17="","",IFERROR(INDEX(CLIENTES!$B$6:$B$305,MATCH(C17,CLIENTES!$A$6:$A$305,0)),"⚠ ID no registrado")) | J17: =IF(C17="","",IFERROR(INDEX(CLIENTES!$Z$6:$Z$305,MATCH(C17,CLIENTES!$A$6:$A$305,0)),"")) | K17: =IF(E17="","",IF(AB17="Siempre","Sí",IF(ISNUMBER(AC17),IF(E17>=AC17,"Sí",IF(AW17>=AC17,"Sí (serie 24 h)","No")),""))) | L17: =IF(E17="","",AA17) | M17: =IF(E17="","",IF(AA17<>"ACUMULA","No aplica",IF(LEFT(K17,2)="Sí","Sí","No"))) | N17: =IF(M17="Sí",AJ17,"") | O17: =IF(M17="Sí",AK17,"") | P17: =IF(AND(LEFT(D17,6)="XIV - ",LEFT(AX17,5)="AVISO"),"Pedimento (R 16): no va al SPPLD",AX17) | Q17: =IF(LEFT(P17,5)="AVISO",IF(ISNUMBER(B17),DATE(YEAR(B17),MONTH(B17)+1,17),"Falta fecha"),"") | R17: =IF(OR(F17="",F17=0),"",IF(ISNUMBER(AG17),IF(F17>=AG17,"PROHIBIDO","Dentro del límite"),"No aplica")) | S17: =IF(E17="","",MID(IF(AQ17=1," · Excede el perfil declarado","")&IF(H17="Sí"," · Paga un tercero","")&IF(J17="Alto"," · Cliente de riesgo alto: DDR (RCG 23 Ter 3 y 4)","")&IF(AND(AS17<>"",AS17<>"No",AS17<>0)," · PEP","")&IF(R17="PROHIBIDO"," · Efectivo prohibido: no lo recibas (Art. 32)","")&IF(AR17=1," · ⚠ Fecha fuera de orden","")&IF(LEFT(I17,1)="⚠"," · ⚠ Cliente no registrado","")&IF(D17=""," · ⚠ Falta la actividad","")&IF(AND(LEFT(P17,5)="AVISO",W17="")," · Captura la cifra total con IVA para el Aviso","")&IF(AND(ISNUMBER(W17),W17<E17)," · ⚠ La cifra con IVA es menor que el monto sin IVA",""),4,400)) | V17: =IF(LEFT(P17,5)<>"AVISO","",IF(T17="Presentado",IF(AND(ISNUMBER(U17),ISNUMBER(Q17),U17>Q17),"Presentado tarde","Presentado"),IF(NOT(ISNUMBER(Q17)),"Falta fecha",IF(Q17<CONFIG!$B$6,"VENCIDO","Vence en "&(Q17-CONFIG!$B$6)&" días")))) | AA17: =IF(AM17="","",INDEX(CATÁLOGO!$D$5:$D$39,AM17)) | AB17: =IF(AM17="","",INDEX(CATÁLOGO!$E$5:$E$39,AM17)) | AC17: =IF(AB17="","",IF(ISNUMBER(AB17),AB17*AV17,AB17)) | AD17: =IF(AM17="","",INDEX(CATÁLOGO!$F$5:$F$39,AM17)) | AE17: =IF(AD17="","",IF(ISNUMBER(AD17),AD17*AV17,AD17)) | AF17: =IF(AM17="","",INDEX(CATÁLOGO!$G$5:$G$39,AM17)) | AG17: =IF(AF17="","",IF(ISNUMBER(AF17),AF17*AV17,AF17)) | AH17: =IF(E17="","",C17&"|"&D17) | AI17: =IF(M17<>"Sí",0,SUMPRODUCT(MAX(($AH$5:AH16=AH17)*($M$5:M16="Sí")*ROW($AH$5:AH16)))) -> 0 | AJ17: =IF(M17<>"Sí","",IF(AL17=1,B17,INDEX($AJ:$AJ,AI17))) | AK17: =IF(M17<>"Sí","",IF(AL17=1,E17,INDEX($AK:$AK,AI17)+E17)) | AL17: =IF(M17<>"Sí","",IF(AI17=0,1,IF(INDEX($AN:$AN,AI17)=0,1,IF(B17>=EDATE(INDEX($AJ:$AJ,AI17),6),1,0)))) | AM17: =IF(D17="","",IFERROR(MATCH(D17,CATÁLOGO!$C$5:$C$39,0),"")) | AN17: =IF(M17<>"Sí","",IF(AND(ISNUMBER(AE17),AK17>=AE17),0,1)) | AO17: =IF(OR(E17="",C17="",NOT(ISNUMBER(B17))),"",SUMIFS($E$6:$E$505,$C$6:$C$505,C17,$B$6:$B$505,">="&DATE(YEAR(B17),MONTH(B17),1),$B$6:$B$505,"<"&DATE(YEAR(B17),MONTH(B17)+1,1))) | AP17: =IF(C17="","",IFERROR(INDEX(CLIENTES!$M$6:$M$305,MATCH(C17,CLIENTES!$A$6:$A$305,0)),"")) | AQ17: =IF(AND(ISNUMBER(AO17),ISNUMBER(AP17)),IF(AND(AP17>0,AO17>AP17),1,0),0) -> 0 | AR17: =IF(NOT(ISNUMBER(B17)),0,IF(B17<MAX($B$5:B16),1,0)) -> 0 | AS17: =IF(C17="","",IFERROR(INDEX(CLIENTES!$H$6:$H$305,MATCH(C17,CLIENTES!$A$6:$A$305,0)),"")) | AT17: =IF(AND(LEFT(P17,5)="AVISO",T17<>"Presentado",ISNUMBER(Q17)),Q17,"") | AU17: =IF(AND(D17="XVI - Activos virtuales (PSAV): operación de intercambio/transferencia",M17="Sí",ISNUMBER(AE17)),IF(AK17>=AE17,1,0),0) -> 0 | AV17: =IF(NOT(ISNUMBER(B17)),CONFIG!$B$4,IFERROR(INDEX(CONFIG!$I$5:$I$14,MATCH(IF(MONTH(B17)=1,YEAR(B17)-1,YEAR(B17)),CONFIG!$H$5:$H$14,0)),CONFIG!$B$4)) -> 117.31 | AW17: =IF(AND(LEFT(D17,4)="I - ",ISNUMBER(B17),C17<>""),SUMIFS($E$6:$E$505,$C$6:$C$505,C17,$D$6:$D$505,D17,$B$6:$B$505,">"&(B17-1),$B$6:$B$505,"<="&B17),0) -> 0 | AX17: =IF(E17="","",IF(AD17="Siempre","AVISO (siempre)",IF(AD17="No aplica","Sin Aviso (sólo preparas: Ley 17 XI)",IF(NOT(ISNUMBER(AE17)),"",IF(AA17<>"ACUMULA",IF(E17>=AE17,IF(AND(D17="XVI - Activos virtuales (PSAV): cobro de contraprestación (comisión) por el servicio",COUNTIFS($C$6:$C$505,C17,$B$6:$B$505,">="&INT(B17),$B$6:$B$505,"<"&(INT(B17)+1),$AU$6:$AU$505,1)>0),"En el Aviso del inciso a) (R 31 Bis)","AVISO"),"—"),IF(M17<>"Sí","—",IF(AK17>=AE17,IF(AK17=E17,"AVISO","AVISO (acumulado)"),"Acumulando")))))))
A18: =IF(E18="","",ROW()-5) | I18: =IF(C18="","",IFERROR(INDEX(CLIENTES!$B$6:$B$305,MATCH(C18,CLIENTES!$A$6:$A$305,0)),"⚠ ID no registrado")) | J18: =IF(C18="","",IFERROR(INDEX(CLIENTES!$Z$6:$Z$305,MATCH(C18,CLIENTES!$A$6:$A$305,0)),"")) | K18: =IF(E18="","",IF(AB18="Siempre","Sí",IF(ISNUMBER(AC18),IF(E18>=AC18,"Sí",IF(AW18>=AC18,"Sí (serie 24 h)","No")),""))) | L18: =IF(E18="","",AA18) | M18: =IF(E18="","",IF(AA18<>"ACUMULA","No aplica",IF(LEFT(K18,2)="Sí","Sí","No"))) | N18: =IF(M18="Sí",AJ18,"") | O18: =IF(M18="Sí",AK18,"") | P18: =IF(AND(LEFT(D18,6)="XIV - ",LEFT(AX18,5)="AVISO"),"Pedimento (R 16): no va al SPPLD",AX18) | Q18: =IF(LEFT(P18,5)="AVISO",IF(ISNUMBER(B18),DATE(YEAR(B18),MONTH(B18)+1,17),"Falta fecha"),"") | R18: =IF(OR(F18="",F18=0),"",IF(ISNUMBER(AG18),IF(F18>=AG18,"PROHIBIDO","Dentro del límite"),"No aplica")) | S18: =IF(E18="","",MID(IF(AQ18=1," · Excede el perfil declarado","")&IF(H18="Sí"," · Paga un tercero","")&IF(J18="Alto"," · Cliente de riesgo alto: DDR (RCG 23 Ter 3 y 4)","")&IF(AND(AS18<>"",AS18<>"No",AS18<>0)," · PEP","")&IF(R18="PROHIBIDO"," · Efectivo prohibido: no lo recibas (Art. 32)","")&IF(AR18=1," · ⚠ Fecha fuera de orden","")&IF(LEFT(I18,1)="⚠"," · ⚠ Cliente no registrado","")&IF(D18=""," · ⚠ Falta la actividad","")&IF(AND(LEFT(P18,5)="AVISO",W18="")," · Captura la cifra total con IVA para el Aviso","")&IF(AND(ISNUMBER(W18),W18<E18)," · ⚠ La cifra con IVA es menor que el monto sin IVA",""),4,400)) | V18: =IF(LEFT(P18,5)<>"AVISO","",IF(T18="Presentado",IF(AND(ISNUMBER(U18),ISNUMBER(Q18),U18>Q18),"Presentado tarde","Presentado"),IF(NOT(ISNUMBER(Q18)),"Falta fecha",IF(Q18<CONFIG!$B$6,"VENCIDO","Vence en "&(Q18-CONFIG!$B$6)&" días")))) | AA18: =IF(AM18="","",INDEX(CATÁLOGO!$D$5:$D$39,AM18)) | AB18: =IF(AM18="","",INDEX(CATÁLOGO!$E$5:$E$39,AM18)) | AC18: =IF(AB18="","",IF(ISNUMBER(AB18),AB18*AV18,AB18)) | AD18: =IF(AM18="","",INDEX(CATÁLOGO!$F$5:$F$39,AM18)) | AE18: =IF(AD18="","",IF(ISNUMBER(AD18),AD18*AV18,AD18)) | AF18: =IF(AM18="","",INDEX(CATÁLOGO!$G$5:$G$39,AM18)) | AG18: =IF(AF18="","",IF(ISNUMBER(AF18),AF18*AV18,AF18)) | AH18: =IF(E18="","",C18&"|"&D18) | AI18: =IF(M18<>"Sí",0,SUMPRODUCT(MAX(($AH$5:AH17=AH18)*($M$5:M17="Sí")*ROW($AH$5:AH17)))) -> 0 | AJ18: =IF(M18<>"Sí","",IF(AL18=1,B18,INDEX($AJ:$AJ,AI18))) | AK18: =IF(M18<>"Sí","",IF(AL18=1,E18,INDEX($AK:$AK,AI18)+E18)) | AL18: =IF(M18<>"Sí","",IF(AI18=0,1,IF(INDEX($AN:$AN,AI18)=0,1,IF(B18>=EDATE(INDEX($AJ:$AJ,AI18),6),1,0)))) | AM18: =IF(D18="","",IFERROR(MATCH(D18,CATÁLOGO!$C$5:$C$39,0),"")) | AN18: =IF(M18<>"Sí","",IF(AND(ISNUMBER(AE18),AK18>=AE18),0,1)) | AO18: =IF(OR(E18="",C18="",NOT(ISNUMBER(B18))),"",SUMIFS($E$6:$E$505,$C$6:$C$505,C18,$B$6:$B$505,">="&DATE(YEAR(B18),MONTH(B18),1),$B$6:$B$505,"<"&DATE(YEAR(B18),MONTH(B18)+1,1))) | AP18: =IF(C18="","",IFERROR(INDEX(CLIENTES!$M$6:$M$305,MATCH(C18,CLIENTES!$A$6:$A$305,0)),"")) | AQ18: =IF(AND(ISNUMBER(AO18),ISNUMBER(AP18)),IF(AND(AP18>0,AO18>AP18),1,0),0) -> 0 | AR18: =IF(NOT(ISNUMBER(B18)),0,IF(B18<MAX($B$5:B17),1,0)) -> 0 | AS18: =IF(C18="","",IFERROR(INDEX(CLIENTES!$H$6:$H$305,MATCH(C18,CLIENTES!$A$6:$A$305,0)),"")) | AT18: =IF(AND(LEFT(P18,5)="AVISO",T18<>"Presentado",ISNUMBER(Q18)),Q18,"") | AU18: =IF(AND(D18="XVI - Activos virtuales (PSAV): operación de intercambio/transferencia",M18="Sí",ISNUMBER(AE18)),IF(AK18>=AE18,1,0),0) -> 0 | AV18: =IF(NOT(ISNUMBER(B18)),CONFIG!$B$4,IFERROR(INDEX(CONFIG!$I$5:$I$14,MATCH(IF(MONTH(B18)=1,YEAR(B18)-1,YEAR(B18)),CONFIG!$H$5:$H$14,0)),CONFIG!$B$4)) -> 117.31 | AW18: =IF(AND(LEFT(D18,4)="I - ",ISNUMBER(B18),C18<>""),SUMIFS($E$6:$E$505,$C$6:$C$505,C18,$D$6:$D$505,D18,$B$6:$B$505,">"&(B18-1),$B$6:$B$505,"<="&B18),0) -> 0 | AX18: =IF(E18="","",IF(AD18="Siempre","AVISO (siempre)",IF(AD18="No aplica","Sin Aviso (sólo preparas: Ley 17 XI)",IF(NOT(ISNUMBER(AE18)),"",IF(AA18<>"ACUMULA",IF(E18>=AE18,IF(AND(D18="XVI - Activos virtuales (PSAV): cobro de contraprestación (comisión) por el servicio",COUNTIFS($C$6:$C$505,C18,$B$6:$B$505,">="&INT(B18),$B$6:$B$505,"<"&(INT(B18)+1),$AU$6:$AU$505,1)>0),"En el Aviso del inciso a) (R 31 Bis)","AVISO"),"—"),IF(M18<>"Sí","—",IF(AK18>=AE18,IF(AK18=E18,"AVISO","AVISO (acumulado)"),"Acumulando")))))))
... A505: =IF(E505="","",ROW()-5) | I505: =IF(C505="","",IFERROR(INDEX(CLIENTES!$B$6:$B$305,MATCH(C505,CLIENTES!$A$6:$A$305,0)),"⚠ ID no registrado")) | J505: =IF(C505="","",IFERROR(INDEX(CLIENTES!$Z$6:$Z$305,MATCH(C505,CLIENTES!$A$6:$A$305,0)),"")) | K505: =IF(E505="","",IF(AB505="Siempre","Sí",IF(ISNUMBER(AC505),IF(E505>=AC505,"Sí",IF(AW505>=AC505,"Sí (serie 24 h)","No")),""))) | L505: =IF(E505="","",AA505) | M505: =IF(E505="","",IF(AA505<>"ACUMULA","No aplica",IF(LEFT(K505,2)="Sí","Sí","No"))) | N505: =IF(M505="Sí",AJ505,"") | O505: =IF(M505="Sí",AK505,"") | P505: =IF(AND(LEFT(D505,6)="XIV - ",LEFT(AX505,5)="AVISO"),"Pedimento (R 16): no va al SPPLD",AX505) | Q505: =IF(LEFT(P505,5)="AVISO",IF(ISNUMBER(B505),DATE(YEAR(B505),MONTH(B505)+1,17),"Falta fecha"),"") | R505: =IF(OR(F505="",F505=0),"",IF(ISNUMBER(AG505),IF(F505>=AG505,"PROHIBIDO","Dentro del límite"),"No aplica")) | S505: =IF(E505="","",MID(IF(AQ505=1," · Excede el perfil declarado","")&IF(H505="Sí"," · Paga un tercero","")&IF(J505="Alto"," · Cliente de riesgo alto: DDR (RCG 23 Ter 3 y 4)","")&IF(AND(AS505<>"",AS505<>"No",AS505<>0)," · PEP","")&IF(R505="PROHIBIDO"," · Efectivo prohibido: no lo recibas (Art. 32)","")&IF(AR505=1," · ⚠ Fecha fuera de orden","")&IF(LEFT(I505,1)="⚠"," · ⚠ Cliente no registrado","")&IF(D505=""," · ⚠ Falta la actividad","")&IF(AND(LEFT(P505,5)="AVISO",W505="")," · Captura la cifra total con IVA para el Aviso","")&IF(AND(ISNUMBER(W505),W505<E505)," · ⚠ La cifra con IVA es menor que el monto sin IVA",""),4,400)) | V505: =IF(LEFT(P505,5)<>"AVISO","",IF(T505="Presentado",IF(AND(ISNUMBER(U505),ISNUMBER(Q505),U505>Q505),"Presentado tarde","Presentado"),IF(NOT(ISNUMBER(Q505)),"Falta fecha",IF(Q505<CONFIG!$B$6,"VENCIDO","Vence en "&(Q505-CONFIG!$B$6)&" días")))) | AA505: =IF(AM505="","",INDEX(CATÁLOGO!$D$5:$D$39,AM505)) | AB505: =IF(AM505="","",INDEX(CATÁLOGO!$E$5:$E$39,AM505)) | AC505: =IF(AB505="","",IF(ISNUMBER(AB505),AB505*AV505,AB505)) | AD505: =IF(AM505="","",INDEX(CATÁLOGO!$F$5:$F$39,AM505)) | AE505: =IF(AD505="","",IF(ISNUMBER(AD505),AD505*AV505,AD505)) | AF505: =IF(AM505="","",INDEX(CATÁLOGO!$G$5:$G$39,AM505)) | AG505: =IF(AF505="","",IF(ISNUMBER(AF505),AF505*AV505,AF505)) | AH505: =IF(E505="","",C505&"|"&D505) | AI505: =IF(M505<>"Sí",0,SUMPRODUCT(MAX(($AH$5:AH504=AH505)*($M$5:M504="Sí")*ROW($AH$5:AH504)))) -> 0 | AJ505: =IF(M505<>"Sí","",IF(AL505=1,B505,INDEX($AJ:$AJ,AI505))) | AK505: =IF(M505<>"Sí","",IF(AL505=1,E505,INDEX($AK:$AK,AI505)+E505)) | AL505: =IF(M505<>"Sí","",IF(AI505=0,1,IF(INDEX($AN:$AN,AI505)=0,1,IF(B505>=EDATE(INDEX($AJ:$AJ,AI505),6),1,0)))) | AM505: =IF(D505="","",IFERROR(MATCH(D505,CATÁLOGO!$C$5:$C$39,0),"")) | AN505: =IF(M505<>"Sí","",IF(AND(ISNUMBER(AE505),AK505>=AE505),0,1)) | AO505: =IF(OR(E505="",C505="",NOT(ISNUMBER(B505))),"",SUMIFS($E$6:$E$505,$C$6:$C$505,C505,$B$6:$B$505,">="&DATE(YEAR(B505),MONTH(B505),1),$B$6:$B$505,"<"&DATE(YEAR(B505),MONTH(B505)+1,1))) | AP505: =IF(C505="","",IFERROR(INDEX(CLIENTES!$M$6:$M$305,MATCH(C505,CLIENTES!$A$6:$A$305,0)),"")) | AQ505: =IF(AND(ISNUMBER(AO505),ISNUMBER(AP505)),IF(AND(AP505>0,AO505>AP505),1,0),0) -> 0 | AR505: =IF(NOT(ISNUMBER(B505)),0,IF(B505<MAX($B$5:B504),1,0)) -> 0 | AS505: =IF(C505="","",IFERROR(INDEX(CLIENTES!$H$6:$H$305,MATCH(C505,CLIENTES!$A$6:$A$305,0)),"")) | AT505: =IF(AND(LEFT(P505,5)="AVISO",T505<>"Presentado",ISNUMBER(Q505)),Q505,"") | AU505: =IF(AND(D505="XVI - Activos virtuales (PSAV): operación de intercambio/transferencia",M505="Sí",ISNUMBER(AE505)),IF(AK505>=AE505,1,0),0) -> 0 | AV505: =IF(NOT(ISNUMBER(B505)),CONFIG!$B$4,IFERROR(INDEX(CONFIG!$I$5:$I$14,MATCH(IF(MONTH(B505)=1,YEAR(B505)-1,YEAR(B505)),CONFIG!$H$5:$H$14,0)),CONFIG!$B$4)) -> 117.31 | AW505: =IF(AND(LEFT(D505,4)="I - ",ISNUMBER(B505),C505<>""),SUMIFS($E$6:$E$505,$C$6:$C$505,C505,$D$6:$D$505,D505,$B$6:$B$505,">"&(B505-1),$B$6:$B$505,"<="&B505),0) -> 0 | AX505: =IF(E505="","",IF(AD505="Siempre","AVISO (siempre)",IF(AD505="No aplica","Sin Aviso (sólo preparas: Ley 17 XI)",IF(NOT(ISNUMBER(AE505)),"",IF(AA505<>"ACUMULA",IF(E505>=AE505,IF(AND(D505="XVI - Activos virtuales (PSAV): cobro de contraprestación (comisión) por el servicio",COUNTIFS($C$6:$C$505,C505,$B$6:$B$505,">="&INT(B505),$B$6:$B$505,"<"&(INT(B505)+1),$AU$6:$AU$505,1)>0),"En el Aviso del inciso a) (R 31 Bis)","AVISO"),"—"),IF(M505<>"Sí","—",IF(AK505>=AE505,IF(AK505=E505,"AVISO","AVISO (acumulado)"),"Acumulando")))))))

Sheet CLIENTES
A1: CLIENTES — Expediente, perfil y grado de riesgo
A2: Un renglón por cliente. Captura lo amarillo; el grado de riesgo, la próxima evaluación, la verificación anual y los pendientes se calculan solos (RCG 12, 21, 23 Bis a 23 Ter 1 y 23 Quinquies). El renglón EJEMPLO-01 muestra el formato: bórralo cuando captures tus clientes.
A5: ID cliente | B5: Nombre o razón social | C5: Tipo de persona | D5: RFC | E5: Residencia | F5: Nacionalidad | G5: ¿Vinculado a jurisdicción de riesgo? | H5: PEP | I5: ¿En listas? | J5: Riesgo de su actividad económica | K5: Canal | L5: Origen de recursos documentado | M5: Perfil: monto máximo mensual declarado | N5: Fecha de alta | O5: Fecha última evaluación de riesgo | P5: ¿Expediente completo? | Q5: Beneficiario Controlador | R5: Fecha comprobante de domicilio | S5: Fecha última verificación anual | T5: Ajuste del REC (opcional) | U5: Justificación del ajuste | V5: Puntaje inherente | W5: Puntaje transaccional | X5: Puntaje total | Y5: Grado calculado | Z5: GRADO FINAL | AA5: Motivo del grado | AB5: Próxima evaluación de riesgo | AC5: Próxima verificación del expediente | AD5: Pendientes | AE5: Semáforo | AF5: Operaciones / monto
A6: EJEMPLO-01 | B6: Comercializadora Ejemplo, S.A. de C.V. | C6: Persona moral | D6: CEJ200101AB1 | E6: Residente en México | F6: Mexicana | G6: No | H6: No | I6: No | J6: Medio | K6: Presencial | L6: Sí | M6: 250000 | N6: 46083 | O6: 46083 | P6: Sí | Q6: Identificado | R6: 46073 | S6: 46083 | V6: =IF(A6="","",SUMIFS(CONFIG!$F$5:$F$26,CONFIG!$D$5:$D$26,"Tipo de persona",CONFIG!$E$5:$E$26,C6)+SUMIFS(CONFIG!$F$5:$F$26,CONFIG!$D$5:$D$26,"Residencia",CONFIG!$E$5:$E$26,E6)+SUMIFS(CONFIG!$F$5:$F$26,CONFIG!$D$5:$D$26,"Nacionalidad",CONFIG!$E$5:$E$26,F6)+SUMIFS(CONFIG!$F$5:$F$26,CONFIG!$D$5:$D$26,"Jurisdicción de riesgo",CONFIG!$E$5:$E$26,G6)+SUMIFS(CONFIG!$F$5:$F$26,CONFIG!$D$5:$D$26,"PEP",CONFIG!$E$5:$E$26,H6)+SUMIFS(CONFIG!$F$5:$F$26,CONFIG!$D$5:$D$26,"En listas",CONFIG!$E$5:$E$26,I6)+SUMIFS(CONFIG!$F$5:$F$26,CONFIG!$D$5:$D$26,"Riesgo de su actividad económica",CONFIG!$E$5:$E$26,J6)+SUMIFS(CONFIG!$F$5:$F$26,CONFIG!$D$5:$D$26,"Canal",CONFIG!$E$5:$E$26,K6)+SUMIFS(CONFIG!$F$5:$F$26,CONFIG!$D$5:$D$26,"Origen de recursos documentado",CONFIG!$E$5:$E$26,L6)) -> 4 | W6: =IF(A6="","",IF(SUMIF(OPERACIONES!$C$6:$C$505,A6,OPERACIONES!$E$6:$E$505)>0,IF(SUMIF(OPERACIONES!$C$6:$C$505,A6,OPERACIONES!$F$6:$F$505)/SUMIF(OPERACIONES!$C$6:$C$505,A6,OPERACIONES!$E$6:$E$505)>0.5,CONFIG!$B$20,IF(SUMIF(OPERACIONES!$C$6:$C$505,A6,OPERACIONES!$F$6:$F$505)>0,CONFIG!$B$21,0)),0)+IF(COUNTIFS(OPERACIONES!$C$6:$C$505,A6,OPERACIONES!$AQ$6:$AQ$505,1)>0,CONFIG!$B$22,0)+IF(COUNTIFS(OPERACIONES!$C$6:$C$505,A6,OPERACIONES!$H$6:$H$505,"Sí")>0,CONFIG!$B$23,0)) -> 0 | X6: =IF(A6="","",V6+W6) -> 4 | Y6: =IF(A6="","",IF(X6<=CONFIG!$B$13,"Bajo",IF(X6<=CONFIG!$B$14,"Medio","Alto"))) -> Medio | Z6: =IF(A6="","",IF(OR(H6="Extranjera",AND(E6="No residente",G6="Sí"),I6="Sí"),"Alto",IF(T6<>"",T6,Y6))) -> Medio | AA6: =IF(A6="","",IF(H6="Extranjera","Alto obligatorio: PEP extranjera (RCG 23 Bis 4)",IF(AND(E6="No residente",G6="Sí"),"Alto obligatorio: no residente vinculado a jurisdicción de riesgo (RCG 23 Bis 4)",IF(I6="Sí","Alto por criterio: persona en listas. Evalúa no operar y Aviso de 24 h",IF(T6<>"","Ajuste del REC: "&U6,"Modelo: "&X6&" puntos"))))) -> Modelo: 4 puntos | AB6: =IF(A6="","",IF(COUNT(N6,O6)=0,"Falta fecha",EDATE(MAX(N6,O6),IF(Z6="Alto",CONFIG!$B$18,IF(Z6="Medio",CONFIG!$B$17,CONFIG!$B$16))))) -> 46267 | AC6: =IF(A6="","",IF(ISNUMBER(S6),EDATE(S6,12),IF(ISNUMBER(N6),EDATE(N6,12),"Falta fecha"))) -> 46448 | AD6: =IF(A6="","",MID(IF(P6<>"Sí"," · Expediente incompleto","")&IF(OR(Q6="",Q6="Pendiente")," · Falta el Beneficiario Controlador","")&IF(M6=""," · Sin perfil transaccional","")&IF(AND(ISNUMBER(AB6),AB6<CONFIG!$B$6)," · Evaluación de riesgo vencida","")&IF(AND(ISNUMBER(AC6),AC6<CONFIG!$B$6)," · Verificación anual vencida","")&IF(AND(ISNUMBER(R6),ISNUMBER(S6),S6-R6>92)," · Comprobante de domicilio con más de 3 meses","")&IF(AND(T6<>"",U6="")," · Ajuste del REC sin justificación",""),4,400)) -> Evaluación de riesgo vencida | AE6: =IF(A6="","",IF(AD6="","Al día","Revisar")) -> Revisar | AF6: =IF(A6="","",COUNTIF(OPERACIONES!$C$6:$C$505,A6)&" / $"&FIXED(SUMIF(OPERACIONES!$C$6:$C$505,A6,OPERACIONES!$E$6:$E$505),0)) -> 1 / $120,000
V7: =IF(A7="","",SUMIFS(CONFIG!$F$5:$F$26,CONFIG!$D$5:$D$26,"Tipo de persona",CONFIG!$E$5:$E$26,C7)+SUMIFS(CONFIG!$F$5:$F$26,CONFIG!$D$5:$D$26,"Residencia",CONFIG!$E$5:$E$26,E7)+SUMIFS(CONFIG!$F$5:$F$26,CONFIG!$D$5:$D$26,"Nacionalidad",CONFIG!$E$5:$E$26,F7)+SUMIFS(CONFIG!$F$5:$F$26,CONFIG!$D$5:$D$26,"Jurisdicción de riesgo",CONFIG!$E$5:$E$26,G7)+SUMIFS(CONFIG!$F$5:$F$26,CONFIG!$D$5:$D$26,"PEP",CONFIG!$E$5:$E$26,H7)+SUMIFS(CONFIG!$F$5:$F$26,CONFIG!$D$5:$D$26,"En listas",CONFIG!$E$5:$E$26,I7)+SUMIFS(CONFIG!$F$5:$F$26,CONFIG!$D$5:$D$26,"Riesgo de su actividad económica",CONFIG!$E$5:$E$26,J7)+SUMIFS(CONFIG!$F$5:$F$26,CONFIG!$D$5:$D$26,"Canal",CONFIG!$E$5:$E$26,K7)+SUMIFS(CONFIG!$F$5:$F$26,CONFIG!$D$5:$D$26,"Origen de recursos documentado",CONFIG!$E$5:$E$26,L7)) | W7: =IF(A7="","",IF(SUMIF(OPERACIONES!$C$6:$C$505,A7,OPERACIONES!$E$6:$E$505)>0,IF(SUMIF(OPERACIONES!$C$6:$C$505,A7,OPERACIONES!$F$6:$F$505)/SUMIF(OPERACIONES!$C$6:$C$505,A7,OPERACIONES!$E$6:$E$505)>0.5,CONFIG!$B$20,IF(SUMIF(OPERACIONES!$C$6:$C$505,A7,OPERACIONES!$F$6:$F$505)>0,CONFIG!$B$21,0)),0)+IF(COUNTIFS(OPERACIONES!$C$6:$C$505,A7,OPERACIONES!$AQ$6:$AQ$505,1)>0,CONFIG!$B$22,0)+IF(COUNTIFS(OPERACIONES!$C$6:$C$505,A7,OPERACIONES!$H$6:$H$505,"Sí")>0,CONFIG!$B$23,0)) | X7: =IF(A7="","",V7+W7) | Y7: =IF(A7="","",IF(X7<=CONFIG!$B$13,"Bajo",IF(X7<=CONFIG!$B$14,"Medio","Alto"))) | Z7: =IF(A7="","",IF(OR(H7="Extranjera",AND(E7="No residente",G7="Sí"),I7="Sí"),"Alto",IF(T7<>"",T7,Y7))) | AA7: =IF(A7="","",IF(H7="Extranjera","Alto obligatorio: PEP extranjera (RCG 23 Bis 4)",IF(AND(E7="No residente",G7="Sí"),"Alto obligatorio: no residente vinculado a jurisdicción de riesgo (RCG 23 Bis 4)",IF(I7="Sí","Alto por criterio: persona en listas. Evalúa no operar y Aviso de 24 h",IF(T7<>"","Ajuste del REC: "&U7,"Modelo: "&X7&" puntos"))))) | AB7: =IF(A7="","",IF(COUNT(N7,O7)=0,"Falta fecha",EDATE(MAX(N7,O7),IF(Z7="Alto",CONFIG!$B$18,IF(Z7="Medio",CONFIG!$B$17,CONFIG!$B$16))))) | AC7: =IF(A7="","",IF(ISNUMBER(S7),EDATE(S7,12),IF(ISNUMBER(N7),EDATE(N7,12),"Falta fecha"))) | AD7: =IF(A7="","",MID(IF(P7<>"Sí"," · Expediente incompleto","")&IF(OR(Q7="",Q7="Pendiente")," · Falta el Beneficiario Controlador","")&IF(M7=""," · Sin perfil transaccional","")&IF(AND(ISNUMBER(AB7),AB7<CONFIG!$B$6)," · Evaluación de riesgo vencida","")&IF(AND(ISNUMBER(AC7),AC7<CONFIG!$B$6)," · Verificación anual vencida","")&IF(AND(ISNUMBER(R7),ISNUMBER(S7),S7-R7>92)," · Comprobante de domicilio con más de 3 meses","")&IF(AND(T7<>"",U7="")," · Ajuste del REC sin justificación",""),4,400)) | AE7: =IF(A7="","",IF(AD7="","Al día","Revisar")) | AF7: =IF(A7="","",COUNTIF(OPERACIONES!$C$6:$C$505,A7)&" / $"&FIXED(SUMIF(OPERACIONES!$C$6:$C$505,A7,OPERACIONES!$E$6:$E$505),0))
V8: =IF(A8="","",SUMIFS(CONFIG!$F$5:$F$26,CONFIG!$D$5:$D$26,"Tipo de persona",CONFIG!$E$5:$E$26,C8)+SUMIFS(CONFIG!$F$5:$F$26,CONFIG!$D$5:$D$26,"Residencia",CONFIG!$E$5:$E$26,E8)+SUMIFS(CONFIG!$F$5:$F$26,CONFIG!$D$5:$D$26,"Nacionalidad",CONFIG!$E$5:$E$26,F8)+SUMIFS(CONFIG!$F$5:$F$26,CONFIG!$D$5:$D$26,"Jurisdicción de riesgo",CONFIG!$E$5:$E$26,G8)+SUMIFS(CONFIG!$F$5:$F$26,CONFIG!$D$5:$D$26,"PEP",CONFIG!$E$5:$E$26,H8)+SUMIFS(CONFIG!$F$5:$F$26,CONFIG!$D$5:$D$26,"En listas",CONFIG!$E$5:$E$26,I8)+SUMIFS(CONFIG!$F$5:$F$26,CONFIG!$D$5:$D$26,"Riesgo de su actividad económica",CONFIG!$E$5:$E$26,J8)+SUMIFS(CONFIG!$F$5:$F$26,CONFIG!$D$5:$D$26,"Canal",CONFIG!$E$5:$E$26,K8)+SUMIFS(CONFIG!$F$5:$F$26,CONFIG!$D$5:$D$26,"Origen de recursos documentado",CONFIG!$E$5:$E$26,L8)) | W8: =IF(A8="","",IF(SUMIF(OPERACIONES!$C$6:$C$505,A8,OPERACIONES!$E$6:$E$505)>0,IF(SUMIF(OPERACIONES!$C$6:$C$505,A8,OPERACIONES!$F$6:$F$505)/SUMIF(OPERACIONES!$C$6:$C$505,A8,OPERACIONES!$E$6:$E$505)>0.5,CONFIG!$B$20,IF(SUMIF(OPERACIONES!$C$6:$C$505,A8,OPERACIONES!$F$6:$F$505)>0,CONFIG!$B$21,0)),0)+IF(COUNTIFS(OPERACIONES!$C$6:$C$505,A8,OPERACIONES!$AQ$6:$AQ$505,1)>0,CONFIG!$B$22,0)+IF(COUNTIFS(OPERACIONES!$C$6:$C$505,A8,OPERACIONES!$H$6:$H$505,"Sí")>0,CONFIG!$B$23,0)) | X8: =IF(A8="","",V8+W8) | Y8: =IF(A8="","",IF(X8<=CONFIG!$B$13,"Bajo",IF(X8<=CONFIG!$B$14,"Medio","Alto"))) | Z8: =IF(A8="","",IF(OR(H8="Extranjera",AND(E8="No residente",G8="Sí"),I8="Sí"),"Alto",IF(T8<>"",T8,Y8))) | AA8: =IF(A8="","",IF(H8="Extranjera","Alto obligatorio: PEP extranjera (RCG 23 Bis 4)",IF(AND(E8="No residente",G8="Sí"),"Alto obligatorio: no residente vinculado a jurisdicción de riesgo (RCG 23 Bis 4)",IF(I8="Sí","Alto por criterio: persona en listas. Evalúa no operar y Aviso de 24 h",IF(T8<>"","Ajuste del REC: "&U8,"Modelo: "&X8&" puntos"))))) | AB8: =IF(A8="","",IF(COUNT(N8,O8)=0,"Falta fecha",EDATE(MAX(N8,O8),IF(Z8="Alto",CONFIG!$B$18,IF(Z8="Medio",CONFIG!$B$17,CONFIG!$B$16))))) | AC8: =IF(A8="","",IF(ISNUMBER(S8),EDATE(S8,12),IF(ISNUMBER(N8),EDATE(N8,12),"Falta fecha"))) | AD8: =IF(A8="","",MID(IF(P8<>"Sí"," · Expediente incompleto","")&IF(OR(Q8="",Q8="Pendiente")," · Falta el Beneficiario Controlador","")&IF(M8=""," · Sin perfil transaccional","")&IF(AND(ISNUMBER(AB8),AB8<CONFIG!$B$6)," · Evaluación de riesgo vencida","")&IF(AND(ISNUMBER(AC8),AC8<CONFIG!$B$6)," · Verificación anual vencida","")&IF(AND(ISNUMBER(R8),ISNUMBER(S8),S8-R8>92)," · Comprobante de domicilio con más de 3 meses","")&IF(AND(T8<>"",U8="")," · Ajuste del REC sin justificación",""),4,400)) | AE8: =IF(A8="","",IF(AD8="","Al día","Revisar")) | AF8: =IF(A8="","",COUNTIF(OPERACIONES!$C$6:$C$505,A8)&" / $"&FIXED(SUMIF(OPERACIONES!$C$6:$C$505,A8,OPERACIONES!$E$6:$E$505),0))
V9: =IF(A9="","",SUMIFS(CONFIG!$F$5:$F$26,CONFIG!$D$5:$D$26,"Tipo de persona",CONFIG!$E$5:$E$26,C9)+SUMIFS(CONFIG!$F$5:$F$26,CONFIG!$D$5:$D$26,"Residencia",CONFIG!$E$5:$E$26,E9)+SUMIFS(CONFIG!$F$5:$F$26,CONFIG!$D$5:$D$26,"Nacionalidad",CONFIG!$E$5:$E$26,F9)+SUMIFS(CONFIG!$F$5:$F$26,CONFIG!$D$5:$D$26,"Jurisdicción de riesgo",CONFIG!$E$5:$E$26,G9)+SUMIFS(CONFIG!$F$5:$F$26,CONFIG!$D$5:$D$26,"PEP",CONFIG!$E$5:$E$26,H9)+SUMIFS(CONFIG!$F$5:$F$26,CONFIG!$D$5:$D$26,"En listas",CONFIG!$E$5:$E$26,I9)+SUMIFS(CONFIG!$F$5:$F$26,CONFIG!$D$5:$D$26,"Riesgo de su actividad económica",CONFIG!$E$5:$E$26,J9)+SUMIFS(CONFIG!$F$5:$F$26,CONFIG!$D$5:$D$26,"Canal",CONFIG!$E$5:$E$26,K9)+SUMIFS(CONFIG!$F$5:$F$26,CONFIG!$D$5:$D$26,"Origen de recursos documentado",CONFIG!$E$5:$E$26,L9)) | W9: =IF(A9="","",IF(SUMIF(OPERACIONES!$C$6:$C$505,A9,OPERACIONES!$E$6:$E$505)>0,IF(SUMIF(OPERACIONES!$C$6:$C$505,A9,OPERACIONES!$F$6:$F$505)/SUMIF(OPERACIONES!$C$6:$C$505,A9,OPERACIONES!$E$6:$E$505)>0.5,CONFIG!$B$20,IF(SUMIF(OPERACIONES!$C$6:$C$505,A9,OPERACIONES!$F$6:$F$505)>0,CONFIG!$B$21,0)),0)+IF(COUNTIFS(OPERACIONES!$C$6:$C$505,A9,OPERACIONES!$AQ$6:$AQ$505,1)>0,CONFIG!$B$22,0)+IF(COUNTIFS(OPERACIONES!$C$6:$C$505,A9,OPERACIONES!$H$6:$H$505,"Sí")>0,CONFIG!$B$23,0)) | X9: =IF(A9="","",V9+W9) | Y9: =IF(A9="","",IF(X9<=CONFIG!$B$13,"Bajo",IF(X9<=CONFIG!$B$14,"Medio","Alto"))) | Z9: =IF(A9="","",IF(OR(H9="Extranjera",AND(E9="No residente",G9="Sí"),I9="Sí"),"Alto",IF(T9<>"",T9,Y9))) | AA9: =IF(A9="","",IF(H9="Extranjera","Alto obligatorio: PEP extranjera (RCG 23 Bis 4)",IF(AND(E9="No residente",G9="Sí"),"Alto obligatorio: no residente vinculado a jurisdicción de riesgo (RCG 23 Bis 4)",IF(I9="Sí","Alto por criterio: persona en listas. Evalúa no operar y Aviso de 24 h",IF(T9<>"","Ajuste del REC: "&U9,"Modelo: "&X9&" puntos"))))) | AB9: =IF(A9="","",IF(COUNT(N9,O9)=0,"Falta fecha",EDATE(MAX(N9,O9),IF(Z9="Alto",CONFIG!$B$18,IF(Z9="Medio",CONFIG!$B$17,CONFIG!$B$16))))) | AC9: =IF(A9="","",IF(ISNUMBER(S9),EDATE(S9,12),IF(ISNUMBER(N9),EDATE(N9,12),"Falta fecha"))) | AD9: =IF(A9="","",MID(IF(P9<>"Sí"," · Expediente incompleto","")&IF(OR(Q9="",Q9="Pendiente")," · Falta el Beneficiario Controlador","")&IF(M9=""," · Sin perfil transaccional","")&IF(AND(ISNUMBER(AB9),AB9<CONFIG!$B$6)," · Evaluación de riesgo vencida","")&IF(AND(ISNUMBER(AC9),AC9<CONFIG!$B$6)," · Verificación anual vencida","")&IF(AND(ISNUMBER(R9),ISNUMBER(S9),S9-R9>92)," · Comprobante de domicilio con más de 3 meses","")&IF(AND(T9<>"",U9="")," · Ajuste del REC sin justificación",""),4,400)) | AE9: =IF(A9="","",IF(AD9="","Al día","Revisar")) | AF9: =IF(A9="","",COUNTIF(OPERACIONES!$C$6:$C$505,A9)&" / $"&FIXED(SUMIF(OPERACIONES!$C$6:$C$505,A9,OPERACIONES!$E$6:$E$505),0))
V10: =IF(A10="","",SUMIFS(CONFIG!$F$5:$F$26,CONFIG!$D$5:$D$26,"Tipo de persona",CONFIG!$E$5:$E$26,C10)+SUMIFS(CONFIG!$F$5:$F$26,CONFIG!$D$5:$D$26,"Residencia",CONFIG!$E$5:$E$26,E10)+SUMIFS(CONFIG!$F$5:$F$26,CONFIG!$D$5:$D$26,"Nacionalidad",CONFIG!$E$5:$E$26,F10)+SUMIFS(CONFIG!$F$5:$F$26,CONFIG!$D$5:$D$26,"Jurisdicción de riesgo",CONFIG!$E$5:$E$26,G10)+SUMIFS(CONFIG!$F$5:$F$26,CONFIG!$D$5:$D$26,"PEP",CONFIG!$E$5:$E$26,H10)+SUMIFS(CONFIG!$F$5:$F$26,CONFIG!$D$5:$D$26,"En listas",CONFIG!$E$5:$E$26,I10)+SUMIFS(CONFIG!$F$5:$F$26,CONFIG!$D$5:$D$26,"Riesgo de su actividad económica",CONFIG!$E$5:$E$26,J10)+SUMIFS(CONFIG!$F$5:$F$26,CONFIG!$D$5:$D$26,"Canal",CONFIG!$E$5:$E$26,K10)+SUMIFS(CONFIG!$F$5:$F$26,CONFIG!$D$5:$D$26,"Origen de recursos documentado",CONFIG!$E$5:$E$26,L10)) | W10: =IF(A10="","",IF(SUMIF(OPERACIONES!$C$6:$C$505,A10,OPERACIONES!$E$6:$E$505)>0,IF(SUMIF(OPERACIONES!$C$6:$C$505,A10,OPERACIONES!$F$6:$F$505)/SUMIF(OPERACIONES!$C$6:$C$505,A10,OPERACIONES!$E$6:$E$505)>0.5,CONFIG!$B$20,IF(SUMIF(OPERACIONES!$C$6:$C$505,A10,OPERACIONES!$F$6:$F$505)>0,CONFIG!$B$21,0)),0)+IF(COUNTIFS(OPERACIONES!$C$6:$C$505,A10,OPERACIONES!$AQ$6:$AQ$505,1)>0,CONFIG!$B$22,0)+IF(COUNTIFS(OPERACIONES!$C$6:$C$505,A10,OPERACIONES!$H$6:$H$505,"Sí")>0,CONFIG!$B$23,0)) | X10: =IF(A10="","",V10+W10) | Y10: =IF(A10="","",IF(X10<=CONFIG!$B$13,"Bajo",IF(X10<=CONFIG!$B$14,"Medio","Alto"))) | Z10: =IF(A10="","",IF(OR(H10="Extranjera",AND(E10="No residente",G10="Sí"),I10="Sí"),"Alto",IF(T10<>"",T10,Y10))) | AA10: =IF(A10="","",IF(H10="Extranjera","Alto obligatorio: PEP extranjera (RCG 23 Bis 4)",IF(AND(E10="No residente",G10="Sí"),"Alto obligatorio: no residente vinculado a jurisdicción de riesgo (RCG 23 Bis 4)",IF(I10="Sí","Alto por criterio: persona en listas. Evalúa no operar y Aviso de 24 h",IF(T10<>"","Ajuste del REC: "&U10,"Modelo: "&X10&" puntos"))))) | AB10: =IF(A10="","",IF(COUNT(N10,O10)=0,"Falta fecha",EDATE(MAX(N10,O10),IF(Z10="Alto",CONFIG!$B$18,IF(Z10="Medio",CONFIG!$B$17,CONFIG!$B$16))))) | AC10: =IF(A10="","",IF(ISNUMBER(S10),EDATE(S10,12),IF(ISNUMBER(N10),EDATE(N10,12),"Falta fecha"))) | AD10: =IF(A10="","",MID(IF(P10<>"Sí"," · Expediente incompleto","")&IF(OR(Q10="",Q10="Pendiente")," · Falta el Beneficiario Controlador","")&IF(M10=""," · Sin perfil transaccional","")&IF(AND(ISNUMBER(AB10),AB10<CONFIG!$B$6)," · Evaluación de riesgo vencida","")&IF(AND(ISNUMBER(AC10),AC10<CONFIG!$B$6)," · Verificación anual vencida","")&IF(AND(ISNUMBER(R10),ISNUMBER(S10),S10-R10>92)," · Comprobante de domicilio con más de 3 meses","")&IF(AND(T10<>"",U10="")," · Ajuste del REC sin justificación",""),4,400)) | AE10: =IF(A10="","",IF(AD10="","Al día","Revisar")) | AF10: =IF(A10="","",COUNTIF(OPERACIONES!$C$6:$C$505,A10)&" / $"&FIXED(SUMIF(OPERACIONES!$C$6:$C$505,A10,OPERACIONES!$E$6:$E$505),0))
V11: =IF(A11="","",SUMIFS(CONFIG!$F$5:$F$26,CONFIG!$D$5:$D$26,"Tipo de persona",CONFIG!$E$5:$E$26,C11)+SUMIFS(CONFIG!$F$5:$F$26,CONFIG!$D$5:$D$26,"Residencia",CONFIG!$E$5:$E$26,E11)+SUMIFS(CONFIG!$F$5:$F$26,CONFIG!$D$5:$D$26,"Nacionalidad",CONFIG!$E$5:$E$26,F11)+SUMIFS(CONFIG!$F$5:$F$26,CONFIG!$D$5:$D$26,"Jurisdicción de riesgo",CONFIG!$E$5:$E$26,G11)+SUMIFS(CONFIG!$F$5:$F$26,CONFIG!$D$5:$D$26,"PEP",CONFIG!$E$5:$E$26,H11)+SUMIFS(CONFIG!$F$5:$F$26,CONFIG!$D$5:$D$26,"En listas",CONFIG!$E$5:$E$26,I11)+SUMIFS(CONFIG!$F$5:$F$26,CONFIG!$D$5:$D$26,"Riesgo de su actividad económica",CONFIG!$E$5:$E$26,J11)+SUMIFS(CONFIG!$F$5:$F$26,CONFIG!$D$5:$D$26,"Canal",CONFIG!$E$5:$E$26,K11)+SUMIFS(CONFIG!$F$5:$F$26,CONFIG!$D$5:$D$26,"Origen de recursos documentado",CONFIG!$E$5:$E$26,L11)) | W11: =IF(A11="","",IF(SUMIF(OPERACIONES!$C$6:$C$505,A11,OPERACIONES!$E$6:$E$505)>0,IF(SUMIF(OPERACIONES!$C$6:$C$505,A11,OPERACIONES!$F$6:$F$505)/SUMIF(OPERACIONES!$C$6:$C$505,A11,OPERACIONES!$E$6:$E$505)>0.5,CONFIG!$B$20,IF(SUMIF(OPERACIONES!$C$6:$C$505,A11,OPERACIONES!$F$6:$F$505)>0,CONFIG!$B$21,0)),0)+IF(COUNTIFS(OPERACIONES!$C$6:$C$505,A11,OPERACIONES!$AQ$6:$AQ$505,1)>0,CONFIG!$B$22,0)+IF(COUNTIFS(OPERACIONES!$C$6:$C$505,A11,OPERACIONES!$H$6:$H$505,"Sí")>0,CONFIG!$B$23,0)) | X11: =IF(A11="","",V11+W11) | Y11: =IF(A11="","",IF(X11<=CONFIG!$B$13,"Bajo",IF(X11<=CONFIG!$B$14,"Medio","Alto"))) | Z11: =IF(A11="","",IF(OR(H11="Extranjera",AND(E11="No residente",G11="Sí"),I11="Sí"),"Alto",IF(T11<>"",T11,Y11))) | AA11: =IF(A11="","",IF(H11="Extranjera","Alto obligatorio: PEP extranjera (RCG 23 Bis 4)",IF(AND(E11="No residente",G11="Sí"),"Alto obligatorio: no residente vinculado a jurisdicción de riesgo (RCG 23 Bis 4)",IF(I11="Sí","Alto por criterio: persona en listas. Evalúa no operar y Aviso de 24 h",IF(T11<>"","Ajuste del REC: "&U11,"Modelo: "&X11&" puntos"))))) | AB11: =IF(A11="","",IF(COUNT(N11,O11)=0,"Falta fecha",EDATE(MAX(N11,O11),IF(Z11="Alto",CONFIG!$B$18,IF(Z11="Medio",CONFIG!$B$17,CONFIG!$B$16))))) | AC11: =IF(A11="","",IF(ISNUMBER(S11),EDATE(S11,12),IF(ISNUMBER(N11),EDATE(N11,12),"Falta fecha"))) | AD11: =IF(A11="","",MID(IF(P11<>"Sí"," · Expediente incompleto","")&IF(OR(Q11="",Q11="Pendiente")," · Falta el Beneficiario Controlador","")&IF(M11=""," · Sin perfil transaccional","")&IF(AND(ISNUMBER(AB11),AB11<CONFIG!$B$6)," · Evaluación de riesgo vencida","")&IF(AND(ISNUMBER(AC11),AC11<CONFIG!$B$6)," · Verificación anual vencida","")&IF(AND(ISNUMBER(R11),ISNUMBER(S11),S11-R11>92)," · Comprobante de domicilio con más de 3 meses","")&IF(AND(T11<>"",U11="")," · Ajuste del REC sin justificación",""),4,400)) | AE11: =IF(A11="","",IF(AD11="","Al día","Revisar")) | AF11: =IF(A11="","",COUNTIF(OPERACIONES!$C$6:$C$505,A11)&" / $"&FIXED(SUMIF(OPERACIONES!$C$6:$C$505,A11,OPERACIONES!$E$6:$E$505),0))
V12: =IF(A12="","",SUMIFS(CONFIG!$F$5:$F$26,CONFIG!$D$5:$D$26,"Tipo de persona",CONFIG!$E$5:$E$26,C12)+SUMIFS(CONFIG!$F$5:$F$26,CONFIG!$D$5:$D$26,"Residencia",CONFIG!$E$5:$E$26,E12)+SUMIFS(CONFIG!$F$5:$F$26,CONFIG!$D$5:$D$26,"Nacionalidad",CONFIG!$E$5:$E$26,F12)+SUMIFS(CONFIG!$F$5:$F$26,CONFIG!$D$5:$D$26,"Jurisdicción de riesgo",CONFIG!$E$5:$E$26,G12)+SUMIFS(CONFIG!$F$5:$F$26,CONFIG!$D$5:$D$26,"PEP",CONFIG!$E$5:$E$26,H12)+SUMIFS(CONFIG!$F$5:$F$26,CONFIG!$D$5:$D$26,"En listas",CONFIG!$E$5:$E$26,I12)+SUMIFS(CONFIG!$F$5:$F$26,CONFIG!$D$5:$D$26,"Riesgo de su actividad económica",CONFIG!$E$5:$E$26,J12)+SUMIFS(CONFIG!$F$5:$F$26,CONFIG!$D$5:$D$26,"Canal",CONFIG!$E$5:$E$26,K12)+SUMIFS(CONFIG!$F$5:$F$26,CONFIG!$D$5:$D$26,"Origen de recursos documentado",CONFIG!$E$5:$E$26,L12)) | W12: =IF(A12="","",IF(SUMIF(OPERACIONES!$C$6:$C$505,A12,OPERACIONES!$E$6:$E$505)>0,IF(SUMIF(OPERACIONES!$C$6:$C$505,A12,OPERACIONES!$F$6:$F$505)/SUMIF(OPERACIONES!$C$6:$C$505,A12,OPERACIONES!$E$6:$E$505)>0.5,CONFIG!$B$20,IF(SUMIF(OPERACIONES!$C$6:$C$505,A12,OPERACIONES!$F$6:$F$505)>0,CONFIG!$B$21,0)),0)+IF(COUNTIFS(OPERACIONES!$C$6:$C$505,A12,OPERACIONES!$AQ$6:$AQ$505,1)>0,CONFIG!$B$22,0)+IF(COUNTIFS(OPERACIONES!$C$6:$C$505,A12,OPERACIONES!$H$6:$H$505,"Sí")>0,CONFIG!$B$23,0)) | X12: =IF(A12="","",V12+W12) | Y12: =IF(A12="","",IF(X12<=CONFIG!$B$13,"Bajo",IF(X12<=CONFIG!$B$14,"Medio","Alto"))) | Z12: =IF(A12="","",IF(OR(H12="Extranjera",AND(E12="No residente",G12="Sí"),I12="Sí"),"Alto",IF(T12<>"",T12,Y12))) | AA12: =IF(A12="","",IF(H12="Extranjera","Alto obligatorio: PEP extranjera (RCG 23 Bis 4)",IF(AND(E12="No residente",G12="Sí"),"Alto obligatorio: no residente vinculado a jurisdicción de riesgo (RCG 23 Bis 4)",IF(I12="Sí","Alto por criterio: persona en listas. Evalúa no operar y Aviso de 24 h",IF(T12<>"","Ajuste del REC: "&U12,"Modelo: "&X12&" puntos"))))) | AB12: =IF(A12="","",IF(COUNT(N12,O12)=0,"Falta fecha",EDATE(MAX(N12,O12),IF(Z12="Alto",CONFIG!$B$18,IF(Z12="Medio",CONFIG!$B$17,CONFIG!$B$16))))) | AC12: =IF(A12="","",IF(ISNUMBER(S12),EDATE(S12,12),IF(ISNUMBER(N12),EDATE(N12,12),"Falta fecha"))) | AD12: =IF(A12="","",MID(IF(P12<>"Sí"," · Expediente incompleto","")&IF(OR(Q12="",Q12="Pendiente")," · Falta el Beneficiario Controlador","")&IF(M12=""," · Sin perfil transaccional","")&IF(AND(ISNUMBER(AB12),AB12<CONFIG!$B$6)," · Evaluación de riesgo vencida","")&IF(AND(ISNUMBER(AC12),AC12<CONFIG!$B$6)," · Verificación anual vencida","")&IF(AND(ISNUMBER(R12),ISNUMBER(S12),S12-R12>92)," · Comprobante de domicilio con más de 3 meses","")&IF(AND(T12<>"",U12="")," · Ajuste del REC sin justificación",""),4,400)) | AE12: =IF(A12="","",IF(AD12="","Al día","Revisar")) | AF12: =IF(A12="","",COUNTIF(OPERACIONES!$C$6:$C$505,A12)&" / $"&FIXED(SUMIF(OPERACIONES!$C$6:$C$505,A12,OPERACIONES!$E$6:$E$505),0))
V13: =IF(A13="","",SUMIFS(CONFIG!$F$5:$F$26,CONFIG!$D$5:$D$26,"Tipo de persona",CONFIG!$E$5:$E$26,C13)+SUMIFS(CONFIG!$F$5:$F$26,CONFIG!$D$5:$D$26,"Residencia",CONFIG!$E$5:$E$26,E13)+SUMIFS(CONFIG!$F$5:$F$26,CONFIG!$D$5:$D$26,"Nacionalidad",CONFIG!$E$5:$E$26,F13)+SUMIFS(CONFIG!$F$5:$F$26,CONFIG!$D$5:$D$26,"Jurisdicción de riesgo",CONFIG!$E$5:$E$26,G13)+SUMIFS(CONFIG!$F$5:$F$26,CONFIG!$D$5:$D$26,"PEP",CONFIG!$E$5:$E$26,H13)+SUMIFS(CONFIG!$F$5:$F$26,CONFIG!$D$5:$D$26,"En listas",CONFIG!$E$5:$E$26,I13)+SUMIFS(CONFIG!$F$5:$F$26,CONFIG!$D$5:$D$26,"Riesgo de su actividad económica",CONFIG!$E$5:$E$26,J13)+SUMIFS(CONFIG!$F$5:$F$26,CONFIG!$D$5:$D$26,"Canal",CONFIG!$E$5:$E$26,K13)+SUMIFS(CONFIG!$F$5:$F$26,CONFIG!$D$5:$D$26,"Origen de recursos documentado",CONFIG!$E$5:$E$26,L13)) | W13: =IF(A13="","",IF(SUMIF(OPERACIONES!$C$6:$C$505,A13,OPERACIONES!$E$6:$E$505)>0,IF(SUMIF(OPERACIONES!$C$6:$C$505,A13,OPERACIONES!$F$6:$F$505)/SUMIF(OPERACIONES!$C$6:$C$505,A13,OPERACIONES!$E$6:$E$505)>0.5,CONFIG!$B$20,IF(SUMIF(OPERACIONES!$C$6:$C$505,A13,OPERACIONES!$F$6:$F$505)>0,CONFIG!$B$21,0)),0)+IF(COUNTIFS(OPERACIONES!$C$6:$C$505,A13,OPERACIONES!$AQ$6:$AQ$505,1)>0,CONFIG!$B$22,0)+IF(COUNTIFS(OPERACIONES!$C$6:$C$505,A13,OPERACIONES!$H$6:$H$505,"Sí")>0,CONFIG!$B$23,0)) | X13: =IF(A13="","",V13+W13) | Y13: =IF(A13="","",IF(X13<=CONFIG!$B$13,"Bajo",IF(X13<=CONFIG!$B$14,"Medio","Alto"))) | Z13: =IF(A13="","",IF(OR(H13="Extranjera",AND(E13="No residente",G13="Sí"),I13="Sí"),"Alto",IF(T13<>"",T13,Y13))) | AA13: =IF(A13="","",IF(H13="Extranjera","Alto obligatorio: PEP extranjera (RCG 23 Bis 4)",IF(AND(E13="No residente",G13="Sí"),"Alto obligatorio: no residente vinculado a jurisdicción de riesgo (RCG 23 Bis 4)",IF(I13="Sí","Alto por criterio: persona en listas. Evalúa no operar y Aviso de 24 h",IF(T13<>"","Ajuste del REC: "&U13,"Modelo: "&X13&" puntos"))))) | AB13: =IF(A13="","",IF(COUNT(N13,O13)=0,"Falta fecha",EDATE(MAX(N13,O13),IF(Z13="Alto",CONFIG!$B$18,IF(Z13="Medio",CONFIG!$B$17,CONFIG!$B$16))))) | AC13: =IF(A13="","",IF(ISNUMBER(S13),EDATE(S13,12),IF(ISNUMBER(N13),EDATE(N13,12),"Falta fecha"))) | AD13: =IF(A13="","",MID(IF(P13<>"Sí"," · Expediente incompleto","")&IF(OR(Q13="",Q13="Pendiente")," · Falta el Beneficiario Controlador","")&IF(M13=""," · Sin perfil transaccional","")&IF(AND(ISNUMBER(AB13),AB13<CONFIG!$B$6)," · Evaluación de riesgo vencida","")&IF(AND(ISNUMBER(AC13),AC13<CONFIG!$B$6)," · Verificación anual vencida","")&IF(AND(ISNUMBER(R13),ISNUMBER(S13),S13-R13>92)," · Comprobante de domicilio con más de 3 meses","")&IF(AND(T13<>"",U13="")," · Ajuste del REC sin justificación",""),4,400)) | AE13: =IF(A13="","",IF(AD13="","Al día","Revisar")) | AF13: =IF(A13="","",COUNTIF(OPERACIONES!$C$6:$C$505,A13)&" / $"&FIXED(SUMIF(OPERACIONES!$C$6:$C$505,A13,OPERACIONES!$E$6:$E$505),0))
V14: =IF(A14="","",SUMIFS(CONFIG!$F$5:$F$26,CONFIG!$D$5:$D$26,"Tipo de persona",CONFIG!$E$5:$E$26,C14)+SUMIFS(CONFIG!$F$5:$F$26,CONFIG!$D$5:$D$26,"Residencia",CONFIG!$E$5:$E$26,E14)+SUMIFS(CONFIG!$F$5:$F$26,CONFIG!$D$5:$D$26,"Nacionalidad",CONFIG!$E$5:$E$26,F14)+SUMIFS(CONFIG!$F$5:$F$26,CONFIG!$D$5:$D$26,"Jurisdicción de riesgo",CONFIG!$E$5:$E$26,G14)+SUMIFS(CONFIG!$F$5:$F$26,CONFIG!$D$5:$D$26,"PEP",CONFIG!$E$5:$E$26,H14)+SUMIFS(CONFIG!$F$5:$F$26,CONFIG!$D$5:$D$26,"En listas",CONFIG!$E$5:$E$26,I14)+SUMIFS(CONFIG!$F$5:$F$26,CONFIG!$D$5:$D$26,"Riesgo de su actividad económica",CONFIG!$E$5:$E$26,J14)+SUMIFS(CONFIG!$F$5:$F$26,CONFIG!$D$5:$D$26,"Canal",CONFIG!$E$5:$E$26,K14)+SUMIFS(CONFIG!$F$5:$F$26,CONFIG!$D$5:$D$26,"Origen de recursos documentado",CONFIG!$E$5:$E$26,L14)) | W14: =IF(A14="","",IF(SUMIF(OPERACIONES!$C$6:$C$505,A14,OPERACIONES!$E$6:$E$505)>0,IF(SUMIF(OPERACIONES!$C$6:$C$505,A14,OPERACIONES!$F$6:$F$505)/SUMIF(OPERACIONES!$C$6:$C$505,A14,OPERACIONES!$E$6:$E$505)>0.5,CONFIG!$B$20,IF(SUMIF(OPERACIONES!$C$6:$C$505,A14,OPERACIONES!$F$6:$F$505)>0,CONFIG!$B$21,0)),0)+IF(COUNTIFS(OPERACIONES!$C$6:$C$505,A14,OPERACIONES!$AQ$6:$AQ$505,1)>0,CONFIG!$B$22,0)+IF(COUNTIFS(OPERACIONES!$C$6:$C$505,A14,OPERACIONES!$H$6:$H$505,"Sí")>0,CONFIG!$B$23,0)) | X14: =IF(A14="","",V14+W14) | Y14: =IF(A14="","",IF(X14<=CONFIG!$B$13,"Bajo",IF(X14<=CONFIG!$B$14,"Medio","Alto"))) | Z14: =IF(A14="","",IF(OR(H14="Extranjera",AND(E14="No residente",G14="Sí"),I14="Sí"),"Alto",IF(T14<>"",T14,Y14))) | AA14: =IF(A14="","",IF(H14="Extranjera","Alto obligatorio: PEP extranjera (RCG 23 Bis 4)",IF(AND(E14="No residente",G14="Sí"),"Alto obligatorio: no residente vinculado a jurisdicción de riesgo (RCG 23 Bis 4)",IF(I14="Sí","Alto por criterio: persona en listas. Evalúa no operar y Aviso de 24 h",IF(T14<>"","Ajuste del REC: "&U14,"Modelo: "&X14&" puntos"))))) | AB14: =IF(A14="","",IF(COUNT(N14,O14)=0,"Falta fecha",EDATE(MAX(N14,O14),IF(Z14="Alto",CONFIG!$B$18,IF(Z14="Medio",CONFIG!$B$17,CONFIG!$B$16))))) | AC14: =IF(A14="","",IF(ISNUMBER(S14),EDATE(S14,12),IF(ISNUMBER(N14),EDATE(N14,12),"Falta fecha"))) | AD14: =IF(A14="","",MID(IF(P14<>"Sí"," · Expediente incompleto","")&IF(OR(Q14="",Q14="Pendiente")," · Falta el Beneficiario Controlador","")&IF(M14=""," · Sin perfil transaccional","")&IF(AND(ISNUMBER(AB14),AB14<CONFIG!$B$6)," · Evaluación de riesgo vencida","")&IF(AND(ISNUMBER(AC14),AC14<CONFIG!$B$6)," · Verificación anual vencida","")&IF(AND(ISNUMBER(R14),ISNUMBER(S14),S14-R14>92)," · Comprobante de domicilio con más de 3 meses","")&IF(AND(T14<>"",U14="")," · Ajuste del REC sin justificación",""),4,400)) | AE14: =IF(A14="","",IF(AD14="","Al día","Revisar")) | AF14: =IF(A14="","",COUNTIF(OPERACIONES!$C$6:$C$505,A14)&" / $"&FIXED(SUMIF(OPERACIONES!$C$6:$C$505,A14,OPERACIONES!$E$6:$E$505),0))
V15: =IF(A15="","",SUMIFS(CONFIG!$F$5:$F$26,CONFIG!$D$5:$D$26,"Tipo de persona",CONFIG!$E$5:$E$26,C15)+SUMIFS(CONFIG!$F$5:$F$26,CONFIG!$D$5:$D$26,"Residencia",CONFIG!$E$5:$E$26,E15)+SUMIFS(CONFIG!$F$5:$F$26,CONFIG!$D$5:$D$26,"Nacionalidad",CONFIG!$E$5:$E$26,F15)+SUMIFS(CONFIG!$F$5:$F$26,CONFIG!$D$5:$D$26,"Jurisdicción de riesgo",CONFIG!$E$5:$E$26,G15)+SUMIFS(CONFIG!$F$5:$F$26,CONFIG!$D$5:$D$26,"PEP",CONFIG!$E$5:$E$26,H15)+SUMIFS(CONFIG!$F$5:$F$26,CONFIG!$D$5:$D$26,"En listas",CONFIG!$E$5:$E$26,I15)+SUMIFS(CONFIG!$F$5:$F$26,CONFIG!$D$5:$D$26,"Riesgo de su actividad económica",CONFIG!$E$5:$E$26,J15)+SUMIFS(CONFIG!$F$5:$F$26,CONFIG!$D$5:$D$26,"Canal",CONFIG!$E$5:$E$26,K15)+SUMIFS(CONFIG!$F$5:$F$26,CONFIG!$D$5:$D$26,"Origen de recursos documentado",CONFIG!$E$5:$E$26,L15)) | W15: =IF(A15="","",IF(SUMIF(OPERACIONES!$C$6:$C$505,A15,OPERACIONES!$E$6:$E$505)>0,IF(SUMIF(OPERACIONES!$C$6:$C$505,A15,OPERACIONES!$F$6:$F$505)/SUMIF(OPERACIONES!$C$6:$C$505,A15,OPERACIONES!$E$6:$E$505)>0.5,CONFIG!$B$20,IF(SUMIF(OPERACIONES!$C$6:$C$505,A15,OPERACIONES!$F$6:$F$505)>0,CONFIG!$B$21,0)),0)+IF(COUNTIFS(OPERACIONES!$C$6:$C$505,A15,OPERACIONES!$AQ$6:$AQ$505,1)>0,CONFIG!$B$22,0)+IF(COUNTIFS(OPERACIONES!$C$6:$C$505,A15,OPERACIONES!$H$6:$H$505,"Sí")>0,CONFIG!$B$23,0)) | X15: =IF(A15="","",V15+W15) | Y15: =IF(A15="","",IF(X15<=CONFIG!$B$13,"Bajo",IF(X15<=CONFIG!$B$14,"Medio","Alto"))) | Z15: =IF(A15="","",IF(OR(H15="Extranjera",AND(E15="No residente",G15="Sí"),I15="Sí"),"Alto",IF(T15<>"",T15,Y15))) | AA15: =IF(A15="","",IF(H15="Extranjera","Alto obligatorio: PEP extranjera (RCG 23 Bis 4)",IF(AND(E15="No residente",G15="Sí"),"Alto obligatorio: no residente vinculado a jurisdicción de riesgo (RCG 23 Bis 4)",IF(I15="Sí","Alto por criterio: persona en listas. Evalúa no operar y Aviso de 24 h",IF(T15<>"","Ajuste del REC: "&U15,"Modelo: "&X15&" puntos"))))) | AB15: =IF(A15="","",IF(COUNT(N15,O15)=0,"Falta fecha",EDATE(MAX(N15,O15),IF(Z15="Alto",CONFIG!$B$18,IF(Z15="Medio",CONFIG!$B$17,CONFIG!$B$16))))) | AC15: =IF(A15="","",IF(ISNUMBER(S15),EDATE(S15,12),IF(ISNUMBER(N15),EDATE(N15,12),"Falta fecha"))) | AD15: =IF(A15="","",MID(IF(P15<>"Sí"," · Expediente incompleto","")&IF(OR(Q15="",Q15="Pendiente")," · Falta el Beneficiario Controlador","")&IF(M15=""," · Sin perfil transaccional","")&IF(AND(ISNUMBER(AB15),AB15<CONFIG!$B$6)," · Evaluación de riesgo vencida","")&IF(AND(ISNUMBER(AC15),AC15<CONFIG!$B$6)," · Verificación anual vencida","")&IF(AND(ISNUMBER(R15),ISNUMBER(S15),S15-R15>92)," · Comprobante de domicilio con más de 3 meses","")&IF(AND(T15<>"",U15="")," · Ajuste del REC sin justificación",""),4,400)) | AE15: =IF(A15="","",IF(AD15="","Al día","Revisar")) | AF15: =IF(A15="","",COUNTIF(OPERACIONES!$C$6:$C$505,A15)&" / $"&FIXED(SUMIF(OPERACIONES!$C$6:$C$505,A15,OPERACIONES!$E$6:$E$505),0))
V16: =IF(A16="","",SUMIFS(CONFIG!$F$5:$F$26,CONFIG!$D$5:$D$26,"Tipo de persona",CONFIG!$E$5:$E$26,C16)+SUMIFS(CONFIG!$F$5:$F$26,CONFIG!$D$5:$D$26,"Residencia",CONFIG!$E$5:$E$26,E16)+SUMIFS(CONFIG!$F$5:$F$26,CONFIG!$D$5:$D$26,"Nacionalidad",CONFIG!$E$5:$E$26,F16)+SUMIFS(CONFIG!$F$5:$F$26,CONFIG!$D$5:$D$26,"Jurisdicción de riesgo",CONFIG!$E$5:$E$26,G16)+SUMIFS(CONFIG!$F$5:$F$26,CONFIG!$D$5:$D$26,"PEP",CONFIG!$E$5:$E$26,H16)+SUMIFS(CONFIG!$F$5:$F$26,CONFIG!$D$5:$D$26,"En listas",CONFIG!$E$5:$E$26,I16)+SUMIFS(CONFIG!$F$5:$F$26,CONFIG!$D$5:$D$26,"Riesgo de su actividad económica",CONFIG!$E$5:$E$26,J16)+SUMIFS(CONFIG!$F$5:$F$26,CONFIG!$D$5:$D$26,"Canal",CONFIG!$E$5:$E$26,K16)+SUMIFS(CONFIG!$F$5:$F$26,CONFIG!$D$5:$D$26,"Origen de recursos documentado",CONFIG!$E$5:$E$26,L16)) | W16: =IF(A16="","",IF(SUMIF(OPERACIONES!$C$6:$C$505,A16,OPERACIONES!$E$6:$E$505)>0,IF(SUMIF(OPERACIONES!$C$6:$C$505,A16,OPERACIONES!$F$6:$F$505)/SUMIF(OPERACIONES!$C$6:$C$505,A16,OPERACIONES!$E$6:$E$505)>0.5,CONFIG!$B$20,IF(SUMIF(OPERACIONES!$C$6:$C$505,A16,OPERACIONES!$F$6:$F$505)>0,CONFIG!$B$21,0)),0)+IF(COUNTIFS(OPERACIONES!$C$6:$C$505,A16,OPERACIONES!$AQ$6:$AQ$505,1)>0,CONFIG!$B$22,0)+IF(COUNTIFS(OPERACIONES!$C$6:$C$505,A16,OPERACIONES!$H$6:$H$505,"Sí")>0,CONFIG!$B$23,0)) | X16: =IF(A16="","",V16+W16) | Y16: =IF(A16="","",IF(X16<=CONFIG!$B$13,"Bajo",IF(X16<=CONFIG!$B$14,"Medio","Alto"))) | Z16: =IF(A16="","",IF(OR(H16="Extranjera",AND(E16="No residente",G16="Sí"),I16="Sí"),"Alto",IF(T16<>"",T16,Y16))) | AA16: =IF(A16="","",IF(H16="Extranjera","Alto obligatorio: PEP extranjera (RCG 23 Bis 4)",IF(AND(E16="No residente",G16="Sí"),"Alto obligatorio: no residente vinculado a jurisdicción de riesgo (RCG 23 Bis 4)",IF(I16="Sí","Alto por criterio: persona en listas. Evalúa no operar y Aviso de 24 h",IF(T16<>"","Ajuste del REC: "&U16,"Modelo: "&X16&" puntos"))))) | AB16: =IF(A16="","",IF(COUNT(N16,O16)=0,"Falta fecha",EDATE(MAX(N16,O16),IF(Z16="Alto",CONFIG!$B$18,IF(Z16="Medio",CONFIG!$B$17,CONFIG!$B$16))))) | AC16: =IF(A16="","",IF(ISNUMBER(S16),EDATE(S16,12),IF(ISNUMBER(N16),EDATE(N16,12),"Falta fecha"))) | AD16: =IF(A16="","",MID(IF(P16<>"Sí"," · Expediente incompleto","")&IF(OR(Q16="",Q16="Pendiente")," · Falta el Beneficiario Controlador","")&IF(M16=""," · Sin perfil transaccional","")&IF(AND(ISNUMBER(AB16),AB16<CONFIG!$B$6)," · Evaluación de riesgo vencida","")&IF(AND(ISNUMBER(AC16),AC16<CONFIG!$B$6)," · Verificación anual vencida","")&IF(AND(ISNUMBER(R16),ISNUMBER(S16),S16-R16>92)," · Comprobante de domicilio con más de 3 meses","")&IF(AND(T16<>"",U16="")," · Ajuste del REC sin justificación",""),4,400)) | AE16: =IF(A16="","",IF(AD16="","Al día","Revisar")) | AF16: =IF(A16="","",COUNTIF(OPERACIONES!$C$6:$C$505,A16)&" / $"&FIXED(SUMIF(OPERACIONES!$C$6:$C$505,A16,OPERACIONES!$E$6:$E$505),0))
V17: =IF(A17="","",SUMIFS(CONFIG!$F$5:$F$26,CONFIG!$D$5:$D$26,"Tipo de persona",CONFIG!$E$5:$E$26,C17)+SUMIFS(CONFIG!$F$5:$F$26,CONFIG!$D$5:$D$26,"Residencia",CONFIG!$E$5:$E$26,E17)+SUMIFS(CONFIG!$F$5:$F$26,CONFIG!$D$5:$D$26,"Nacionalidad",CONFIG!$E$5:$E$26,F17)+SUMIFS(CONFIG!$F$5:$F$26,CONFIG!$D$5:$D$26,"Jurisdicción de riesgo",CONFIG!$E$5:$E$26,G17)+SUMIFS(CONFIG!$F$5:$F$26,CONFIG!$D$5:$D$26,"PEP",CONFIG!$E$5:$E$26,H17)+SUMIFS(CONFIG!$F$5:$F$26,CONFIG!$D$5:$D$26,"En listas",CONFIG!$E$5:$E$26,I17)+SUMIFS(CONFIG!$F$5:$F$26,CONFIG!$D$5:$D$26,"Riesgo de su actividad económica",CONFIG!$E$5:$E$26,J17)+SUMIFS(CONFIG!$F$5:$F$26,CONFIG!$D$5:$D$26,"Canal",CONFIG!$E$5:$E$26,K17)+SUMIFS(CONFIG!$F$5:$F$26,CONFIG!$D$5:$D$26,"Origen de recursos documentado",CONFIG!$E$5:$E$26,L17)) | W17: =IF(A17="","",IF(SUMIF(OPERACIONES!$C$6:$C$505,A17,OPERACIONES!$E$6:$E$505)>0,IF(SUMIF(OPERACIONES!$C$6:$C$505,A17,OPERACIONES!$F$6:$F$505)/SUMIF(OPERACIONES!$C$6:$C$505,A17,OPERACIONES!$E$6:$E$505)>0.5,CONFIG!$B$20,IF(SUMIF(OPERACIONES!$C$6:$C$505,A17,OPERACIONES!$F$6:$F$505)>0,CONFIG!$B$21,0)),0)+IF(COUNTIFS(OPERACIONES!$C$6:$C$505,A17,OPERACIONES!$AQ$6:$AQ$505,1)>0,CONFIG!$B$22,0)+IF(COUNTIFS(OPERACIONES!$C$6:$C$505,A17,OPERACIONES!$H$6:$H$505,"Sí")>0,CONFIG!$B$23,0)) | X17: =IF(A17="","",V17+W17) | Y17: =IF(A17="","",IF(X17<=CONFIG!$B$13,"Bajo",IF(X17<=CONFIG!$B$14,"Medio","Alto"))) | Z17: =IF(A17="","",IF(OR(H17="Extranjera",AND(E17="No residente",G17="Sí"),I17="Sí"),"Alto",IF(T17<>"",T17,Y17))) | AA17: =IF(A17="","",IF(H17="Extranjera","Alto obligatorio: PEP extranjera (RCG 23 Bis 4)",IF(AND(E17="No residente",G17="Sí"),"Alto obligatorio: no residente vinculado a jurisdicción de riesgo (RCG 23 Bis 4)",IF(I17="Sí","Alto por criterio: persona en listas. Evalúa no operar y Aviso de 24 h",IF(T17<>"","Ajuste del REC: "&U17,"Modelo: "&X17&" puntos"))))) | AB17: =IF(A17="","",IF(COUNT(N17,O17)=0,"Falta fecha",EDATE(MAX(N17,O17),IF(Z17="Alto",CONFIG!$B$18,IF(Z17="Medio",CONFIG!$B$17,CONFIG!$B$16))))) | AC17: =IF(A17="","",IF(ISNUMBER(S17),EDATE(S17,12),IF(ISNUMBER(N17),EDATE(N17,12),"Falta fecha"))) | AD17: =IF(A17="","",MID(IF(P17<>"Sí"," · Expediente incompleto","")&IF(OR(Q17="",Q17="Pendiente")," · Falta el Beneficiario Controlador","")&IF(M17=""," · Sin perfil transaccional","")&IF(AND(ISNUMBER(AB17),AB17<CONFIG!$B$6)," · Evaluación de riesgo vencida","")&IF(AND(ISNUMBER(AC17),AC17<CONFIG!$B$6)," · Verificación anual vencida","")&IF(AND(ISNUMBER(R17),ISNUMBER(S17),S17-R17>92)," · Comprobante de domicilio con más de 3 meses","")&IF(AND(T17<>"",U17="")," · Ajuste del REC sin justificación",""),4,400)) | AE17: =IF(A17="","",IF(AD17="","Al día","Revisar")) | AF17: =IF(A17="","",COUNTIF(OPERACIONES!$C$6:$C$505,A17)&" / $"&FIXED(SUMIF(OPERACIONES!$C$6:$C$505,A17,OPERACIONES!$E$6:$E$505),0))
V18: =IF(A18="","",SUMIFS(CONFIG!$F$5:$F$26,CONFIG!$D$5:$D$26,"Tipo de persona",CONFIG!$E$5:$E$26,C18)+SUMIFS(CONFIG!$F$5:$F$26,CONFIG!$D$5:$D$26,"Residencia",CONFIG!$E$5:$E$26,E18)+SUMIFS(CONFIG!$F$5:$F$26,CONFIG!$D$5:$D$26,"Nacionalidad",CONFIG!$E$5:$E$26,F18)+SUMIFS(CONFIG!$F$5:$F$26,CONFIG!$D$5:$D$26,"Jurisdicción de riesgo",CONFIG!$E$5:$E$26,G18)+SUMIFS(CONFIG!$F$5:$F$26,CONFIG!$D$5:$D$26,"PEP",CONFIG!$E$5:$E$26,H18)+SUMIFS(CONFIG!$F$5:$F$26,CONFIG!$D$5:$D$26,"En listas",CONFIG!$E$5:$E$26,I18)+SUMIFS(CONFIG!$F$5:$F$26,CONFIG!$D$5:$D$26,"Riesgo de su actividad económica",CONFIG!$E$5:$E$26,J18)+SUMIFS(CONFIG!$F$5:$F$26,CONFIG!$D$5:$D$26,"Canal",CONFIG!$E$5:$E$26,K18)+SUMIFS(CONFIG!$F$5:$F$26,CONFIG!$D$5:$D$26,"Origen de recursos documentado",CONFIG!$E$5:$E$26,L18)) | W18: =IF(A18="","",IF(SUMIF(OPERACIONES!$C$6:$C$505,A18,OPERACIONES!$E$6:$E$505)>0,IF(SUMIF(OPERACIONES!$C$6:$C$505,A18,OPERACIONES!$F$6:$F$505)/SUMIF(OPERACIONES!$C$6:$C$505,A18,OPERACIONES!$E$6:$E$505)>0.5,CONFIG!$B$20,IF(SUMIF(OPERACIONES!$C$6:$C$505,A18,OPERACIONES!$F$6:$F$505)>0,CONFIG!$B$21,0)),0)+IF(COUNTIFS(OPERACIONES!$C$6:$C$505,A18,OPERACIONES!$AQ$6:$AQ$505,1)>0,CONFIG!$B$22,0)+IF(COUNTIFS(OPERACIONES!$C$6:$C$505,A18,OPERACIONES!$H$6:$H$505,"Sí")>0,CONFIG!$B$23,0)) | X18: =IF(A18="","",V18+W18) | Y18: =IF(A18="","",IF(X18<=CONFIG!$B$13,"Bajo",IF(X18<=CONFIG!$B$14,"Medio","Alto"))) | Z18: =IF(A18="","",IF(OR(H18="Extranjera",AND(E18="No residente",G18="Sí"),I18="Sí"),"Alto",IF(T18<>"",T18,Y18))) | AA18: =IF(A18="","",IF(H18="Extranjera","Alto obligatorio: PEP extranjera (RCG 23 Bis 4)",IF(AND(E18="No residente",G18="Sí"),"Alto obligatorio: no residente vinculado a jurisdicción de riesgo (RCG 23 Bis 4)",IF(I18="Sí","Alto por criterio: persona en listas. Evalúa no operar y Aviso de 24 h",IF(T18<>"","Ajuste del REC: "&U18,"Modelo: "&X18&" puntos"))))) | AB18: =IF(A18="","",IF(COUNT(N18,O18)=0,"Falta fecha",EDATE(MAX(N18,O18),IF(Z18="Alto",CONFIG!$B$18,IF(Z18="Medio",CONFIG!$B$17,CONFIG!$B$16))))) | AC18: =IF(A18="","",IF(ISNUMBER(S18),EDATE(S18,12),IF(ISNUMBER(N18),EDATE(N18,12),"Falta fecha"))) | AD18: =IF(A18="","",MID(IF(P18<>"Sí"," · Expediente incompleto","")&IF(OR(Q18="",Q18="Pendiente")," · Falta el Beneficiario Controlador","")&IF(M18=""," · Sin perfil transaccional","")&IF(AND(ISNUMBER(AB18),AB18<CONFIG!$B$6)," · Evaluación de riesgo vencida","")&IF(AND(ISNUMBER(AC18),AC18<CONFIG!$B$6)," · Verificación anual vencida","")&IF(AND(ISNUMBER(R18),ISNUMBER(S18),S18-R18>92)," · Comprobante de domicilio con más de 3 meses","")&IF(AND(T18<>"",U18="")," · Ajuste del REC sin justificación",""),4,400)) | AE18: =IF(A18="","",IF(AD18="","Al día","Revisar")) | AF18: =IF(A18="","",COUNTIF(OPERACIONES!$C$6:$C$505,A18)&" / $"&FIXED(SUMIF(OPERACIONES!$C$6:$C$505,A18,OPERACIONES!$E$6:$E$505),0))
... V305: =IF(A305="","",SUMIFS(CONFIG!$F$5:$F$26,CONFIG!$D$5:$D$26,"Tipo de persona",CONFIG!$E$5:$E$26,C305)+SUMIFS(CONFIG!$F$5:$F$26,CONFIG!$D$5:$D$26,"Residencia",CONFIG!$E$5:$E$26,E305)+SUMIFS(CONFIG!$F$5:$F$26,CONFIG!$D$5:$D$26,"Nacionalidad",CONFIG!$E$5:$E$26,F305)+SUMIFS(CONFIG!$F$5:$F$26,CONFIG!$D$5:$D$26,"Jurisdicción de riesgo",CONFIG!$E$5:$E$26,G305)+SUMIFS(CONFIG!$F$5:$F$26,CONFIG!$D$5:$D$26,"PEP",CONFIG!$E$5:$E$26,H305)+SUMIFS(CONFIG!$F$5:$F$26,CONFIG!$D$5:$D$26,"En listas",CONFIG!$E$5:$E$26,I305)+SUMIFS(CONFIG!$F$5:$F$26,CONFIG!$D$5:$D$26,"Riesgo de su actividad económica",CONFIG!$E$5:$E$26,J305)+SUMIFS(CONFIG!$F$5:$F$26,CONFIG!$D$5:$D$26,"Canal",CONFIG!$E$5:$E$26,K305)+SUMIFS(CONFIG!$F$5:$F$26,CONFIG!$D$5:$D$26,"Origen de recursos documentado",CONFIG!$E$5:$E$26,L305)) | W305: =IF(A305="","",IF(SUMIF(OPERACIONES!$C$6:$C$505,A305,OPERACIONES!$E$6:$E$505)>0,IF(SUMIF(OPERACIONES!$C$6:$C$505,A305,OPERACIONES!$F$6:$F$505)/SUMIF(OPERACIONES!$C$6:$C$505,A305,OPERACIONES!$E$6:$E$505)>0.5,CONFIG!$B$20,IF(SUMIF(OPERACIONES!$C$6:$C$505,A305,OPERACIONES!$F$6:$F$505)>0,CONFIG!$B$21,0)),0)+IF(COUNTIFS(OPERACIONES!$C$6:$C$505,A305,OPERACIONES!$AQ$6:$AQ$505,1)>0,CONFIG!$B$22,0)+IF(COUNTIFS(OPERACIONES!$C$6:$C$505,A305,OPERACIONES!$H$6:$H$505,"Sí")>0,CONFIG!$B$23,0)) | X305: =IF(A305="","",V305+W305) | Y305: =IF(A305="","",IF(X305<=CONFIG!$B$13,"Bajo",IF(X305<=CONFIG!$B$14,"Medio","Alto"))) | Z305: =IF(A305="","",IF(OR(H305="Extranjera",AND(E305="No residente",G305="Sí"),I305="Sí"),"Alto",IF(T305<>"",T305,Y305))) | AA305: =IF(A305="","",IF(H305="Extranjera","Alto obligatorio: PEP extranjera (RCG 23 Bis 4)",IF(AND(E305="No residente",G305="Sí"),"Alto obligatorio: no residente vinculado a jurisdicción de riesgo (RCG 23 Bis 4)",IF(I305="Sí","Alto por criterio: persona en listas. Evalúa no operar y Aviso de 24 h",IF(T305<>"","Ajuste del REC: "&U305,"Modelo: "&X305&" puntos"))))) | AB305: =IF(A305="","",IF(COUNT(N305,O305)=0,"Falta fecha",EDATE(MAX(N305,O305),IF(Z305="Alto",CONFIG!$B$18,IF(Z305="Medio",CONFIG!$B$17,CONFIG!$B$16))))) | AC305: =IF(A305="","",IF(ISNUMBER(S305),EDATE(S305,12),IF(ISNUMBER(N305),EDATE(N305,12),"Falta fecha"))) | AD305: =IF(A305="","",MID(IF(P305<>"Sí"," · Expediente incompleto","")&IF(OR(Q305="",Q305="Pendiente")," · Falta el Beneficiario Controlador","")&IF(M305=""," · Sin perfil transaccional","")&IF(AND(ISNUMBER(AB305),AB305<CONFIG!$B$6)," · Evaluación de riesgo vencida","")&IF(AND(ISNUMBER(AC305),AC305<CONFIG!$B$6)," · Verificación anual vencida","")&IF(AND(ISNUMBER(R305),ISNUMBER(S305),S305-R305>92)," · Comprobante de domicilio con más de 3 meses","")&IF(AND(T305<>"",U305="")," · Ajuste del REC sin justificación",""),4,400)) | AE305: =IF(A305="","",IF(AD305="","Al día","Revisar")) | AF305: =IF(A305="","",COUNTIF(OPERACIONES!$C$6:$C$505,A305)&" / $"&FIXED(SUMIF(OPERACIONES!$C$6:$C$505,A305,OPERACIONES!$E$6:$E$505),0))

Sheet AVISOS_24H
A1: AVISOS_24H — Registro de sospechas, hechos o indicios e intentos
A2: Ley 18 fr. VI y RCG 26 Bis a 26 Bis 2: el Aviso va dentro de las 24 horas siguientes, aunque la operación no alcance el monto o no se haya concretado, si hay datos para identificar a quien la intentó. El envío arranca seis meses después de que se publique el formato oficial (Trans. Quinto): mientras, este registro es tu evidencia.
A5: Folio | B5: Fecha y hora en que lo detectaste | C5: Persona o cliente | D5: ID cliente (si existe) | E5: Tipo de Aviso | F5: ¿Se concretó la operación? | G5: ¿Tienes datos para identificarla? | H5: Qué pasó (hechos, montos, por qué es inusual) | I5: Límite (24 h) | J5: Estatus | K5: Fecha y hora de envío | L5: Semáforo
A6: =IF(B6="","",ROW()-5) | I6: =IF(ISNUMBER(B6),B6+1,"") | L6: =IF(B6="","",IF(G6="No","Sin datos: documenta y analiza",IF(J6="Presentado",IF(AND(ISNUMBER(K6),K6>I6),"Presentado fuera de plazo","Presentado"),IF(J6="Descartado con análisis","Descartado",IF(J6="Registro interno (formato pendiente)","Registro interno",IF(NOW()>I6,"VENCIDO","Faltan "&ROUND((I6-NOW())*24,0)&" horas"))))))
A7: =IF(B7="","",ROW()-5) | I7: =IF(ISNUMBER(B7),B7+1,"") | L7: =IF(B7="","",IF(G7="No","Sin datos: documenta y analiza",IF(J7="Presentado",IF(AND(ISNUMBER(K7),K7>I7),"Presentado fuera de plazo","Presentado"),IF(J7="Descartado con análisis","Descartado",IF(J7="Registro interno (formato pendiente)","Registro interno",IF(NOW()>I7,"VENCIDO","Faltan "&ROUND((I7-NOW())*24,0)&" horas"))))))
A8: =IF(B8="","",ROW()-5) | I8: =IF(ISNUMBER(B8),B8+1,"") | L8: =IF(B8="","",IF(G8="No","Sin datos: documenta y analiza",IF(J8="Presentado",IF(AND(ISNUMBER(K8),K8>I8),"Presentado fuera de plazo","Presentado"),IF(J8="Descartado con análisis","Descartado",IF(J8="Registro interno (formato pendiente)","Registro interno",IF(NOW()>I8,"VENCIDO","Faltan "&ROUND((I8-NOW())*24,0)&" horas"))))))
A9: =IF(B9="","",ROW()-5) | I9: =IF(ISNUMBER(B9),B9+1,"") | L9: =IF(B9="","",IF(G9="No","Sin datos: documenta y analiza",IF(J9="Presentado",IF(AND(ISNUMBER(K9),K9>I9),"Presentado fuera de plazo","Presentado"),IF(J9="Descartado con análisis","Descartado",IF(J9="Registro interno (formato pendiente)","Registro interno",IF(NOW()>I9,"VENCIDO","Faltan "&ROUND((I9-NOW())*24,0)&" horas"))))))
A10: =IF(B10="","",ROW()-5) | I10: =IF(ISNUMBER(B10),B10+1,"") | L10: =IF(B10="","",IF(G10="No","Sin datos: documenta y analiza",IF(J10="Presentado",IF(AND(ISNUMBER(K10),K10>I10),"Presentado fuera de plazo","Presentado"),IF(J10="Descartado con análisis","Descartado",IF(J10="Registro interno (formato pendiente)","Registro interno",IF(NOW()>I10,"VENCIDO","Faltan "&ROUND((I10-NOW())*24,0)&" horas"))))))
A11: =IF(B11="","",ROW()-5) | I11: =IF(ISNUMBER(B11),B11+1,"") | L11: =IF(B11="","",IF(G11="No","Sin datos: documenta y analiza",IF(J11="Presentado",IF(AND(ISNUMBER(K11),K11>I11),"Presentado fuera de plazo","Presentado"),IF(J11="Descartado con análisis","Descartado",IF(J11="Registro interno (formato pendiente)","Registro interno",IF(NOW()>I11,"VENCIDO","Faltan "&ROUND((I11-NOW())*24,0)&" horas"))))))
A12: =IF(B12="","",ROW()-5) | I12: =IF(ISNUMBER(B12),B12+1,"") | L12: =IF(B12="","",IF(G12="No","Sin datos: documenta y analiza",IF(J12="Presentado",IF(AND(ISNUMBER(K12),K12>I12),"Presentado fuera de plazo","Presentado"),IF(J12="Descartado con análisis","Descartado",IF(J12="Registro interno (formato pendiente)","Registro interno",IF(NOW()>I12,"VENCIDO","Faltan "&ROUND((I12-NOW())*24,0)&" horas"))))))
A13: =IF(B13="","",ROW()-5) | I13: =IF(ISNUMBER(B13),B13+1,"") | L13: =IF(B13="","",IF(G13="No","Sin datos: documenta y analiza",IF(J13="Presentado",IF(AND(ISNUMBER(K13),K13>I13),"Presentado fuera de plazo","Presentado"),IF(J13="Descartado con análisis","Descartado",IF(J13="Registro interno (formato pendiente)","Registro interno",IF(NOW()>I13,"VENCIDO","Faltan "&ROUND((I13-NOW())*24,0)&" horas"))))))
A14: =IF(B14="","",ROW()-5) | I14: =IF(ISNUMBER(B14),B14+1,"") | L14: =IF(B14="","",IF(G14="No","Sin datos: documenta y analiza",IF(J14="Presentado",IF(AND(ISNUMBER(K14),K14>I14),"Presentado fuera de plazo","Presentado"),IF(J14="Descartado con análisis","Descartado",IF(J14="Registro interno (formato pendiente)","Registro interno",IF(NOW()>I14,"VENCIDO","Faltan "&ROUND((I14-NOW())*24,0)&" horas"))))))
A15: =IF(B15="","",ROW()-5) | I15: =IF(ISNUMBER(B15),B15+1,"") | L15: =IF(B15="","",IF(G15="No","Sin datos: documenta y analiza",IF(J15="Presentado",IF(AND(ISNUMBER(K15),K15>I15),"Presentado fuera de plazo","Presentado"),IF(J15="Descartado con análisis","Descartado",IF(J15="Registro interno (formato pendiente)","Registro interno",IF(NOW()>I15,"VENCIDO","Faltan "&ROUND((I15-NOW())*24,0)&" horas"))))))
A16: =IF(B16="","",ROW()-5) | I16: =IF(ISNUMBER(B16),B16+1,"") | L16: =IF(B16="","",IF(G16="No","Sin datos: documenta y analiza",IF(J16="Presentado",IF(AND(ISNUMBER(K16),K16>I16),"Presentado fuera de plazo","Presentado"),IF(J16="Descartado con análisis","Descartado",IF(J16="Registro interno (formato pendiente)","Registro interno",IF(NOW()>I16,"VENCIDO","Faltan "&ROUND((I16-NOW())*24,0)&" horas"))))))
A17: =IF(B17="","",ROW()-5) | I17: =IF(ISNUMBER(B17),B17+1,"") | L17: =IF(B17="","",IF(G17="No","Sin datos: documenta y analiza",IF(J17="Presentado",IF(AND(ISNUMBER(K17),K17>I17),"Presentado fuera de plazo","Presentado"),IF(J17="Descartado con análisis","Descartado",IF(J17="Registro interno (formato pendiente)","Registro interno",IF(NOW()>I17,"VENCIDO","Faltan "&ROUND((I17-NOW())*24,0)&" horas"))))))
... A105: =IF(B105="","",ROW()-5) | I105: =IF(ISNUMBER(B105),B105+1,"") | L105: =IF(B105="","",IF(G105="No","Sin datos: documenta y analiza",IF(J105="Presentado",IF(AND(ISNUMBER(K105),K105>I105),"Presentado fuera de plazo","Presentado"),IF(J105="Descartado con análisis","Descartado",IF(J105="Registro interno (formato pendiente)","Registro interno",IF(NOW()>I105,"VENCIDO","Faltan "&ROUND((I105-NOW())*24,0)&" horas"))))))

Sheet CALENDARIO
A1: CALENDARIO — Avisos mensuales e informe en ceros
A2: Ley art. 23: los Avisos se presentan a más tardar el día 17 del mes siguiente. RCG 25: si en el mes no hubo operaciones objeto de Aviso, se presenta un informe (en ceros). El año se cambia en CONFIG!B10. Captura en amarillo cuando lo presentes.
A5: Mes | B5: Inicio | C5: Operaciones | D5: Avisos que se generan | E5: Avisos presentados | F5: Avisos pendientes | G5: Avisos de 24 h registrados | H5: ¿Informe en ceros? | I5: Fecha límite | J5: Estatus del mes (lo capturas) | K5: Semáforo
A6: Enero | B6: =DATE(CONFIG!$B$10,1,1) -> 46023 | C6: =COUNTIFS(OPERACIONES!$B$6:$B$505,">="&B6,OPERACIONES!$B$6:$B$505,"<"&EDATE(B6,1)) -> 0 | D6: =COUNTIFS(OPERACIONES!$B$6:$B$505,">="&B6,OPERACIONES!$B$6:$B$505,"<"&EDATE(B6,1),OPERACIONES!$P$6:$P$505,"AVISO*") -> 0 | E6: =COUNTIFS(OPERACIONES!$B$6:$B$505,">="&B6,OPERACIONES!$B$6:$B$505,"<"&EDATE(B6,1),OPERACIONES!$P$6:$P$505,"AVISO*",OPERACIONES!$T$6:$T$505,"Presentado") -> 0 | F6: =D6-E6 -> 0 | G6: =COUNTIFS(AVISOS_24H!$B$6:$B$105,">="&B6,AVISOS_24H!$B$6:$B$105,"<"&EDATE(B6,1)) -> 0 | H6: =IF(D6=0,"Sí (RCG 25)","No: presentar Avisos") -> Sí (RCG 25) | I6: =DATE(CONFIG!$B$10,2,17) -> 46070 | K6: =IF(AND(ISNUMBER(CONFIG!$B$11),EDATE(B6,1)<=DATE(YEAR(CONFIG!$B$11),MONTH(CONFIG!$B$11),1)),"Antes del inicio",IF(IF(D6>0,F6=0,J6="Presentado"),"Cumplido",IF(CONFIG!$B$6>I6,"VENCIDO",IF(CONFIG!$B$6>=B6,"En curso","Próximo")))) -> VENCIDO
A7: Febrero | B7: =DATE(CONFIG!$B$10,2,1) -> 46054 | C7: =COUNTIFS(OPERACIONES!$B$6:$B$505,">="&B7,OPERACIONES!$B$6:$B$505,"<"&EDATE(B7,1)) -> 0 | D7: =COUNTIFS(OPERACIONES!$B$6:$B$505,">="&B7,OPERACIONES!$B$6:$B$505,"<"&EDATE(B7,1),OPERACIONES!$P$6:$P$505,"AVISO*") -> 0 | E7: =COUNTIFS(OPERACIONES!$B$6:$B$505,">="&B7,OPERACIONES!$B$6:$B$505,"<"&EDATE(B7,1),OPERACIONES!$P$6:$P$505,"AVISO*",OPERACIONES!$T$6:$T$505,"Presentado") -> 0 | F7: =D7-E7 -> 0 | G7: =COUNTIFS(AVISOS_24H!$B$6:$B$105,">="&B7,AVISOS_24H!$B$6:$B$105,"<"&EDATE(B7,1)) -> 0 | H7: =IF(D7=0,"Sí (RCG 25)","No: presentar Avisos") -> Sí (RCG 25) | I7: =DATE(CONFIG!$B$10,3,17) -> 46098 | K7: =IF(AND(ISNUMBER(CONFIG!$B$11),EDATE(B7,1)<=DATE(YEAR(CONFIG!$B$11),MONTH(CONFIG!$B$11),1)),"Antes del inicio",IF(IF(D7>0,F7=0,J7="Presentado"),"Cumplido",IF(CONFIG!$B$6>I7,"VENCIDO",IF(CONFIG!$B$6>=B7,"En curso","Próximo")))) -> VENCIDO
A8: Marzo | B8: =DATE(CONFIG!$B$10,3,1) -> 46082 | C8: =COUNTIFS(OPERACIONES!$B$6:$B$505,">="&B8,OPERACIONES!$B$6:$B$505,"<"&EDATE(B8,1)) -> 1 | D8: =COUNTIFS(OPERACIONES!$B$6:$B$505,">="&B8,OPERACIONES!$B$6:$B$505,"<"&EDATE(B8,1),OPERACIONES!$P$6:$P$505,"AVISO*") -> 0 | E8: =COUNTIFS(OPERACIONES!$B$6:$B$505,">="&B8,OPERACIONES!$B$6:$B$505,"<"&EDATE(B8,1),OPERACIONES!$P$6:$P$505,"AVISO*",OPERACIONES!$T$6:$T$505,"Presentado") -> 0 | F8: =D8-E8 -> 0 | G8: =COUNTIFS(AVISOS_24H!$B$6:$B$105,">="&B8,AVISOS_24H!$B$6:$B$105,"<"&EDATE(B8,1)) -> 0 | H8: =IF(D8=0,"Sí (RCG 25)","No: presentar Avisos") -> Sí (RCG 25) | I8: =DATE(CONFIG!$B$10,4,17) -> 46129 | K8: =IF(AND(ISNUMBER(CONFIG!$B$11),EDATE(B8,1)<=DATE(YEAR(CONFIG!$B$11),MONTH(CONFIG!$B$11),1)),"Antes del inicio",IF(IF(D8>0,F8=0,J8="Presentado"),"Cumplido",IF(CONFIG!$B$6>I8,"VENCIDO",IF(CONFIG!$B$6>=B8,"En curso","Próximo")))) -> VENCIDO
A9: Abril | B9: =DATE(CONFIG!$B$10,4,1) -> 46113 | C9: =COUNTIFS(OPERACIONES!$B$6:$B$505,">="&B9,OPERACIONES!$B$6:$B$505,"<"&EDATE(B9,1)) -> 0 | D9: =COUNTIFS(OPERACIONES!$B$6:$B$505,">="&B9,OPERACIONES!$B$6:$B$505,"<"&EDATE(B9,1),OPERACIONES!$P$6:$P$505,"AVISO*") -> 0 | E9: =COUNTIFS(OPERACIONES!$B$6:$B$505,">="&B9,OPERACIONES!$B$6:$B$505,"<"&EDATE(B9,1),OPERACIONES!$P$6:$P$505,"AVISO*",OPERACIONES!$T$6:$T$505,"Presentado") -> 0 | F9: =D9-E9 -> 0 | G9: =COUNTIFS(AVISOS_24H!$B$6:$B$105,">="&B9,AVISOS_24H!$B$6:$B$105,"<"&EDATE(B9,1)) -> 0 | H9: =IF(D9=0,"Sí (RCG 25)","No: presentar Avisos") -> Sí (RCG 25) | I9: =DATE(CONFIG!$B$10,5,17) -> 46159 | K9: =IF(AND(ISNUMBER(CONFIG!$B$11),EDATE(B9,1)<=DATE(YEAR(CONFIG!$B$11),MONTH(CONFIG!$B$11),1)),"Antes del inicio",IF(IF(D9>0,F9=0,J9="Presentado"),"Cumplido",IF(CONFIG!$B$6>I9,"VENCIDO",IF(CONFIG!$B$6>=B9,"En curso","Próximo")))) -> VENCIDO
A10: Mayo | B10: =DATE(CONFIG!$B$10,5,1) -> 46143 | C10: =COUNTIFS(OPERACIONES!$B$6:$B$505,">="&B10,OPERACIONES!$B$6:$B$505,"<"&EDATE(B10,1)) -> 0 | D10: =COUNTIFS(OPERACIONES!$B$6:$B$505,">="&B10,OPERACIONES!$B$6:$B$505,"<"&EDATE(B10,1),OPERACIONES!$P$6:$P$505,"AVISO*") -> 0 | E10: =COUNTIFS(OPERACIONES!$B$6:$B$505,">="&B10,OPERACIONES!$B$6:$B$505,"<"&EDATE(B10,1),OPERACIONES!$P$6:$P$505,"AVISO*",OPERACIONES!$T$6:$T$505,"Presentado") -> 0 | F10: =D10-E10 -> 0 | G10: =COUNTIFS(AVISOS_24H!$B$6:$B$105,">="&B10,AVISOS_24H!$B$6:$B$105,"<"&EDATE(B10,1)) -> 0 | H10: =IF(D10=0,"Sí (RCG 25)","No: presentar Avisos") -> Sí (RCG 25) | I10: =DATE(CONFIG!$B$10,6,17) -> 46190 | K10: =IF(AND(ISNUMBER(CONFIG!$B$11),EDATE(B10,1)<=DATE(YEAR(CONFIG!$B$11),MONTH(CONFIG!$B$11),1)),"Antes del inicio",IF(IF(D10>0,F10=0,J10="Presentado"),"Cumplido",IF(CONFIG!$B$6>I10,"VENCIDO",IF(CONFIG!$B$6>=B10,"En curso","Próximo")))) -> VENCIDO
A11: Junio | B11: =DATE(CONFIG!$B$10,6,1) -> 46174 | C11: =COUNTIFS(OPERACIONES!$B$6:$B$505,">="&B11,OPERACIONES!$B$6:$B$505,"<"&EDATE(B11,1)) -> 0 | D11: =COUNTIFS(OPERACIONES!$B$6:$B$505,">="&B11,OPERACIONES!$B$6:$B$505,"<"&EDATE(B11,1),OPERACIONES!$P$6:$P$505,"AVISO*") -> 0 | E11: =COUNTIFS(OPERACIONES!$B$6:$B$505,">="&B11,OPERACIONES!$B$6:$B$505,"<"&EDATE(B11,1),OPERACIONES!$P$6:$P$505,"AVISO*",OPERACIONES!$T$6:$T$505,"Presentado") -> 0 | F11: =D11-E11 -> 0 | G11: =COUNTIFS(AVISOS_24H!$B$6:$B$105,">="&B11,AVISOS_24H!$B$6:$B$105,"<"&EDATE(B11,1)) -> 0 | H11: =IF(D11=0,"Sí (RCG 25)","No: presentar Avisos") -> Sí (RCG 25) | I11: =DATE(CONFIG!$B$10,7,17) -> 46220 | K11: =IF(AND(ISNUMBER(CONFIG!$B$11),EDATE(B11,1)<=DATE(YEAR(CONFIG!$B$11),MONTH(CONFIG!$B$11),1)),"Antes del inicio",IF(IF(D11>0,F11=0,J11="Presentado"),"Cumplido",IF(CONFIG!$B$6>I11,"VENCIDO",IF(CONFIG!$B$6>=B11,"En curso","Próximo")))) -> VENCIDO
A12: Julio | B12: =DATE(CONFIG!$B$10,7,1) -> 46204 | C12: =COUNTIFS(OPERACIONES!$B$6:$B$505,">="&B12,OPERACIONES!$B$6:$B$505,"<"&EDATE(B12,1)) -> 0 | D12: =COUNTIFS(OPERACIONES!$B$6:$B$505,">="&B12,OPERACIONES!$B$6:$B$505,"<"&EDATE(B12,1),OPERACIONES!$P$6:$P$505,"AVISO*") -> 0 | E12: =COUNTIFS(OPERACIONES!$B$6:$B$505,">="&B12,OPERACIONES!$B$6:$B$505,"<"&EDATE(B12,1),OPERACIONES!$P$6:$P$505,"AVISO*",OPERACIONES!$T$6:$T$505,"Presentado") -> 0 | F12: =D12-E12 -> 0 | G12: =COUNTIFS(AVISOS_24H!$B$6:$B$105,">="&B12,AVISOS_24H!$B$6:$B$105,"<"&EDATE(B12,1)) -> 0 | H12: =IF(D12=0,"Sí (RCG 25)","No: presentar Avisos") -> Sí (RCG 25) | I12: =DATE(CONFIG!$B$10,8,17) -> 46251 | K12: =IF(AND(ISNUMBER(CONFIG!$B$11),EDATE(B12,1)<=DATE(YEAR(CONFIG!$B$11),MONTH(CONFIG!$B$11),1)),"Antes del inicio",IF(IF(D12>0,F12=0,J12="Presentado"),"Cumplido",IF(CONFIG!$B$6>I12,"VENCIDO",IF(CONFIG!$B$6>=B12,"En curso","Próximo")))) -> VENCIDO
A13: Agosto | B13: =DATE(CONFIG!$B$10,8,1) -> 46235 | C13: =COUNTIFS(OPERACIONES!$B$6:$B$505,">="&B13,OPERACIONES!$B$6:$B$505,"<"&EDATE(B13,1)) -> 0 | D13: =COUNTIFS(OPERACIONES!$B$6:$B$505,">="&B13,OPERACIONES!$B$6:$B$505,"<"&EDATE(B13,1),OPERACIONES!$P$6:$P$505,"AVISO*") -> 0 | E13: =COUNTIFS(OPERACIONES!$B$6:$B$505,">="&B13,OPERACIONES!$B$6:$B$505,"<"&EDATE(B13,1),OPERACIONES!$P$6:$P$505,"AVISO*",OPERACIONES!$T$6:$T$505,"Presentado") -> 0 | F13: =D13-E13 -> 0 | G13: =COUNTIFS(AVISOS_24H!$B$6:$B$105,">="&B13,AVISOS_24H!$B$6:$B$105,"<"&EDATE(B13,1)) -> 0 | H13: =IF(D13=0,"Sí (RCG 25)","No: presentar Avisos") -> Sí (RCG 25) | I13: =DATE(CONFIG!$B$10,9,17) -> 46282 | K13: =IF(AND(ISNUMBER(CONFIG!$B$11),EDATE(B13,1)<=DATE(YEAR(CONFIG!$B$11),MONTH(CONFIG!$B$11),1)),"Antes del inicio",IF(IF(D13>0,F13=0,J13="Presentado"),"Cumplido",IF(CONFIG!$B$6>I13,"VENCIDO",IF(CONFIG!$B$6>=B13,"En curso","Próximo")))) -> VENCIDO
A14: Septiembre | B14: =DATE(CONFIG!$B$10,9,1) -> 46266 | C14: =COUNTIFS(OPERACIONES!$B$6:$B$505,">="&B14,OPERACIONES!$B$6:$B$505,"<"&EDATE(B14,1)) -> 0 | D14: =COUNTIFS(OPERACIONES!$B$6:$B$505,">="&B14,OPERACIONES!$B$6:$B$505,"<"&EDATE(B14,1),OPERACIONES!$P$6:$P$505,"AVISO*") -> 0 | E14: =COUNTIFS(OPERACIONES!$B$6:$B$505,">="&B14,OPERACIONES!$B$6:$B$505,"<"&EDATE(B14,1),OPERACIONES!$P$6:$P$505,"AVISO*",OPERACIONES!$T$6:$T$505,"Presentado") -> 0 | F14: =D14-E14 -> 0 | G14: =COUNTIFS(AVISOS_24H!$B$6:$B$105,">="&B14,AVISOS_24H!$B$6:$B$105,"<"&EDATE(B14,1)) -> 0 | H14: =IF(D14=0,"Sí (RCG 25)","No: presentar Avisos") -> Sí (RCG 25) | I14: =DATE(CONFIG!$B$10,10,17) -> 46312 | K14: =IF(AND(ISNUMBER(CONFIG!$B$11),EDATE(B14,1)<=DATE(YEAR(CONFIG!$B$11),MONTH(CONFIG!$B$11),1)),"Antes del inicio",IF(IF(D14>0,F14=0,J14="Presentado"),"Cumplido",IF(CONFIG!$B$6>I14,"VENCIDO",IF(CONFIG!$B$6>=B14,"En curso","Próximo")))) -> En curso
A15: Octubre | B15: =DATE(CONFIG!$B$10,10,1) -> 46296 | C15: =COUNTIFS(OPERACIONES!$B$6:$B$505,">="&B15,OPERACIONES!$B$6:$B$505,"<"&EDATE(B15,1)) -> 0 | D15: =COUNTIFS(OPERACIONES!$B$6:$B$505,">="&B15,OPERACIONES!$B$6:$B$505,"<"&EDATE(B15,1),OPERACIONES!$P$6:$P$505,"AVISO*") -> 0 | E15: =COUNTIFS(OPERACIONES!$B$6:$B$505,">="&B15,OPERACIONES!$B$6:$B$505,"<"&EDATE(B15,1),OPERACIONES!$P$6:$P$505,"AVISO*",OPERACIONES!$T$6:$T$505,"Presentado") -> 0 | F15: =D15-E15 -> 0 | G15: =COUNTIFS(AVISOS_24H!$B$6:$B$105,">="&B15,AVISOS_24H!$B$6:$B$105,"<"&EDATE(B15,1)) -> 0 | H15: =IF(D15=0,"Sí (RCG 25)","No: presentar Avisos") -> Sí (RCG 25) | I15: =DATE(CONFIG!$B$10,11,17) -> 46343 | K15: =IF(AND(ISNUMBER(CONFIG!$B$11),EDATE(B15,1)<=DATE(YEAR(CONFIG!$B$11),MONTH(CONFIG!$B$11),1)),"Antes del inicio",IF(IF(D15>0,F15=0,J15="Presentado"),"Cumplido",IF(CONFIG!$B$6>I15,"VENCIDO",IF(CONFIG!$B$6>=B15,"En curso","Próximo")))) -> Próximo
A16: Noviembre | B16: =DATE(CONFIG!$B$10,11,1) -> 46327 | C16: =COUNTIFS(OPERACIONES!$B$6:$B$505,">="&B16,OPERACIONES!$B$6:$B$505,"<"&EDATE(B16,1)) -> 0 | D16: =COUNTIFS(OPERACIONES!$B$6:$B$505,">="&B16,OPERACIONES!$B$6:$B$505,"<"&EDATE(B16,1),OPERACIONES!$P$6:$P$505,"AVISO*") -> 0 | E16: =COUNTIFS(OPERACIONES!$B$6:$B$505,">="&B16,OPERACIONES!$B$6:$B$505,"<"&EDATE(B16,1),OPERACIONES!$P$6:$P$505,"AVISO*",OPERACIONES!$T$6:$T$505,"Presentado") -> 0 | F16: =D16-E16 -> 0 | G16: =COUNTIFS(AVISOS_24H!$B$6:$B$105,">="&B16,AVISOS_24H!$B$6:$B$105,"<"&EDATE(B16,1)) -> 0 | H16: =IF(D16=0,"Sí (RCG 25)","No: presentar Avisos") -> Sí (RCG 25) | I16: =DATE(CONFIG!$B$10,12,17) -> 46373 | K16: =IF(AND(ISNUMBER(CONFIG!$B$11),EDATE(B16,1)<=DATE(YEAR(CONFIG!$B$11),MONTH(CONFIG!$B$11),1)),"Antes del inicio",IF(IF(D16>0,F16=0,J16="Presentado"),"Cumplido",IF(CONFIG!$B$6>I16,"VENCIDO",IF(CONFIG!$B$6>=B16,"En curso","Próximo")))) -> Próximo
A17: Diciembre | B17: =DATE(CONFIG!$B$10,12,1) -> 46357 | C17: =COUNTIFS(OPERACIONES!$B$6:$B$505,">="&B17,OPERACIONES!$B$6:$B$505,"<"&EDATE(B17,1)) -> 0 | D17: =COUNTIFS(OPERACIONES!$B$6:$B$505,">="&B17,OPERACIONES!$B$6:$B$505,"<"&EDATE(B17,1),OPERACIONES!$P$6:$P$505,"AVISO*") -> 0 | E17: =COUNTIFS(OPERACIONES!$B$6:$B$505,">="&B17,OPERACIONES!$B$6:$B$505,"<"&EDATE(B17,1),OPERACIONES!$P$6:$P$505,"AVISO*",OPERACIONES!$T$6:$T$505,"Presentado") -> 0 | F17: =D17-E17 -> 0 | G17: =COUNTIFS(AVISOS_24H!$B$6:$B$105,">="&B17,AVISOS_24H!$B$6:$B$105,"<"&EDATE(B17,1)) -> 0 | H17: =IF(D17=0,"Sí (RCG 25)","No: presentar Avisos") -> Sí (RCG 25) | I17: =DATE(CONFIG!$B$10,13,17) -> 46404 | K17: =IF(AND(ISNUMBER(CONFIG!$B$11),EDATE(B17,1)<=DATE(YEAR(CONFIG!$B$11),MONTH(CONFIG!$B$11),1)),"Antes del inicio",IF(IF(D17>0,F17=0,J17="Presentado"),"Cumplido",IF(CONFIG!$B$6>I17,"VENCIDO",IF(CONFIG!$B$6>=B17,"En curso","Próximo")))) -> Próximo
A19: Nota: los Avisos de comercio exterior (fr. XIV) se cumplen con el pedimento (R 16) y no se cuentan aquí. Si capturas en CONFIG el mes en que empezaste a usar la consola, los meses anteriores salen como "Antes del inicio". El semáforo marca "Cumplido" cuando todos los Avisos del mes están presentados (hoja OPERACIONES) o, si no hubo Avisos, cuando capturas "Presentado" para el informe en ceros. La fecha límite del informe en ceros se toma igual a la de los Avisos (día 17): criterio del libro.

Sheet CONSULTA
A1: CONSULTA — ¿Esta operación me obliga?
A2: Respuesta rápida para una operación suelta, antes de registrarla. No acumula: para eso está OPERACIONES.
A4: Actividad | B4: VIII - Distribución/comercialización vehículos
A5: Monto SIN IVA ni accesorios | B5: 400000
A6: Pagado en efectivo (CON IVA y accesorios) | B6: 0
A8: Fracción | B8: =IFERROR(INDEX(CATÁLOGO!$A$5:$A$39,MATCH($B$4,CATÁLOGO!$C$5:$C$39,0)),"") -> VIII
A9: Umbral de identificación | B9: =IFERROR(IF(ISNUMBER(INDEX(CATÁLOGO!$H$5:$H$39,MATCH($B$4,CATÁLOGO!$C$5:$C$39,0))),INDEX(CATÁLOGO!$H$5:$H$39,MATCH($B$4,CATÁLOGO!$C$5:$C$39,0)),INDEX(CATÁLOGO!$E$5:$E$39,MATCH($B$4,CATÁLOGO!$C$5:$C$39,0))),"") -> 376565.1
A10: Umbral de Aviso | B10: =IFERROR(IF(ISNUMBER(INDEX(CATÁLOGO!$I$5:$I$39,MATCH($B$4,CATÁLOGO!$C$5:$C$39,0))),INDEX(CATÁLOGO!$I$5:$I$39,MATCH($B$4,CATÁLOGO!$C$5:$C$39,0)),INDEX(CATÁLOGO!$F$5:$F$39,MATCH($B$4,CATÁLOGO!$C$5:$C$39,0))),"") -> 753130.2
A11: Límite de efectivo (Art. 32) | B11: =IFERROR(IF(ISNUMBER(INDEX(CATÁLOGO!$J$5:$J$39,MATCH($B$4,CATÁLOGO!$C$5:$C$39,0))),INDEX(CATÁLOGO!$J$5:$J$39,MATCH($B$4,CATÁLOGO!$C$5:$C$39,0)),"No aplica"),"") -> 376565.1
A12: ¿Identificar? | B12: =IF(B9="Siempre","SÍ (siempre)",IF(ISNUMBER(B9),IF(B5>=B9,"SÍ","No"),"")) -> SÍ
A13: ¿Aviso por esta operación sola? | B13: =IF(B10="Siempre","SÍ (siempre)",IF(B10="No aplica","No: sólo hay Aviso si ejecutas la operación en nombre del cliente",IF(ISNUMBER(B10),IF(B5>=B10,IF(LEFT(B8,3)="XIV","SÍ, vía pedimento (R 16)","SÍ"),"No, pero revisa la acumulación"),""))) -> No, pero revisa la acumulación
A14: ¿Acumula? | B14: =IFERROR(IF(INDEX(CATÁLOGO!$D$5:$D$39,MATCH($B$4,CATÁLOGO!$C$5:$C$39,0))="ACUMULA","Sí: regístrala en OPERACIONES para ver si con otras alcanza el umbral","No: se evalúa sola (RCG 19)"),"") -> Sí: regístrala en OPERACIONES para ver si con otras alcanza el umbral
A15: ¿Puedo recibir ese efectivo? | B15: =IF(OR(B6="",B6=0),"",IF(ISNUMBER(B11),IF(B6>=B11,"NO: prohibido por el Art. 32","Sí, dentro del límite"),"No hay límite del Art. 32 para esta actividad"))
A16: Riesgo ALTO en esta actividad cuando… | B16: =IFERROR(INDEX(CATÁLOGO!$L$5:$L$39,MATCH($B$4,CATÁLOGO!$C$5:$C$39,0)),"") -> Venta de vehículos de lujo o coleccionables, pagos en efectivo, operaciones múltiples en corto plazo.
A17: Riesgo MEDIO cuando… | B17: =IFERROR(INDEX(CATÁLOGO!$M$5:$M$39,MATCH($B$4,CATÁLOGO!$C$5:$C$39,0)),"") -> Venta de vehículos de gama media con esquemas de financiamiento parcial.
A18: Riesgo BAJO cuando… | B18: =IFERROR(INDEX(CATÁLOGO!$N$5:$N$39,MATCH($B$4,CATÁLOGO!$C$5:$C$39,0)),"") -> Venta de vehículos económicos a través de agencias con pagos bancarios y crédito formal.
A19: Evento típico de lavado | B19: =IFERROR(INDEX(CATÁLOGO!$O$5:$O$39,MATCH($B$4,CATÁLOGO!$C$5:$C$39,0)),"") -> Adquisición de vehículos para ocultar origen ilícito de fondos.
A21: Esta consulta usa la UMA vigente a la fecha de corte. Juegos (fr. I): varias operaciones del mismo cliente que sumen 325 UMA en 24 horas también obligan a identificar (R 21 Bis): regístralas en OPERACIONES. Si algo te huele mal, el Aviso de 24 horas procede sin importar el monto (hoja AVISOS_24H).

Sheet OBLIGACIONES
A1: OBLIGACIONES — Lo que piden las RCG 2026 y desde cuándo
A2: Checklist del Acuerdo 115/2026 (DOF 7-ago-2026). Captura estatus, responsable y evidencia. La columna F cuenta los días contra la fecha de CONFIG.
A3: Avance: | B3: =IFERROR(COUNTIF(G6:G19,"Listo")/COUNTA(B6:B19),0) -> 0
A5: # | B5: Obligación | C5: Qué te piden | D5: Fundamento | E5: Exigible desde | F5: ¿Cuánto falta? | G5: Estatus | H5: Responsable | I5: Evidencia / notas
A6: 1 | B6: Entrada en vigor de las RCG | C6: Rige el Acuerdo 115/2026, salvo las excepciones de sus transitorios. | D6: RCG Trans. Primero | E6: 46356 | F6: =IF(E6-CONFIG!$B$6<=0,"Ya exigible",E6-CONFIG!$B$6&" días") -> 70 días | G6: Pendiente
A7: 2 | B7: Dueño real en personas morales y fideicomisos: identificar, no sólo recabar la declaración | C7: Ya no basta la constancia de lo que declaró el cliente: hay que identificar al Beneficiario Controlador. En persona física sigue la declaración. | D7: L 3 fr. III; RCG 12 fr. VII y Anexos 4, 6 y 8; Trans. Primero | E7: 46356 | F7: =IF(E7-CONFIG!$B$6<=0,"Ya exigible",E7-CONFIG!$B$6&" días") -> 70 días | G7: Pendiente
A8: 3 | B8: Evaluación de riesgo del negocio (metodología) | C8: Metodología escrita con datos de al menos 12 meses (clientes, operaciones y monto); cuatro elementos: actos u operaciones, tipo de clientes, países y áreas geográficas, transacciones y canales; doble ponderación; Mitigantes y su efectiva aplicación; indicadores de CPF 139 Quáter y 400 Bis por elemento. A disposición con datos del año anterior. | D8: L 18 fr. VII; RCG 10 Septies a 10 Septies 6; Trans. Segundo | E8: 46447 | F8: =IF(E8-CONFIG!$B$6<=0,"Ya exigible",E8-CONFIG!$B$6&" días") -> 161 días | G8: Pendiente
A9: 4 | B9: Manual de Políticas Internas con la metodología | C9: Catorce contenidos mínimos, incluida la metodología de riesgo y los criterios de apertura, limitación o terminación de relaciones. | D9: L 18 fr. VIII; RCG 37 y 37 Bis; Trans. Tercero | E9: 46447 | F9: =IF(E9-CONFIG!$B$6<=0,"Ya exigible",E9-CONFIG!$B$6&" días") -> 161 días | G9: Pendiente
A10: 5 | B10: Grado de Riesgo de cada cliente | C10: Al menos tres grados (bajo, medio, alto); grado inicial y reevaluación cada 6 meses; PEP extranjeras y no residentes ligados a jurisdicciones de riesgo = alto. | D10: RCG 23 Bis a 23 Bis 4; Trans. Cuarto | E10: 46447 | F10: =IF(E10-CONFIG!$B$6<=0,"Ya exigible",E10-CONFIG!$B$6&" días") -> 161 días | G10: Pendiente
A11: 6 | B11: Conocimiento del cliente y perfil transaccional | C11: Política basada en el grado de riesgo; perfil (monto, frecuencia, origen y destino); evaluación semestral; sistema de alertas. | D11: RCG 23 Ter a 23 Ter 2; Trans. Cuarto | E11: 46447 | F11: =IF(E11-CONFIG!$B$6<=0,"Ya exigible",E11-CONFIG!$B$6&" días") -> 161 días | G11: Pendiente
A12: 7 | B12: Debida diligencia reforzada | C12: Riesgo alto: más información, monitoreo estricto, cuestionario de origen y destino, datos de cónyuge, dependientes o accionistas. PEP + riesgo alto: aprobación de un directivo. | D12: RCG 23 Ter 3, 23 Ter 4 y 23 Ter 5; Trans. Cuarto | E12: 46447 | F12: =IF(E12-CONFIG!$B$6<=0,"Ya exigible",E12-CONFIG!$B$6&" días") -> 161 días | G12: Pendiente
A13: 8 | B13: Beneficiario Controlador: orden de prelación | C13: 1) 25% o más del capital; 2) control por otros medios; 3) alta dirección. Fideicomisos: control efectivo, subiendo por la cadena. Identificación previa a la operación. | D13: RCG 23 Quinquies a 23 Quinquies 3; Trans. Cuarto | E13: 46447 | F13: =IF(E13-CONFIG!$B$6<=0,"Ya exigible",E13-CONFIG!$B$6&" días") -> 161 días | G13: Pendiente
A14: 9 | B14: Selección de personal | C14: Procedimientos de selección y declaración firmada de cada empleado nuevo. | D14: L 18 fr. IX; RCG 39 Bis 2; Trans. Sexto | E14: 46447 | F14: =IF(E14-CONFIG!$B$6<=0,"Ya exigible",E14-CONFIG!$B$6&" días") -> 161 días | G14: Pendiente
A15: 10 | B15: Capacitación anual | C15: Al menos una vez al año, con temas coherentes con la evaluación de riesgo, evaluación y constancia; instructor con 5 años de experiencia; evidencia 10 años. Primer periodo: 1-ene al 31-dic-2027. | D15: L 18 fr. IX; RCG 39 Bis y 39 Bis 1; Trans. Séptimo | E15: 46388 | F15: =IF(E15-CONFIG!$B$6<=0,"Ya exigible",E15-CONFIG!$B$6&" días") -> 102 días | G15: Pendiente
A16: 11 | B16: Mecanismos automatizados | C16: Expediente, base consolidada y acumulación, información para la metodología, modelo de grado de riesgo con histórico 10 años, alertas (alto riesgo, PEP, listas, jurisdicciones), monitoreo de efectivo. | D16: L 18 fr. X; RCG 41; Trans. Noveno | E16: 46539 | F16: =IF(E16-CONFIG!$B$6<=0,"Ya exigible",E16-CONFIG!$B$6&" días") -> 253 días | G16: Pendiente
A17: 12 | B17: Consulta PEP 2.0 | C17: Consulta de PEP nacionales en la aplicación de la UIF con e.firma. | D17: RCG 23 Quáter 1; Trans. Décimo (9 meses después del 30-nov-2026) | E17: 46629 | F17: =IF(E17-CONFIG!$B$6<=0,"Ya exigible",E17-CONFIG!$B$6&" días") -> 343 días | G17: Pendiente
A18: 13 | B18: Auditoría anual de efectividad | C18: Riesgo bajo o medio: auditoría o control interno independiente; riesgo alto (o por elección): auditor externo certificado por la UIF. Primer periodo auditado: 2028; dictamen a más tardar el último día hábil de marzo de 2029. | D18: L 18 fr. XI; RCG 42 a 50; Trans. Octavo | E18: 46753 | F18: =IF(E18-CONFIG!$B$6<=0,"Ya exigible",E18-CONFIG!$B$6&" días") -> 467 días | G18: Pendiente
A19: 14 | B19: Avisos de 24 horas (sospecha, hechos o indicios) | C19: Dentro de 24 horas, aunque no se alcance el monto o no se concrete la operación, si hay datos para identificar a quien la intentó. Mientras sale el formato: registro interno. | D19: L 18 fr. VI; R 7 Bis; RCG 26 Bis a 26 Bis 2; Trans. Quinto | E19: Formato pendiente | F19: 6 meses después del formato | G19: Pendiente
A21: La fecha de la Consulta PEP 2.0 es un cómputo (nueve meses desde el 30-nov-2026): verifica la que publique la autoridad.

Sheet ALERTAS
A1: ALERTAS — Catálogo de 393 indicadores por actividad
A2: Consulta: filtra por actividad o nivel de riesgo para saber qué vigilar. La clasificación Alto/Medio/Bajo es una propuesta analítica que el REC debe calibrar.
A4: Actividad | B4: Clave | C4: Indicador de alerta | D4: Tipo | E4: Elemento | F4: ¿Cómo se detecta? | G4: Nivel de riesgo | H4: Patrón | I4: Recurrencia
A5: I. Juegos y Sorteos | B5: 2108 | C5: El cliente o usuario realiza la compra de crédito o fichas en efectivo y solicita el reintegro por medio de un cheque o transferencia. | D5: Uso de efectivo | E5: Transacciones | F5: Sistema automatizado | G5: Medio | H5: Colocación de efectivo | I5: 23
A6: I. Juegos y Sorteos | B6: 2112 | C6: El cliente o usuario solicita que el pago de un premio o fichas sea realizado por medio de una combinación de efectivo, cheques o transferencias. | D6: Uso de efectivo | E6: Transacciones | F6: Sistema automatizado | G6: Medio | H6: Colocación de efectivo | I6: 23
A7: I. Juegos y Sorteos | B7: 2121 | C7: El cliente o usuario insiste en liquidar o pagar la operación en efectivo rebasando el umbral permitido en la Ley. | D7: Uso de efectivo | E7: Transacciones | F7: Sistema automatizado | G7: Medio | H7: Colocación de efectivo | I7: 23
A8: II.1 Tarjetas Cred o Serv | B8: 2202 | C8: El cliente recurrentemente realiza el pago del saldo de la tarjeta en efectivo por cantidades elevadas por medio de canales no bancarios. | D8: Uso de efectivo | E8: Transacciones | F8: Sistema automatizado | G8: Medio | H8: Colocación de efectivo | I8: 23
A9: II.1 Tarjetas Cred o Serv | B9: 2205 | C9: El cliente realiza una compra por un valor significativamente elevado, pagando en la fecha de corte dicha operación en efectivo. | D9: Uso de efectivo | E9: Transacciones | F9: Sistema automatizado | G9: Medio | H9: Colocación de efectivo | I9: 23
A10: II.2 Tarjetas Prep | B10: 2302 | C10: El cliente o usuario realiza la operación de carga o recarga por montos elevados liquidando en efectivo | D10: Uso de efectivo | E10: Transacciones | F10: Sistema automatizado | G10: Medio | H10: Colocación de efectivo | I10: 23
A11: II.3 Tarjetas Dev y Rwd | B11: 3707 | C11: El cliente o usuario realiza una o más compras por un valor significativamente elevado sin lógica aparente, con el objeto de retirar efectivo con las recompensas ganadas. | D11: Uso de efectivo | E11: Transacciones | F11: Sistema automatizado | G11: Medio | H11: Colocación de efectivo | I11: 23
A12: III. Ch. Viajero | B12: 302 | C12: El cliente o usuario realiza la operación de compra o venta de cheques de viajero por monto elevados llevando a cabo su liquidando en efectivo | D12: Uso de efectivo | E12: Transacciones | F12: Sistema automatizado | G12: Medio | H12: Colocación de efectivo | I12: 23
A13: IV. Mutuo y Crédito | B13: 2806 | C13: El cliente o usuario realiza operaciones de manera periódica en las que se liquida el total del monto del préstamo otorgado en efectivo al poco tiempo de haberlo adquirido. | D13: Uso de efectivo | E13: Transacciones | F13: Sistema automatizado | G13: Medio | H13: Colocación de efectivo | I13: 23
A14: IX. Blindaje | B14: 2611 | C14: El cliente o usuario insiste en liquidar o pagar la operación en efectivo rebasando el umbral permitido en la Ley. | D14: Uso de efectivo | E14: Transacciones | F14: Sistema automatizado | G14: Medio | H14: Colocación de efectivo | I14: 23
A15: V. Des Inmobiliario | B15: 3911 | C15: La(s) persona(s) que participa(n) en la operación insiste(n) en realizar sus aportaciones en efectivo por montos elevados. | D15: Uso de efectivo | E15: Transacciones | F15: Sistema automatizado | G15: Medio | H15: Colocación de efectivo | I15: 23
A16: V. Inmuebles | B16: 3114 | C16: El cliente insiste en liquidar o pagar la operación en efectivo rebasando el umbral permitido en la Ley. | D16: Uso de efectivo | E16: Transacciones | F16: Sistema automatizado | G16: Medio | H16: Colocación de efectivo | I16: 23
... A397: XVI. Activos Virtuales | B397: 4112 | C397: El cliente envía o recibe recursos de una cuenta en algún país de alto riesgo. | D397: Transferencias internacionales | E397: Transacciones | F397: Sistema automatizado | G397: Alto | H397: Flujo transfronterizo | I397: 18

Sheet CATÁLOGO
A1: CATÁLOGO — Actividades Vulnerables, umbrales, conversión a pesos y características de riesgo
A2: Fuente única de umbrales del libro (Ley art. 17, art. 32 y RCG 19). Los pesos se calculan con la UMA de CONFIG. Las listas usan la etiqueta "Fracción - Actividad" de la matriz EBR de la sesión 2, y las características, el evento típico, la causa y la consecuencia vienen de esa misma matriz. No se captura nada aquí.
A4: Fr. | B4: Actividad | C4: Actividad (la que eliges en las listas) | D4: Acumulación (RCG 19) | E4: Identificación (UMA) | F4: Aviso (UMA) | G4: Límite efectivo Art. 32 (UMA) | H4: Identificación ($) | I4: Aviso ($) | J4: Límite efectivo ($) | K4: Notas | L4: Características de riesgo ALTO | M4: Características de riesgo MEDIO | N4: Características de riesgo BAJO | O4: Evento típico | P4: Causa | Q4: Consecuencia
A5: I | B5: Juegos con apuesta | C5: I - Juegos con apuesta | D5: ACUMULA | E5: 325 | F5: 645 | G5: 3210 | H5: =IF(ISNUMBER(E5),E5*CONFIG!$B$4,E5) -> 38125.75 | I5: =IF(ISNUMBER(F5),F5*CONFIG!$B$4,F5) -> 75664.95 | J5: =IF(ISNUMBER(G5),G5*CONFIG!$B$4,G5) -> 376565.1 | L5: Apuestas en efectivo de alto monto, clientes no frecuentes o extranjeros, apuestas en línea sin trazabilidad clara. | M5: Apuestas mixtas (efectivo y transferencia), montos moderados, clientes recurrentes. | N5: Apuestas con tarjeta bancaria o monederos electrónicos, montos bajos y clientes identificables. | O5: Introducción de efectivo ilícito en casinos o plataformas. | P5: Uso intensivo de efectivo, dispersión de apuestas. | Q5: Integración de dinero ilícito, multas (arts. 53 a 55) y revocación del permiso (art. 56).
A6: II | B6: Tarjetas de crédito o servicios | C6: II - Tarjetas de crédito o servicios | D6: ACUMULA | E6: 805 | F6: 1285 | G6: No aplica | H6: =IF(ISNUMBER(E6),E6*CONFIG!$B$4,E6) -> 94434.55 | I6: =IF(ISNUMBER(F6),F6*CONFIG!$B$4,F6) -> 150743.35 | J6: =IF(ISNUMBER(G6),G6*CONFIG!$B$4,G6) -> No aplica | L6: Uso de tarjetas emitidas en el extranjero o con líneas de crédito inusualmente altas. | M6: Tarjetas nacionales con uso mixto (efectivo/transferencias) y movimientos atípicos. | N6: Tarjetas nacionales de clientes con historial crediticio claro y montos habituales. | O6: Uso de tarjetas para dispersar fondos ilícitos o triangular pagos. | P6: Montos elevados sin justificación económica. | Q6: Detección por la UIF y multas (arts. 53 a 55).
A7: II | B7: Tarjetas prepagadas y monederos electrónicos | C7: II - Tarjetas prepagadas y monederos electrónicos | D7: NO ACUMULA | E7: 645 | F7: 645 | G7: No aplica | H7: =IF(ISNUMBER(E7),E7*CONFIG!$B$4,E7) -> 75664.95 | I7: =IF(ISNUMBER(F7),F7*CONFIG!$B$4,F7) -> 75664.95 | J7: =IF(ISNUMBER(G7),G7*CONFIG!$B$4,G7) -> No aplica | L7: Tarjetas recargables en efectivo de alto monto, adquiridas de forma masiva. | M7: Tarjetas con recargas mixtas (efectivo y transferencia), uso en varios comercios. | N7: Tarjetas con recarga en cuenta bancaria, límites bajos y trazables. | O7: Uso de monederos para dispersión y anonimato en transacciones. | P7: Bajo nivel de identificación en productos masivos. | Q7: Riesgo de operaciones estructuradas y financiamiento ilícito.
A8: III | B8: Cheques de viajero | C8: III - Cheques de viajero | D8: ACUMULA | E8: Siempre | F8: 645 | G8: No aplica | H8: =IF(ISNUMBER(E8),E8*CONFIG!$B$4,E8) -> Siempre | I8: =IF(ISNUMBER(F8),F8*CONFIG!$B$4,F8) -> 75664.95 | J8: =IF(ISNUMBER(G8),G8*CONFIG!$B$4,G8) -> No aplica | L8: Emisión o adquisición en efectivo, altos montos, operaciones internacionales. | M8: Cheques adquiridos con mezcla de efectivo y transferencias, uso ocasional. | N8: Cheques adquiridos con transferencias desde cuentas bancarias de clientes identificados. | O8: Introducción de recursos ilícitos vía instrumentos internacionales. | P8: Facilidad de portabilidad y canje en múltiples países. | Q8: Riesgo transfronterizo y multas (arts. 53 a 55).
A9: IV | B9: Préstamos o créditos | C9: IV - Préstamos o créditos | D9: ACUMULA | E9: Siempre | F9: 1605 | G9: No aplica | H9: =IF(ISNUMBER(E9),E9*CONFIG!$B$4,E9) -> Siempre | I9: =IF(ISNUMBER(F9),F9*CONFIG!$B$4,F9) -> 188282.55 | J9: =IF(ISNUMBER(G9),G9*CONFIG!$B$4,G9) -> No aplica | L9: Créditos en efectivo, sin garantía real, de monto elevado o a corto plazo, susceptibles de ser liquidados anticipadamente. | M9: Créditos personales o comerciales de mediano plazo, con garantía parcial o con pagos mixtos (efectivo y transferencia). | N9: Créditos hipotecarios, automotrices o empresariales con garantías reales, pagos periódicos y trazables vía sistema financiero. | O9: Uso del crédito para inyectar recursos ilícitos y justificar flujos financieros. | P9: Flexibilidad de los productos de crédito, posibilidad de pagos en efectivo. | Q9: Riesgo de introducir fondos ilícitos disfrazados de financiamiento.
A10: V | B10: Construcción/comercialización inmuebles | C10: V - Construcción/comercialización inmuebles | D10: ACUMULA | E10: Siempre | F10: 8025 | G10: 8025 | H10: =IF(ISNUMBER(E10),E10*CONFIG!$B$4,E10) -> Siempre | I10: =IF(ISNUMBER(F10),F10*CONFIG!$B$4,F10) -> 941412.75 | J10: =IF(ISNUMBER(G10),G10*CONFIG!$B$4,G10) -> 941412.75 | L10: Venta de inmuebles de lujo o múltiples operaciones en preventa con pagos en efectivo. | M10: Venta de inmuebles de valor medio con esquema de pagos mixtos (efectivo + transferencias). | N10: Venta de inmuebles de interés social o vivienda regulada con créditos hipotecarios bancarios. | O10: Uso de operaciones inmobiliarias para introducir o estratificar fondos ilícitos. | P10: Altos montos y posibilidad de pagos fragmentados. | Q10: Riesgo de sobrevaluación, lavado de activos y sanciones.
A11: V Bis | B11: Recepción recursos desarrollo inmobiliario | C11: V Bis - Recepción recursos desarrollo inmobiliario | D11: ACUMULA | E11: Siempre | F11: 8025 | G11: No aplica | H11: =IF(ISNUMBER(E11),E11*CONFIG!$B$4,E11) -> Siempre | I11: =IF(ISNUMBER(F11),F11*CONFIG!$B$4,F11) -> 941412.75 | J11: =IF(ISNUMBER(G11),G11*CONFIG!$B$4,G11) -> No aplica | K11: NUEVA AV (Ley, DOF 16-jul-2025). Art. 17 Fr. V Bis. | L11: Recepción de aportaciones en efectivo o de múltiples inversionistas no identificados. | M11: Recursos mixtos (transferencias + efectivo) en proyectos medianos. | N11: Recursos canalizados vía instituciones financieras con trazabilidad plena y contratos formalizados. | O11: Canalización de recursos ilícitos a proyectos inmobiliarios. | P11: Participación de múltiples inversionistas, dificultad en verificar origen de fondos. | Q11: Riesgo de cooptación de proyectos para blanqueo de capitales.
A12: VI | B12: Piedras y metales preciosos, joyas | C12: VI - Piedras y metales preciosos, joyas | D12: ACUMULA | E12: 805 | F12: 1605 | G12: 3210 | H12: =IF(ISNUMBER(E12),E12*CONFIG!$B$4,E12) -> 94434.55 | I12: =IF(ISNUMBER(F12),F12*CONFIG!$B$4,F12) -> 188282.55 | J12: =IF(ISNUMBER(G12),G12*CONFIG!$B$4,G12) -> 376565.1 | K12: Ya NO se limita a efectivo. | L12: Operaciones en efectivo, piezas de alto valor unitario, transacciones frecuentes en mercados informales. | M12: Operaciones con combinación de pagos (efectivo + transferencia), piezas de valor medio, ventas a consignación. | N12: Ventas con factura a través de establecimientos formales, pagos vía sistema bancario. | O12: Uso de joyas, metales y piedras para mover y ocultar valor ilícito. | P12: Portabilidad, alta liquidez y difícil trazabilidad de estos bienes. | Q12: Riesgo de blanqueo transfronterizo y sanciones.
A13: VII | B13: Subasta/comercialización obras de arte | C13: VII - Subasta/comercialización obras de arte | D13: ACUMULA | E13: 2410 | F13: 4815 | G13: 3210 | H13: =IF(ISNUMBER(E13),E13*CONFIG!$B$4,E13) -> 282717.1 | I13: =IF(ISNUMBER(F13),F13*CONFIG!$B$4,F13) -> 564847.65 | J13: =IF(ISNUMBER(G13),G13*CONFIG!$B$4,G13) -> 376565.1 | L13: Obras de alto valor, subastas internacionales, piezas sin trazabilidad de propiedad. | M13: Obras de valor intermedio, galerías locales, pagos mixtos. | N13: Venta de arte contemporáneo o decorativo de bajo valor con facturación completa. | O13: Uso del arte para justificar incrementos patrimoniales o transferencias internacionales. | P13: Valor subjetivo y dificultad en tasación de obras. | Q13: Riesgo de sobrevaluación, subdeclaración y financiamiento ilícito.
A14: VIII | B14: Distribución/comercialización vehículos | C14: VIII - Distribución/comercialización vehículos | D14: ACUMULA | E14: 3210 | F14: 6420 | G14: 3210 | H14: =IF(ISNUMBER(E14),E14*CONFIG!$B$4,E14) -> 376565.1 | I14: =IF(ISNUMBER(F14),F14*CONFIG!$B$4,F14) -> 753130.2 | J14: =IF(ISNUMBER(G14),G14*CONFIG!$B$4,G14) -> 376565.1 | L14: Venta de vehículos de lujo o coleccionables, pagos en efectivo, operaciones múltiples en corto plazo. | M14: Venta de vehículos de gama media con esquemas de financiamiento parcial. | N14: Venta de vehículos económicos a través de agencias con pagos bancarios y crédito formal. | O14: Adquisición de vehículos para ocultar origen ilícito de fondos. | P14: Alto valor de los bienes y posibilidad de liquidación en efectivo. | Q14: Riesgo de acumulación patrimonial ilícita y decomiso.
A15: IX | B15: Servicios de blindaje | C15: IX - Servicios de blindaje | D15: ACUMULA | E15: 2410 | F15: 4815 | G15: 3210 | H15: =IF(ISNUMBER(E15),E15*CONFIG!$B$4,E15) -> 282717.1 | I15: =IF(ISNUMBER(F15),F15*CONFIG!$B$4,F15) -> 564847.65 | J15: =IF(ISNUMBER(G15),G15*CONFIG!$B$4,G15) -> 376565.1 | L15: Blindaje de vehículos de lujo y bienes inmuebles con pagos en efectivo. | M15: Blindaje de vehículos medianos con pagos mixtos. | N15: Blindaje contratado por empresas reguladas con pagos vía sistema financiero. | O15: Blindaje usado para protección de recursos ilícitos. | P15: Alta demanda de efectivo y bienes de alto valor. | Q15: Vínculo con delincuencia organizada, multas y revocación del permiso (art. 56).
A16: X | B16: Transporte y custodia de valores | C16: X - Transporte y custodia de valores | D16: ACUMULA | E16: Siempre | F16: 3210 | G16: No aplica | H16: =IF(ISNUMBER(E16),E16*CONFIG!$B$4,E16) -> Siempre | I16: =IF(ISNUMBER(F16),F16*CONFIG!$B$4,F16) -> 376565.1 | J16: =IF(ISNUMBER(G16),G16*CONFIG!$B$4,G16) -> No aplica | K16: Si no se puede determinar el monto: Aviso siempre. | L16: Custodia o traslado de valores en efectivo de alto volumen o bienes de alto valor | M16: Custodia de valores mixtos (efectivo y documentos) | N16: Custodia de valores financieros documentados (títulos, cheques, transferencias) | O16: Movilización de efectivo ilícito. | P16: Dificultad de control en traslado físico. | Q16: Multas, revocación del permiso (art. 56) y decomiso en la vía penal.
A17: XI | B17: Servicios Profesionales | C17: XI - Servicios profesionales: prepara la operación | D17: NO ACUMULA | E17: Siempre | F17: No aplica | G17: No aplica | H17: =IF(ISNUMBER(E17),E17*CONFIG!$B$4,E17) -> Siempre | I17: =IF(ISNUMBER(F17),F17*CONFIG!$B$4,F17) -> No aplica | J17: =IF(ISNUMBER(G17),G17*CONFIG!$B$4,G17) -> No aplica | K17: Identificas siempre. Si sólo preparas la operación, no hay Aviso (Ley 17 XI). | L17: Servicios que implican estructuración patrimonial o fiscal compleja | M17: Servicios especializados de valor intermedio (contratos mercantiles, trámites específicos) | N17: Servicios rutinarios o administrativos (contabilidad básica, asesoría legal común) | O17: Profesionales usados para dar apariencia de legalidad. | P17: Posibilidad de diseñar esquemas opacos. | Q17: Corresponsabilidad legal.
A18: XI | B18: Servicios Profesionales | C18: XI - Servicios profesionales: la ejecuta en nombre y representación | D18: NO ACUMULA | E18: Siempre | F18: Siempre | G18: No aplica | H18: =IF(ISNUMBER(E18),E18*CONFIG!$B$4,E18) -> Siempre | I18: =IF(ISNUMBER(F18),F18*CONFIG!$B$4,F18) -> Siempre | J18: =IF(ISNUMBER(G18),G18*CONFIG!$B$4,G18) -> No aplica | K18: Aviso cuando realizas, en nombre y representación del cliente, una operación financiera relacionada (Ley 17 XI, último párrafo). | L18: Servicios que implican estructuración patrimonial o fiscal compleja | M18: Servicios especializados de valor intermedio (contratos mercantiles, trámites específicos) | N18: Servicios rutinarios o administrativos (contabilidad básica, asesoría legal común) | O18: Profesionales usados para dar apariencia de legalidad. | P18: Posibilidad de diseñar esquemas opacos. | Q18: Corresponsabilidad legal.
A19: XII | B19: NOTARIOS: Transmisión de inmuebles | C19: XII - NOTARIOS: Transmisión de inmuebles | D19: ACUMULA | E19: Siempre | F19: 8000 | G19: 8025 | H19: =IF(ISNUMBER(E19),E19*CONFIG!$B$4,E19) -> Siempre | I19: =IF(ISNUMBER(F19),F19*CONFIG!$B$4,F19) -> 938480 | J19: =IF(ISNUMBER(G19),G19*CONFIG!$B$4,G19) -> 941412.75 | K19: Aviso 8,000 UMA (Ley 17 XII A). Ojo: el límite de efectivo del Art. 32 es 8,025 UMA, y el notario identifica la forma de pago desde ese monto (art. 33). | L19: Transmisión de inmuebles de alto valor | M19: Transmisiones de inmuebles de valor intermedio | N19: Transmisiones de inmuebles de bajo valor o vivienda social | O19: Uso de escrituras para legitimar recursos ilícitos. | P19: Alto valor de operaciones notariales. | Q19: Multas y procedimiento ante la autoridad que supervisa la fe pública por notorias deficiencias (art. 58).
A20: XII | B20: NOTARIOS: Poderes irrevocables | C20: XII - NOTARIOS: Poderes irrevocables | D20: NO ACUMULA | E20: Siempre | F20: Siempre | G20: No aplica | H20: =IF(ISNUMBER(E20),E20*CONFIG!$B$4,E20) -> Siempre | I20: =IF(ISNUMBER(F20),F20*CONFIG!$B$4,F20) -> Siempre | J20: =IF(ISNUMBER(G20),G20*CONFIG!$B$4,G20) -> No aplica | L20: Poderes generales con facultades amplias y sin limitación temporal | M20: Poderes especiales de gestión con vigencia determinada | N20: Poderes notariales limitados a actos concretos y de valor reducido | O20: Uso de poderes para ocultar beneficiario final. | P20: Amplio acceso a actos jurídicos sin límite económico. | Q20: Riesgo de facilitar control ilícito de activos.
A21: XII | B21: NOTARIOS: Const. o modif. patrimonial | C21: XII - NOTARIOS: Const. o modif. patrimonial | D21: ACUMULA | E21: Siempre | F21: Siempre | G21: 3210 | H21: =IF(ISNUMBER(E21),E21*CONFIG!$B$4,E21) -> Siempre | I21: =IF(ISNUMBER(F21),F21*CONFIG!$B$4,F21) -> Siempre | J21: =IF(ISNUMBER(G21),G21*CONFIG!$B$4,G21) -> 376565.1 | K21: Aviso SIEMPRE (Ley 17 XII A inciso c). Corregido sep-2026. | L21: Constitución de sociedades patrimoniales con aportaciones significativas | M21: Modificación parcial de sociedades con capital intermedio | N21: Ajustes patrimoniales menores y documentados | O21: Uso de sociedades para canalizar fondos ilícitos. | P21: Flexibilidad de estructuras societarias. | Q21: Riesgo de sobrevaluación y evasión.
A22: XII | B22: NOTARIOS: Const. o modif. fideicomisos | C22: XII - NOTARIOS: Const. o modif. fideicomisos | D22: ACUMULA | E22: Siempre | F22: 4000 | G22: No aplica | H22: =IF(ISNUMBER(E22),E22*CONFIG!$B$4,E22) -> Siempre | I22: =IF(ISNUMBER(F22),F22*CONFIG!$B$4,F22) -> 469240 | J22: =IF(ISNUMBER(G22),G22*CONFIG!$B$4,G22) -> No aplica | K22: Antes 8,025 → ahora 4,000 UMA. | L22: Fideicomisos de inversión de gran valor | M22: Fideicomisos de inversión o administración con montos intermedios | N22: Fideicomisos patrimoniales familiares con montos bajos | O22: Uso de fideicomisos para ocultar recursos ilícitos. | P22: Complejidad de instrumentos fiduciarios. | Q22: Riesgo de ocultar beneficiarios finales.
A23: XII | B23: NOTARIOS: Mutuo con no financiero | C23: XII - NOTARIOS: Mutuo con no financiero | D23: NO ACUMULA | E23: Siempre | F23: Siempre | G23: No aplica | H23: =IF(ISNUMBER(E23),E23*CONFIG!$B$4,E23) -> Siempre | I23: =IF(ISNUMBER(F23),F23*CONFIG!$B$4,F23) -> Siempre | J23: =IF(ISNUMBER(G23),G23*CONFIG!$B$4,G23) -> No aplica | L23: Mutuos de gran monto entre particulares | M23: Mutuos de valor intermedio | N23: Mutuos de bajo monto, formalizados y documentados | O23: Préstamos usados para circular recursos ilícitos. | P23: Flexibilidad del contrato civil. | Q23: Riesgo de simulación de operaciones.
A24: XII | B24: CORREDORES: Avalúos | C24: XII - CORREDORES: Avalúos | D24: NO ACUMULA | E24: 8025 | F24: 8025 | G24: No aplica | H24: =IF(ISNUMBER(E24),E24*CONFIG!$B$4,E24) -> 941412.75 | I24: =IF(ISNUMBER(F24),F24*CONFIG!$B$4,F24) -> 941412.75 | J24: =IF(ISNUMBER(G24),G24*CONFIG!$B$4,G24) -> No aplica | K24: No acumula: el RCG 19 excluye todo el Apartado B. | L24: Avalúos de bienes de alto valor | M24: Avalúos de bienes de valor intermedio | N24: Avalúos de bienes de bajo valor o de vivienda social | O24: Uso de avalúos para inflar patrimonio. | P24: Valoración subjetiva de bienes. | Q24: Justificación ilícita de activos, multas y cancelación de la habilitación por reincidencia (art. 57).
A25: XII | B25: CORREDORES: Const. o modif. patrimonial | C25: XII - CORREDORES: Const. o modif. patrimonial | D25: NO ACUMULA | E25: Siempre | F25: Siempre | G25: No aplica | H25: =IF(ISNUMBER(E25),E25*CONFIG!$B$4,E25) -> Siempre | I25: =IF(ISNUMBER(F25),F25*CONFIG!$B$4,F25) -> Siempre | J25: =IF(ISNUMBER(G25),G25*CONFIG!$B$4,G25) -> No aplica | L25: Constitución de sociedades patrimoniales de alto valor | M25: Modificaciones societarias de valor intermedio | N25: Ajustes menores en sociedades pequeñas | O25: Uso de sociedades mercantiles para blanquear recursos. | P25: Flexibilidad del marco mercantil. | Q25: Riesgo de opacidad en beneficiarios.
A26: XII | B26: CORREDORES: Modif. o cesión fideicomiso | C26: XII - CORREDORES: Modif. o cesión fideicomiso | D26: NO ACUMULA | E26: Siempre | F26: Siempre | G26: No aplica | H26: =IF(ISNUMBER(E26),E26*CONFIG!$B$4,E26) -> Siempre | I26: =IF(ISNUMBER(F26),F26*CONFIG!$B$4,F26) -> Siempre | J26: =IF(ISNUMBER(G26),G26*CONFIG!$B$4,G26) -> No aplica | L26: Cesión de derechos fiduciarios de alto valor | M26: Cesiones parciales de derechos de valor intermedio | N26: Cesiones de bajo valor o entre familiares | O26: Cesión usada para ocultar transferencia ilícita. | P26: Complejidad fiduciaria. | Q26: Riesgo de lavado mediante cesiones.
A27: XII | B27: CORREDORES: Mutuo mercantil | C27: XII - CORREDORES: Mutuo mercantil | D27: NO ACUMULA | E27: Siempre | F27: Siempre | G27: No aplica | H27: =IF(ISNUMBER(E27),E27*CONFIG!$B$4,E27) -> Siempre | I27: =IF(ISNUMBER(F27),F27*CONFIG!$B$4,F27) -> Siempre | J27: =IF(ISNUMBER(G27),G27*CONFIG!$B$4,G27) -> No aplica | L27: Mutuos mercantiles de alto valor | M27: Mutuos mercantiles de valor intermedio | N27: Mutuos mercantiles de bajo valor, documentados | O27: Simulación de préstamos para circular fondos ilícitos. | P27: Flexibilidad contractual. | Q27: Riesgo de simulación patrimonial.
A28: XII | B28: FACILITADORES: Solución de controversias | C28: XII - FACILITADORES: Transmisión de inmuebles | D28: ACUMULA | E28: Siempre | F28: 8000 | G28: 8025 | H28: =IF(ISNUMBER(E28),E28*CONFIG!$B$4,E28) -> Siempre | I28: =IF(ISNUMBER(F28),F28*CONFIG!$B$4,F28) -> 938480 | J28: =IF(ISNUMBER(G28),G28*CONFIG!$B$4,G28) -> 941412.75 | K28: Apartado D: mismos actos y umbrales que notarios (Apartado A). Inmuebles: Aviso 8,000 UMA. | L28: Soluciones de controversias internacionales de alto valor económico | M28: Controversias nacionales de valor intermedio | N28: Controversias de bajo valor económico | O28: Uso de servicios legales para legitimar flujos. | P28: Pago de honorarios difícil de trazar. | Q28: Riesgo de corresponsabilidad.
A29: XII | B29: Facilitadores | C29: XII - FACILITADORES: Poderes irrevocables | D29: ACUMULA | E29: Siempre | F29: Siempre | G29: No aplica | H29: =IF(ISNUMBER(E29),E29*CONFIG!$B$4,E29) -> Siempre | I29: =IF(ISNUMBER(F29),F29*CONFIG!$B$4,F29) -> Siempre | J29: =IF(ISNUMBER(G29),G29*CONFIG!$B$4,G29) -> No aplica | K29: Apartado D: remite al acto equivalente de notarios (Apartado A). | L29: Poderes generales con facultades amplias y sin limitación temporal | M29: Poderes especiales de gestión con vigencia determinada | N29: Poderes notariales limitados a actos concretos y de valor reducido | O29: Uso de poderes para ocultar beneficiario final. | P29: Amplio acceso a actos jurídicos sin límite económico. | Q29: Riesgo de facilitar control ilícito de activos.
A30: XII | B30: Facilitadores | C30: XII - FACILITADORES: Const. o modif. patrimonial | D30: ACUMULA | E30: Siempre | F30: Siempre | G30: 3210 | H30: =IF(ISNUMBER(E30),E30*CONFIG!$B$4,E30) -> Siempre | I30: =IF(ISNUMBER(F30),F30*CONFIG!$B$4,F30) -> Siempre | J30: =IF(ISNUMBER(G30),G30*CONFIG!$B$4,G30) -> 376565.1 | K30: Apartado D: remite al acto equivalente de notarios (Apartado A). | L30: Constitución de sociedades patrimoniales con aportaciones significativas | M30: Modificación parcial de sociedades con capital intermedio | N30: Ajustes patrimoniales menores y documentados | O30: Uso de sociedades para canalizar fondos ilícitos. | P30: Flexibilidad de estructuras societarias. | Q30: Riesgo de sobrevaluación y evasión.
A31: XII | B31: Facilitadores | C31: XII - FACILITADORES: Const. o modif. fideicomisos | D31: ACUMULA | E31: Siempre | F31: 4000 | G31: No aplica | H31: =IF(ISNUMBER(E31),E31*CONFIG!$B$4,E31) -> Siempre | I31: =IF(ISNUMBER(F31),F31*CONFIG!$B$4,F31) -> 469240 | J31: =IF(ISNUMBER(G31),G31*CONFIG!$B$4,G31) -> No aplica | K31: Apartado D: remite al acto equivalente de notarios (Apartado A). | L31: Fideicomisos de inversión de gran valor | M31: Fideicomisos de inversión o administración con montos intermedios | N31: Fideicomisos patrimoniales familiares con montos bajos | O31: Uso de fideicomisos para ocultar recursos ilícitos. | P31: Complejidad de instrumentos fiduciarios. | Q31: Riesgo de ocultar beneficiarios finales.
A32: XII | B32: Facilitadores | C32: XII - FACILITADORES: Mutuo con no financiero | D32: ACUMULA | E32: Siempre | F32: Siempre | G32: No aplica | H32: =IF(ISNUMBER(E32),E32*CONFIG!$B$4,E32) -> Siempre | I32: =IF(ISNUMBER(F32),F32*CONFIG!$B$4,F32) -> Siempre | J32: =IF(ISNUMBER(G32),G32*CONFIG!$B$4,G32) -> No aplica | K32: Apartado D: remite al acto equivalente de notarios (Apartado A). | L32: Mutuos de gran monto entre particulares | M32: Mutuos de valor intermedio | N32: Mutuos de bajo monto, formalizados y documentados | O32: Préstamos usados para circular recursos ilícitos. | P32: Flexibilidad del contrato civil. | Q32: Riesgo de simulación de operaciones.
A33: XIII | B33: Recepción de donativos | C33: XIII - Recepción de donativos | D33: ACUMULA | E33: 1605 | F33: 3210 | G33: No aplica | H33: =IF(ISNUMBER(E33),E33*CONFIG!$B$4,E33) -> 188282.55 | I33: =IF(ISNUMBER(F33),F33*CONFIG!$B$4,F33) -> 376565.1 | J33: =IF(ISNUMBER(G33),G33*CONFIG!$B$4,G33) -> No aplica | L33: Donativos de gran valor económico | M33: Donativos de valor intermedio | N33: Donativos de bajo valor, frecuentes en asociaciones pequeñas | O33: Uso de asociaciones para canalizar fondos ilícitos. | P33: Flexibilidad en recepción de recursos. | Q33: Riesgo de infiltración criminal.
A34: XIV | B34: CEXT: Joyas, metales, piedras preciosas | C34: XIV - CEXT: Joyas, metales, piedras preciosas | D34: NO ACUMULA | E34: 485 | F34: 485 | G34: No aplica | H34: =IF(ISNUMBER(E34),E34*CONFIG!$B$4,E34) -> 56895.35 | I34: =IF(ISNUMBER(F34),F34*CONFIG!$B$4,F34) -> 56895.35 | J34: =IF(ISNUMBER(G34),G34*CONFIG!$B$4,G34) -> No aplica | K34: No acumula: el RCG 19 no incluye la fr. XIV. El Aviso se cumple con el pedimento (R 16), no en el SPPLD. | L34: Transacciones internacionales de alto valor | M34: Operaciones nacionales de valor intermedio | N34: Operaciones nacionales de bajo valor con documentación | O34: Uso de comercio exterior para mover valor ilícito. | P34: Portabilidad y liquidez. | Q34: Contrabando, multas y cancelación de la autorización aduanal (art. 59).
A35: XIV | B35: CEXT: Obras de arte | C35: XIV - CEXT: Obras de arte | D35: NO ACUMULA | E35: 4815 | F35: 4815 | G35: No aplica | H35: =IF(ISNUMBER(E35),E35*CONFIG!$B$4,E35) -> 564847.65 | I35: =IF(ISNUMBER(F35),F35*CONFIG!$B$4,F35) -> 564847.65 | J35: =IF(ISNUMBER(G35),G35*CONFIG!$B$4,G35) -> No aplica | K35: No acumula: el RCG 19 no incluye la fr. XIV. El Aviso se cumple con el pedimento (R 16), no en el SPPLD. | L35: Subastas internacionales de alto valor | M35: Ventas nacionales de valor intermedio | N35: Obras de bajo valor con factura | O35: Uso de arte en comercio exterior para justificar flujos ilícitos. | P35: Valor subjetivo y mercado opaco. | Q35: Riesgo de sobre/subvaluación.
A36: XIV | B36: CEXT: Vehículos, máquinas, blindaje, etc. | C36: XIV - CEXT: Vehículos, máquinas, blindaje, etc. | D36: NO ACUMULA | E36: Siempre | F36: Siempre | G36: No aplica | H36: =IF(ISNUMBER(E36),E36*CONFIG!$B$4,E36) -> Siempre | I36: =IF(ISNUMBER(F36),F36*CONFIG!$B$4,F36) -> Siempre | J36: =IF(ISNUMBER(G36),G36*CONFIG!$B$4,G36) -> No aplica | K36: Nuevo: despacho sin agente aduanal. El Aviso se cumple con el pedimento (R 16), no en el SPPLD. | L36: Importación/exportación de bienes de lujo | M36: Comercialización de bienes de valor intermedio | N36: Bienes de uso común con documentación completa | O36: Comercio exterior usado para estratificación. | P36: Alto valor de mercancías. | Q36: Contrabando, multas y cancelación de la autorización aduanal (art. 59).
A37: XV | B37: Arrendamiento de bienes inmuebles (uso o goce) | C37: XV - Arrendamiento de bienes inmuebles (uso o goce) | D37: ACUMULA | E37: 1605 | F37: 3210 | G37: 3210 | H37: =IF(ISNUMBER(E37),E37*CONFIG!$B$4,E37) -> 188282.55 | I37: =IF(ISNUMBER(F37),F37*CONFIG!$B$4,F37) -> 376565.1 | J37: =IF(ISNUMBER(G37),G37*CONFIG!$B$4,G37) -> 376565.1 | L37: Arrendamiento de inmuebles de alto valor mensual, pagos en efectivo, arrendatarios de dificil identificacion o giro sensible. | M37: Arrendamiento de valor intermedio con pagos mixtos (efectivo y transferencia). | N37: Arrendamiento de bajo valor mensual, contrato formal y pagos trazables. | O37: Uso del arrendamiento como fachada o para introducir recursos ilicitos. | P37: Falta de verificacion del giro real del arrendatario y del origen de los pagos. | Q37: Riesgo legal y reputacional; local usado para actividades ilicitas.
A38: XVI | B38: Activos virtuales (PSAV): operación de intercambio/transferencia | C38: XVI - Activos virtuales (PSAV): operación de intercambio/transferencia | D38: ACUMULA | E38: Siempre | F38: 210 | G38: No aplica | H38: =IF(ISNUMBER(E38),E38*CONFIG!$B$4,E38) -> Siempre | I38: =IF(ISNUMBER(F38),F38*CONFIG!$B$4,F38) -> 24635.1 | J38: =IF(ISNUMBER(G38),G38*CONFIG!$B$4,G38) -> No aplica | K38: Umbrales más bajos del régimen. | L38: Intercambio/transferencia de activos virtuales con clientes no identificados, operaciones transfronterizas, montos elevados o anonimato on-chain. | M38: Operaciones con identificacion parcial y montos moderados. | N38: Operaciones con KYC completo, trazabilidad on-chain y montos bajos en MXN. | O38: Uso de activos virtuales para estratificar u ocultar el origen de recursos. | P38: Anonimato y dificultad de trazabilidad; operacion transfronteriza. | Q38: Riesgo de LD/FT, multas y detección por la UIF.
A39: XVI | B39: Activos virtuales (PSAV): cobro de contraprestación (comisión) por el servicio | C39: XVI - Activos virtuales (PSAV): cobro de contraprestación (comisión) por el servicio | D39: NO ACUMULA | E39: Siempre | F39: 4 | G39: No aplica | H39: =IF(ISNUMBER(E39),E39*CONFIG!$B$4,E39) -> Siempre | I39: =IF(ISNUMBER(F39),F39*CONFIG!$B$4,F39) -> 469.24 | J39: =IF(ISNUMBER(G39),G39*CONFIG!$B$4,G39) -> No aplica | K39: Cada comisión se compara sola contra 4 UMA: no se acumula (RCG 24 Bis 5). Si en la misma operación también hay Aviso por el inciso a), va un solo Aviso (R 31 Bis). | L39: Cobro de comisiones a clientes de alto riesgo o en efectivo, sin trazabilidad del pago. | M39: Comisiones con pagos mixtos e identificacion parcial. | N39: Comisiones cobradas por medios trazables con cliente identificado. | O39: Uso del cobro de comisiones para justificar flujos o fragmentar operaciones. | P39: Falta de trazabilidad en el cobro y bajo umbral de deteccion (4 UMA). | Q39: Riesgo de simulacion y de omitir operaciones sujetas a aviso.

Sheet CONFIG
A1: CONFIG — Parámetros del libro
A2: Lo único que se captura aquí: la UMA de cada año, los datos del sujeto obligado y, si quieres calibrarlo, el modelo de puntos del grado de riesgo del cliente. Todo lo amarillo es editable.
A3: GENERALES | D3: PUNTOS POR FACTOR (inherentes, RCG 23 Bis 2 fr. I) | H3: UMA POR AÑO
A4: UMA diaria vigente a la fecha de corte | B4: =IFERROR(INDEX($I$5:$I$14,MATCH(IF(MONTH(B6)=1,YEAR(B6)-1,YEAR(B6)),$H$5:$H$14,0)),0) -> 117.31 | D4: Factor | E4: Opción | F4: Puntos | H4: Año | I4: UMA diaria
A5: Fecha de corte (opcional) | D5: Tipo de persona | E5: Persona física | F5: 1 | H5: 2021 | I5: 89.62
A6: Fecha que usa el libro (HOY) | B6: =IF(ISNUMBER(B5),B5,TODAY()) -> 46286 | D6: Tipo de persona | E6: Persona moral | F6: 2 | H6: 2022 | I6: 96.22
A7: Sujeto obligado (nombre o razón social) | D7: Tipo de persona | E7: Fideicomiso | F7: 3 | H7: 2023 | I7: 103.74
A8: RFC | D8: Residencia | E8: Residente en México | F8: 0 | H8: 2024 | I8: 108.57
A9: Persona Representante Encargada de Cumplimiento | D9: Residencia | E9: No residente | F9: 2 | H9: 2025 | I9: 113.14
A10: Año del calendario de Avisos | B10: 2026 | D10: Nacionalidad | E10: Mexicana | F10: 0 | H10: 2026 | I10: 117.31
A11: Mes en que empezaste a usar la consola | D11: Nacionalidad | E11: Extranjera | F11: 1 | H11: 2027
A12: MODELO DE GRADO DE RIESGO DEL CLIENTE | D12: Jurisdicción de riesgo | E12: No | F12: 0 | H12: 2028
A13: Grado BAJO si el puntaje es menor o igual a | B13: 3 | D13: Jurisdicción de riesgo | E13: Sí | F13: 3 | H13: 2029
A14: Grado MEDIO si el puntaje es menor o igual a | B14: 7 | D14: PEP | E14: No | F14: 0 | H14: 2030
D15: PEP | E15: Nacional | F15: 3 | H15: Cada operación usa la UMA de su fecha: cambiar de año no altera los Avisos ya calculados. Captura la UMA nueva cada enero, cuando la publique el INEGI.
A16: Meses entre evaluaciones: grado BAJO | B16: 6 | D16: PEP | E16: Extranjera | F16: 5
A17: Meses entre evaluaciones: grado MEDIO | B17: 6 | D17: En listas | E17: No | F17: 0
A18: Meses entre evaluaciones: grado ALTO | B18: 3 | D18: En listas | E18: Sí | F18: 10
D19: Riesgo de su actividad económica | E19: Bajo | F19: 0
A20: Puntos: más del 50% del monto operado en efectivo | B20: 3 | D20: Riesgo de su actividad económica | E20: Medio | F20: 2
A21: Puntos: algún pago en efectivo (hasta 50%) | B21: 1 | D21: Riesgo de su actividad económica | E21: Alto | F21: 4
A22: Puntos: alguna operación excede el perfil declarado | B22: 2 | D22: Canal | E22: Presencial | F22: 0
A23: Puntos: alguna operación la paga un tercero | B23: 2 | D23: Canal | E23: No presencial | F23: 1
D24: Origen de recursos documentado | E24: Sí | F24: 0
D25: Origen de recursos documentado | E25: Parcial | F25: 2
D26: Origen de recursos documentado | E26: No | F26: 4
D28: Grado ALTO obligatorio, sin importar el puntaje: PEP extranjera, y no residente vinculado a jurisdicción de riesgo (RCG 23 Bis 4). Persona en listas: ALTO por criterio del libro.
